Workbook

Sheet DMC_NAVIGATION
A1: 🌐 DMC ERP MASTER WORKBOOK — NAVIGATION HUB
A2: Click any module below to navigate directly. All sheets have a 'Back to Home' button for quick return.
A4: 📋 SETUP & MASTER DATA
A5: Module | B5: Sheet Name | C5: Description | D5: Records | E5: Status
A6: ▶ | B6: TB_COA | C6: Chart of Accounts (Production) | D6: 45 accounts, Hierarchical, Production Ready | E6: ✅ Active | F6: Go →
A7: ▶ | B7: TB_CBE_Rates | C7: CBE Exchange Rates | D7: Daily FX rates, Source tracking | E7: ✅ Active | F7: Go →
A8: ▶ | B8: TB_Clients_Master | C8: Clients Master | D8: 10 clients, Credit limits, VAT reg | E8: ✅ Active | F8: Go →
A9: ▶ | B9: TB_Hotels_Master | C9: Hotels Master | D9: 10 hotels, Commission %, Contract rates | E9: ✅ Active | F9: Go →
A10: ▶ | B10: TB_Reps_Master | C10: Reps Master | D10: 8 reps, Float limits, Commission defaults | E10: ✅ Active | F10: Go →
A11: ▶ | B11: TB_Suppliers_Master | C11: Suppliers Master | D11: 10 suppliers, Payment terms, VAT | E11: ✅ Active | F11: Go →
A12: ▶ | B12: TB_Dimensions | C12: Analytical Dimensions | D12: 3 dimensions, 18 values, Mandatory tagging | E12: ✅ Active | F12: Go →
A14: 🔄 OPERATIONS
A15: Module | B15: Sheet Name | C15: Description | D15: Records | E15: Status
A16: ▶ | B16: TB_Master_Bookings | C16: Master Bookings | D16: 11 bookings, Auto nights, FX conversion | E16: ✅ Active | F16: Go →
A17: ▶ | B17: TB_Hotel_Accruals | C17: Hotel Accruals | D17: 10 accruals, CBE rate lookup | E17: ✅ Active | F17: Go →
A18: ▶ | B18: TB_Excursions_Sales | C18: Excursion Sales | D18: 18 tickets, Auto commission, Deposit | E18: ✅ Active | F18: Go →
A19: ▶ | B19: TB_Cash_Rep_Reconciliation | C19: Cash Reconciliation | D19: 7 daily recs, Variance analysis | E19: ✅ Active | F19: Go →
A20: ▶ | B20: TB_AP_Invoices | C20: AP Invoices | D20: 8 invoices, Due dates, VAT calc | E20: ✅ Active | F20: Go →
A21: ▶ | B21: TB_Bank_Reconciliation | C21: Bank Reconciliation | D21: 5 recs, Auto-flag unmatched | E21: ✅ Active | F21: Go →
A23: 📊 ACCOUNTING & COMPLIANCE
A24: Module | B24: Sheet Name | C24: Description | D24: Records | E24: Status
A25: ▶ | B25: TB_General_Journal | C25: General Journal | D25: 20 lines, Double-entry, FX per line | E25: ✅ Active | F25: Go →
A26: ▶ | B26: TB_Trial_Balance | C26: Trial Balance | D26: 16 accounts, Auto-calculated | E26: ✅ Active | F26: Go →
A27: ▶ | B27: TB_ETA_Integration | C27: ETA E-Invoice | D27: 10 e-invoices, Portal reconciliation | E27: ✅ Active | F27: Go →
A28: ▶ | B28: TB_Audit_Trail | C28: Audit Trail | D28: 12 entries, User ID, Timestamp | E28: ✅ Active | F28: Go →
A30: 💰 REPORTING & ANALYTICS
A31: Module | B31: Sheet Name | C31: Description | D31: Records | E31: Status
A32: ▶ | B32: TB_Budget_vs_Actual | C32: Budget vs Actual | D32: 10 accounts, Variance %, YTD | E32: ✅ Active | F32: Go →
A33: ▶ | B33: TB_Golden_Report | C33: Golden Report (TO P&L) | D33: 10 TOs, Net margin %, Action flags — CEO DASHBOARD | E33: ✅ Active | F33: Go →
A35: 🛠️ MIGRATION & ADMIN
A36: Module | B36: Sheet Name | C36: Description | D36: Records | E36: Status
A37: ▶ | B37: TB_Migration_Plan | C37: COA Migration Plan | D37: 5 phases, 28 steps — Follow strictly | E37: ✅ Active | F37: Go →
A39: 📖 DOCUMENTATION
A40: Module | B40: Sheet Name | C40: Description | D40: Records | E40: Status
A41: ▶ | B41: INDEX_User_Guide | C41: User Guide & Roadmap | D41: Complete index, Limitations, Scale-up plan | E41: ✅ Active | F41: Go →
A43: 🆕 ADDITIONAL MODULES
A44: Module | B44: Sheet Name | C44: Description | D44: Records | E44: Status
A45: ▶ | B45: TB_WHT_Quarterly | C45: Per-invoice WHT tracking for EAS quarterly filing | D45: Live / Dynamic | E45: ✅ Active | F45: Go →
A46: ▶ | B46: TB_Income_Statement | C46: Live P&L by account class, sourced from Trial Balance | D46: Live / Dynamic | E46: ✅ Active | F46: Go →
A47: ▶ | B47: TB_Balance_Sheet | C47: Live Assets = Liabilities + Equity check | D47: Live / Dynamic | E47: ✅ Active | F47: Go →

Sheet INDEX_User_Guide
A1: DMC ERP MASTER WORKBOOK - UNIFIED EDITION | H1: 🏠 Back to Home
A2: Designed for DMC Operations in Egypt | EAS & Tax Compliant | Multi-Currency | Scalable Framework
A4: MODULE INDEX
A5: Sheet Name | B5: Type | C5: Purpose | D5: Records | E5: Key Features
A6: TB_COA | B6: Setup | C6: Chart of Accounts | D6: 45 accounts | E6: IsActive flag, Multi-currency, Data Validation
A7: TB_CBE_Rates | B7: Setup | C7: Daily FX Rates | D7: 18 days | E7: USD/EUR/GBP, Source tracking
A8: TB_Clients_Master | B8: Master Data | C8: Client Registry | D8: 10 clients | E8: Credit limits, VAT reg, Payment terms
A9: TB_Hotels_Master | B9: Master Data | C9: Hotel Contracts | D9: 10 hotels | E9: Star rating, Commission %, Contract rates
A10: TB_Reps_Master | B10: Master Data | C10: Rep Registry | D10: 8 reps | E10: Float limits, Commission defaults, Hotels assigned
A11: TB_Master_Bookings | B11: Operations | C11: Booking Register | D11: 11 bookings | E11: Auto nights, FX conversion, Status tracking
A12: TB_Hotel_Accruals | B12: Operations | C12: Cost Provisions | D12: 10 accruals | E12: Linked to bookings, CBE rate lookup
A13: TB_Excursions_Sales | B13: Operations | C13: Excursion Tickets | D13: 18 tickets | E13: Auto commission, Payment method, Deposit status
A14: TB_Cash_Rep_Reconciliation | B14: Operations | C14: Daily Cash Rec | D14: 7 reconciliations | E14: Expected vs Actual, Variance analysis
A15: TB_AP_Invoices | B15: Operations | C15: Supplier Invoices | D15: 8 invoices | E15: Due dates, VAT calc, Status workflow
A16: TB_General_Journal | B16: Accounting | C16: Journal Entries | D16: 20 lines | E16: Double-entry, FX rate per line, VAT support
A17: TB_Trial_Balance | B17: Reporting | C17: Period Balance | D17: 16 accounts | E17: Auto-calculated from Journal
A20: QUICK START GUIDE
A21: Step | B21: Action | C21: Sheet | D21: Notes
A22: 1 | B22: Update CBE Rates daily | C22: TB_CBE_Rates | D22: Add new row with date and rates. All FX modules reference this sheet.
A23: 2 | B23: Register new clients/hotels/reps | C23: TB_Clients_Master, TB_Hotels_Master, TB_Reps_Master | D23: Use dropdown lists for Status and Type fields.
A24: 3 | B24: Record new bookings | C24: TB_Master_Bookings | D24: Nights auto-calculated. Total FX = Pax × Rate. Total EGP = Total FX × CBE Rate.
A25: 4 | B25: Create hotel accruals | C25: TB_Hotel_Accruals | D25: Link to Booking_Ref. Provision_EGP = Cost_FX × CBE_Rate.
A26: 5 | B26: Record excursion sales | C26: TB_Excursions_Sales | D26: Sale Amount = Pax × Unit Price. Commission auto-calculated.
A27: 6 | B27: Reconcile daily cash | C27: TB_Cash_Rep_Reconciliation | D27: Expected = Cash + POS - Commission. Variance = Actual - Expected.
A28: 7 | B28: Post journal entries | C28: TB_General_Journal | D28: Every transaction MUST have balanced Debit = Credit.
A29: 8 | B29: Review Trial Balance | C29: TB_Trial_Balance | D29: Verify Closing Balance and ensure TOTALS are BALANCED.
A31: FUTURE EXPANSION ROADMAP
A32: Module | B32: Description | C32: Priority | D32: Complexity
A33: TB_Suppliers_Master | B33: Transport, excursion, and other suppliers registry | C33: High | D33: Low
A34: TB_Inventory_Master | B34: Track excursion equipment, gifts, consumables | C34: Medium | D34: Medium
A35: TB_Employees_Payroll | B35: Salaries, social insurance, withholding tax | C35: High | D35: High
A36: TB_Bank_Reconciliation | B36: Match bank statements with journal entries | C36: High | D36: Medium
A37: TB_ETA_Integration | B37: E-invoice submission and reconciliation with tax portal | C37: Critical | D37: High
A38: TB_FX_Hedging | B38: Forward contracts and FX risk management | C38: Medium | D38: High
A39: TB_Budget_vs_Actual | B39: Monthly budget tracking and variance analysis | C39: Medium | D39: Medium
A40: TB_Agent_Performance | B40: Revenue, margin, and collection analysis per agent | C40: Low | D40: Low
A41: TB_Seasonal_Forecasting | B41: Occupancy and revenue projections by season | C41: Low | D41: High
A42: TB_Audit_Trail | B42: Log all changes with user ID and timestamp | C42: High | D42: Medium

Sheet TB_CBE_Rates
A1: MODULE: CBE EXCHANGE RATES | H1: 🏠 Back to Home
A2: Daily official rates from Central Bank of Egypt. Extend range as needed. Used by all FX modules.
A3: Date | B3: USD_Rate | C3: EUR_Rate | D3: GBP_Rate | E3: Source | F3: Last_Updated_By
A4: 2026-08-01 | B4: 48.85 | C4: 53.1 | D4: 61.9 | E4: CBE Official | F4: System
A5: 2026-08-02 | B5: 48.9 | C5: 53.05 | D5: 61.85 | E5: CBE Official | F5: System
A6: 2026-08-03 | B6: 48.92 | C6: 53.2 | D6: 62 | E6: CBE Official | F6: System
A7: 2026-08-04 | B7: 48.95 | C7: 53.15 | D7: 61.95 | E7: CBE Official | F7: System
A8: 2026-08-05 | B8: 49 | C8: 53.3 | D8: 62.1 | E8: CBE Official | F8: System
A9: 2026-08-06 | B9: 49.05 | C9: 53.25 | D9: 62.05 | E9: CBE Official | F9: System
A10: 2026-08-07 | B10: 49.1 | C10: 53.4 | D10: 62.2 | E10: CBE Official | F10: System
A11: 2026-08-08 | B11: 49.08 | C11: 53.35 | D11: 62.15 | E11: CBE Official | F11: System
A12: 2026-08-09 | B12: 49.12 | C12: 53.45 | D12: 62.25 | E12: CBE Official | F12: System
A13: 2026-08-10 | B13: 49.15 | C13: 53.5 | D13: 62.3 | E13: CBE Official | F13: System
A14: 2026-08-14 | B14: 49.05 | C14: 53.7 | D14: 62.4 | E14: CBE Official | F14: System
A15: 2026-08-15 | B15: 49.1 | C15: 53.8 | D15: 62.55 | E15: CBE Official | F15: System
... A49: 2026-09-15 | B49: 49.92 | C49: 55.45 | D49: 64.35 | E49: CBE Official | F49: System

Sheet TB_Suppliers_Master
A1: MODULE: SUPPLIERS MASTER DATA | Q1: 🏠 Back to Home
A2: Transport, excursion, and other suppliers registry. Linked to AP Invoices and Payments.
A3: Supplier_ID | B3: Supplier_Name | C3: Supplier_Type | D3: Category | E3: Contact_Person | F3: Contact_Email | G3: Phone | H3: Payment_Terms_Days | I3: Currency | J3: VAT_Registration | K3: WHT_Exempt | L3: Status | M3: Contract_Start | N3: Notes | O3: Linked_Hotel_ID
A4: SUP-001 | B4: Hurghada Transport Co. | C4: Transport | D4: Ground Transport | E4: Mr. Khaled Samy | F4: ops@hurghadatransport.com | G4: +20-65-123-4567 | H4: 15 | I4: EGP | J4: 123456789 | K4: =FALSE() -> FALSE | L4: Active | M4: 2026-01-01 | N4: Airport transfers & city tours | WHT_Exempt=FALSE (subject to 3% WHT)
A5: SUP-002 | B5: Red Sea Diving Center | C5: Excursion | D5: Water Sports | E5: Ms. Dalia Hassan | F5: bookings@rsdc.com | G5: +20-65-234-5678 | H5: 7 | I5: USD | J5: N/A | K5: =FALSE() -> FALSE | L5: Active | M5: 2026-01-15 | N5: Diving & snorkeling trips | WHT_Exempt=FALSE (subject to 3% WHT)
A6: SUP-003 | B6: Luxor Day Tours | C6: Excursion | D6: Cultural Tours | E6: Mr. Tarek El-Sayed | F6: info@luxordaytours.com | G6: +20-95-345-6789 | H6: 14 | I6: EGP | J6: 987654321 | K6: =FALSE() -> FALSE | L6: Active | M6: 2026-02-01 | N6: Luxor temple & valley tours | WHT_Exempt=FALSE (subject to 3% WHT)
A7: SUP-004 | B7: Cairo Shuttle Express | C7: Transport | D7: Inter-city | E7: Ms. Nour Ibrahim | F7: reservations@cairoshuttle.com | G7: +20-2-456-7890 | H7: 30 | I7: EGP | J7: 456789123 | K7: =FALSE() -> FALSE | L7: Active | M7: 2026-02-15 | N7: Cairo-Hurghada shuttle service | WHT_Exempt=FALSE (subject to 3% WHT)
A8: SUP-005 | B8: Desert Safari Adventures | C8: Excursion | D8: Adventure | E8: Mr. Omar Fathy | F8: adventures@desertsafari.com | G8: +20-65-567-8901 | H8: 7 | I8: USD | J8: N/A | K8: =FALSE() -> FALSE | L8: Active | M8: 2026-03-01 | N8: Quad bikes & camel rides | WHT_Exempt=FALSE (subject to 3% WHT)
A9: SUP-006 | B9: Nile Cruise Operators | C9: Excursion | D9: Cruise | E9: Ms. Laila Mostafa | F9: charter@nilecruise.com | G9: +20-65-678-9012 | H9: 21 | I9: EUR | J9: 789123456 | K9: =FALSE() -> FALSE | L9: Active | M9: 2026-03-15 | N9: Luxor-Aswan cruise packages | WHT_Exempt=FALSE (subject to 3% WHT)
A10: SUP-007 | B10: Sinai Tours & Travel | C10: Excursion | D10: Religious/Cultural | E10: Mr. Wael Hamdy | F10: bookings@sinaitt.com | G10: +20-69-789-0123 | H10: 14 | I10: EGP | J10: 321654987 | K10: =FALSE() -> FALSE | L10: Active | M10: 2026-04-01 | N10: St. Catherine & Moses Mountain | WHT_Exempt=FALSE (subject to 3% WHT)
A11: SUP-008 | B11: Hurghada Car Rental | C11: Transport | D11: Car Hire | E11: Mr. Sami Farouk | F11: rentals@hurghadacars.com | G11: +20-65-890-1234 | H11: 0 | I11: USD | J11: N/A | K11: =FALSE() -> FALSE | L11: Active | M11: 2026-04-15 | N11: Daily & weekly car rentals | WHT_Exempt=FALSE (subject to 3% WHT)
A12: SUP-009 | B12: Gift Shop Suppliers | C12: Retail | D12: Souvenirs | E12: Ms. Sara Khaled | F12: wholesale@gifts-egypt.com | G12: +20-65-901-2345 | H12: 30 | I12: EGP | J12: 654987321 | K12: =FALSE() -> FALSE | L12: Active | M12: 2026-05-01 | N12: Pharaonic souvenirs & gifts | WHT_Exempt=FALSE (subject to 3% WHT)
A13: SUP-010 | B13: Marina Yacht Charters | C13: Excursion | D13: Luxury | E13: Mr. Karim Fathy | F13: charter@marinayacht.com | G13: +20-65-012-3456 | H13: 14 | I13: EUR | J13: N/A | K13: =FALSE() -> FALSE | L13: Active | M13: 2026-05-15 | N13: Private yacht & fishing trips | WHT_Exempt=FALSE (subject to 3% WHT)
A14: SUP-HTL-001 | B14: Steigenberger Aldau Beach | C14: Hotel | O14: HTL-001
A15: SUP-HTL-002 | B15: Jaz Aquamarine Resort | C15: Hotel | O15: HTL-002
A16: SUP-HTL-003 | B16: Sunrise Grand Select | C16: Hotel | O16: HTL-003
A17: SUP-HTL-004 | B17: Sun & Sea Beach Resort | C17: Hotel | O17: HTL-006
A18: SUP-HTL-005 | B18: Coral Hills Resort | C18: Hotel | O18: HTL-007
A19: SUP-HTL-006 | B19: Blue Lagoon Palace | C19: Hotel | O19: HTL-008
A20: SUP-HTL-007 | B20: Desert Rose Plaza | C20: Hotel | O20: HTL-009
A21: SUP-HTL-008 | B21: Seagull Beach Resort | C21: Hotel | O21: HTL-010
A22: SUP-HTL-009 | B22: Pickalbatros Aqua Blu | C22: Hotel | O22: HTL-004
A23: SUP-HTL-010 | B23: Sunny Days El Palacio | C23: Hotel | O23: HTL-005

Sheet TB_Clients_Master
A1: MODULE: CLIENTS MASTER DATA | N1: 🏠 Back to Home
A2: Master registry for all tour operators, agents, and direct clients. Credit limits and payment terms.
A3: Client_ID | B3: Client_Name | C3: Country | D3: Client_Type | E3: Credit_Limit_FX | F3: Credit_Currency | G3: Payment_Terms_Days | H3: VAT_Registration | I3: Contact_Email | J3: Discount_Rate_Pct | K3: Created_Date | L3: Notes
A4: CLI-001 | B4: Alpine Sun Tours Group | C4: Austria | D4: Tour Operator | E4: 500000 | F4: EUR | G4: 30 | H4: ATU12345678 | I4: finance@alpinesun.at | J4: 0 | K4: 2026-01-15 | L4: DMC margin from hotel buy/sell, not client markup
A5: CLI-002 | B5: Nordic Wave DMC | C5: Sweden | D5: Tour Operator | E5: 300000 | F5: EUR | G5: 45 | H5: SE5566778899 | I5: accounts@nordicwave.se | J5: 0 | K5: 2026-01-20 | L5: DMC margin from hotel buy/sell, not client markup
A6: CLI-003 | B6: BritSun Holidays | C6: UK | D6: Tour Operator | E6: 250000 | F6: GBP | G6: 30 | H6: GB123456789 | I6: payments@britsun.co.uk | J6: 0 | K6: 2026-02-01 | L6: DMC margin from hotel buy/sell, not client markup
A7: CLI-004 | B7: Meridian Voyages | C7: Germany | D7: Tour Operator | E7: 400000 | F7: EUR | G7: 30 | H7: DE123456789 | I7: billing@meridian-voyages.de | J7: 0 | K7: 2026-02-10 | L7: DMC margin from hotel buy/sell, not client markup
A8: CLI-005 | B8: Red Sea Direct Bookings | C8: Egypt | D8: Walk-in | E8: 0 | F8: EGP | G8: 0 | H8: N/A | I8: N/A | J8: 0 | K8: 2026-03-01 | L8: DMC margin from hotel buy/sell, not client markup
A9: CLI-006 | B9: EuroSun Tours | C9: Germany | D9: Tour Operator | E9: 350000 | F9: EUR | G9: 30 | H9: DE987654321 | I9: finance@eurosun.de | J9: 0 | K9: 2026-03-15 | L9: DMC margin from hotel buy/sell, not client markup
A10: CLI-007 | B10: Nile Breeze | C10: Egypt | D10: Local Agent | E10: 50000 | F10: USD | G10: 15 | H10: N/A | I10: info@nilebreeze.com | J10: 0 | K10: 2026-04-01 | L10: DMC margin from hotel buy/sell, not client markup
A11: CLI-008 | B11: London Escape | C11: UK | D11: Tour Operator | E11: 200000 | F11: GBP | G11: 30 | H11: GB987654321 | I11: bookings@londonescape.co.uk | J11: 0 | K11: 2026-04-15 | L11: DMC margin from hotel buy/sell, not client markup
A12: CLI-009 | B12: Gulf Adventures | C12: UAE | D12: Tour Operator | E12: 450000 | F12: USD | G12: 45 | H12: AE123456789 | I12: accounts@gulfadventures.ae | J12: 0 | K12: 2026-05-01 | L12: DMC margin from hotel buy/sell, not client markup
A13: CLI-010 | B13: SunSeeker Travel | C13: France | D13: Tour Operator | E13: 200000 | F13: EUR | G13: 60 | H13: FR12345678901 | I13: compta@sunseeker.fr | J13: 0 | K13: 2026-06-01 | L13: DMC margin from hotel buy/sell, not client markup

Sheet TB_Hotels_Master
A1: MODULE: HOTELS MASTER DATA | Q1: 🏠 Back to Home
A2: Contracted hotels with rates, commissions, and payment terms. Linked to bookings and accruals.
A3: Hotel_ID | B3: Hotel_Name | C3: Star_Rating | D3: Location | E3: Contact_Person | F3: Contact_Email | G3: Currency | H3: Buying_Rate_FX | I3: Selling_Rate_FX | J3: DMC_Margin_FX | K3: DMC_Margin_Pct | L3: Payment_Terms_Days | M3: Status | N3: Contract_Start | O3: Supplier_ID
A4: HTL-001 | B4: Steigenberger Aldau Beach | C4: 5 | D4: Hurghada | E4: Mr. Ahmed Hassan | F4: ahmed@steigenberger.com | G4: EUR | H4: 72 | I4: 90 | J4: =I4-H4 -> 18 | K4: =(I4-H4)/I4 -> 0.2 | L4: 30 | M4: Active | N4: 2026-01-01 | O4: =IFERROR(INDEX(TB_Suppliers_Master!$A$4:$A$23,MATCH(A4,TB_Suppliers_Master!$O$4:$O$23,0)),"") -> SUP-HTL-001
A5: HTL-002 | B5: Jaz Aquamarine Resort | C5: 5 | D5: Hurghada | E5: Ms. Sara Khaled | F5: sara@jazhotels.com | G5: EUR | H5: 65 | I5: 82 | J5: =I5-H5 -> 17 | K5: =(I5-H5)/I5 -> 0.20731707 | L5: 30 | M5: Active | N5: 2026-01-01 | O5: =IFERROR(INDEX(TB_Suppliers_Master!$A$4:$A$23,MATCH(A5,TB_Suppliers_Master!$O$4:$O$23,0)),"") -> SUP-HTL-002
A6: HTL-003 | B6: Sunrise Grand Select | C6: 5 | D6: Hurghada | E6: Mr. Karim Fathy | F6: karim@sunrise.com | G6: EUR | H6: 62 | I6: 78 | J6: =I6-H6 -> 16 | K6: =(I6-H6)/I6 -> 0.20512821 | L6: 45 | M6: Active | N6: 2026-01-01 | O6: =IFERROR(INDEX(TB_Suppliers_Master!$A$4:$A$23,MATCH(A6,TB_Suppliers_Master!$O$4:$O$23,0)),"") -> SUP-HTL-003
A7: HTL-004 | B7: Pickalbatros Aqua Blu | C7: 4 | D7: Hurghada | E7: Ms. Dina Samir | F7: dina@pickalbatros.com | G7: EUR | H7: 48 | I7: 60 | J7: =I7-H7 -> 12 | K7: =(I7-H7)/I7 -> 0.2 | L7: 30 | M7: Active | N7: 2026-01-01 | O7: =IFERROR(INDEX(TB_Suppliers_Master!$A$4:$A$23,MATCH(A7,TB_Suppliers_Master!$O$4:$O$23,0)),"") -> SUP-HTL-009
A8: HTL-005 | B8: Sunny Days El Palacio | C8: 4 | D8: Hurghada | E8: Mr. Hossam Ali | F8: hossam@sunnydays.com | G8: EUR | H8: 42 | I8: 53 | J8: =I8-H8 -> 11 | K8: =(I8-H8)/I8 -> 0.20754717 | L8: 30 | M8: Active | N8: 2026-01-01 | O8: =IFERROR(INDEX(TB_Suppliers_Master!$A$4:$A$23,MATCH(A8,TB_Suppliers_Master!$O$4:$O$23,0)),"") -> SUP-HTL-010
A9: HTL-006 | B9: Sun & Sea Beach Resort | C9: 5 | D9: Hurghada | E9: Mr. Tarek Salah | F9: tarek@sunsea.com | G9: EUR | H9: 76 | I9: 95 | J9: =I9-H9 -> 19 | K9: =(I9-H9)/I9 -> 0.2 | L9: 30 | M9: Active | N9: 2026-02-01 | O9: =IFERROR(INDEX(TB_Suppliers_Master!$A$4:$A$23,MATCH(A9,TB_Suppliers_Master!$O$4:$O$23,0)),"") -> SUP-HTL-004
A10: HTL-007 | B10: Coral Hills Resort | C10: 4 | D10: Hurghada | E10: Ms. Nour Ibrahim | F10: nour@coralhills.com | G10: USD | H10: 60 | I10: 75 | J10: =I10-H10 -> 15 | K10: =(I10-H10)/I10 -> 0.2 | L10: 30 | M10: Active | N10: 2026-02-01 | O10: =IFERROR(INDEX(TB_Suppliers_Master!$A$4:$A$23,MATCH(A10,TB_Suppliers_Master!$O$4:$O$23,0)),"") -> SUP-HTL-005
A11: HTL-008 | B11: Blue Lagoon Palace | C11: 5 | D11: Hurghada | E11: Mr. Sami Farouk | F11: sami@bluelagoon.com | G11: GBP | H11: 68 | I11: 85 | J11: =I11-H11 -> 17 | K11: =(I11-H11)/I11 -> 0.2 | L11: 45 | M11: Active | N11: 2026-03-01 | O11: =IFERROR(INDEX(TB_Suppliers_Master!$A$4:$A$23,MATCH(A11,TB_Suppliers_Master!$O$4:$O$23,0)),"") -> SUP-HTL-006
A12: HTL-009 | B12: Desert Rose Plaza | C12: 4 | D12: Hurghada | E12: Ms. Laila Mostafa | F12: laila@desertrose.com | G12: USD | H12: 56 | I12: 70 | J12: =I12-H12 -> 14 | K12: =(I12-H12)/I12 -> 0.2 | L12: 30 | M12: Active | N12: 2026-03-01 | O12: =IFERROR(INDEX(TB_Suppliers_Master!$A$4:$A$23,MATCH(A12,TB_Suppliers_Master!$O$4:$O$23,0)),"") -> SUP-HTL-007
A13: HTL-010 | B13: Seagull Beach Resort | C13: 4 | D13: Hurghada | E13: Mr. Wael Hamdy | F13: wael@seagull.com | G13: EUR | H13: 52 | I13: 65 | J13: =I13-H13 -> 13 | K13: =(I13-H13)/I13 -> 0.2 | L13: 30 | M13: Active | N13: 2026-04-01 | O13: =IFERROR(INDEX(TB_Suppliers_Master!$A$4:$A$23,MATCH(A13,TB_Suppliers_Master!$O$4:$O$23,0)),"") -> SUP-HTL-008

Sheet TB_Reps_Master
A1: MODULE: REPS MASTER DATA | N1: 🏠 Back to Home
A2: Resort representatives with assigned hotels, commission rates, and cash float limits.
A3: Rep_ID | B3: Rep_Name | C3: Nationality | D3: Hotel_Assigned | E3: Base_Salary_EGP | F3: Commission_Rate_Default | G3: Cash_Float_EGP | H3: Start_Date | I3: Status | J3: Emergency_Contact | L3: Client_ID (linked)
A4: REP-01 | B4: Mohamed Ali | C4: Egyptian | D4: Steigenberger Aldau Beach | E4: 5000 | F4: 0.1 | G4: 2000 | H4: 2026-01-15 | I4: Active | J4: +20-100-111-2222 | L4: =IFERROR(INDEX(TB_Master_Bookings!$B$4:$B$1000,MATCH(INDEX(TB_Hotels_Master!$A$4:$A$1000,MATCH(D4,TB_Hotels_Master!$B$4:$B$1000,0)),TB_Master_Bookings!$O$4:$O$1000,0)),"") -> CLI-001
A5: REP-02 | B5: Ahmed Ibrahim | C5: Egyptian | D5: Jaz Aquamarine Resort | E5: 5000 | F5: 0.1 | G5: 2000 | H5: 2026-02-01 | I5: Active | J5: +20-100-333-4444 | L5: =IFERROR(INDEX(TB_Master_Bookings!$B$4:$B$1000,MATCH(INDEX(TB_Hotels_Master!$A$4:$A$1000,MATCH(D5,TB_Hotels_Master!$B$4:$B$1000,0)),TB_Master_Bookings!$O$4:$O$1000,0)),"") -> CLI-002
A6: REP-03 | B6: Sara Hassan | C6: Egyptian | D6: Sunrise Grand Select | E6: 5000 | F6: 0.1 | G6: 2000 | H6: 2026-01-20 | I6: Active | J6: +20-100-555-6666 | L6: =IFERROR(INDEX(TB_Master_Bookings!$B$4:$B$1000,MATCH(INDEX(TB_Hotels_Master!$A$4:$A$1000,MATCH(D6,TB_Hotels_Master!$B$4:$B$1000,0)),TB_Master_Bookings!$O$4:$O$1000,0)),"") -> CLI-003
A7: REP-04 | B7: Khaled Omar | C7: Egyptian | D7: Pickalbatros Aqua Blu | E7: 5000 | F7: 0.1 | G7: 2000 | H7: 2026-03-01 | I7: Active | J7: +20-100-777-8888 | L7: =IFERROR(INDEX(TB_Master_Bookings!$B$4:$B$1000,MATCH(INDEX(TB_Hotels_Master!$A$4:$A$1000,MATCH(D7,TB_Hotels_Master!$B$4:$B$1000,0)),TB_Master_Bookings!$O$4:$O$1000,0)),"") -> CLI-004
A8: REP-05 | B8: Lina Farouk | C8: Egyptian | D8: Sunny Days El Palacio | E8: 5000 | F8: 0.1 | G8: 2000 | H8: 2026-04-01 | I8: On Leave | J8: +20-100-999-0000 | L8: =IFERROR(INDEX(TB_Master_Bookings!$B$4:$B$1000,MATCH(INDEX(TB_Hotels_Master!$A$4:$A$1000,MATCH(D8,TB_Hotels_Master!$B$4:$B$1000,0)),TB_Master_Bookings!$O$4:$O$1000,0)),"") -> CLI-005
A9: REP-HRG-01 | B9: Omar Fathy | C9: Egyptian | D9: Sun & Sea Beach Resort | E9: 5500 | F9: 0.1 | G9: 2500 | H9: 2026-05-01 | I9: Active | J9: +20-101-111-2222 | L9: =IFERROR(INDEX(TB_Master_Bookings!$B$4:$B$1000,MATCH(INDEX(TB_Hotels_Master!$A$4:$A$1000,MATCH(D9,TB_Hotels_Master!$B$4:$B$1000,0)),TB_Master_Bookings!$O$4:$O$1000,0)),"") -> CLI-006
A10: REP-HRG-02 | B10: Nadia Samir | C10: Egyptian | D10: Blue Lagoon Palace | E10: 5500 | F10: 0.1 | G10: 2500 | H10: 2026-05-15 | I10: Active | J10: +20-101-333-4444 | L10: =IFERROR(INDEX(TB_Master_Bookings!$B$4:$B$1000,MATCH(INDEX(TB_Hotels_Master!$A$4:$A$1000,MATCH(D10,TB_Hotels_Master!$B$4:$B$1000,0)),TB_Master_Bookings!$O$4:$O$1000,0)),"") -> CLI-008
A11: REP-HRG-03 | B11: Tamer Hosny | C11: Egyptian | D11: Coral Hills Resort | E11: 5500 | F11: 0.1 | G11: 2500 | H11: 2026-06-01 | I11: Active | J11: +20-101-555-6666 | L11: =IFERROR(INDEX(TB_Master_Bookings!$B$4:$B$1000,MATCH(INDEX(TB_Hotels_Master!$A$4:$A$1000,MATCH(D11,TB_Hotels_Master!$B$4:$B$1000,0)),TB_Master_Bookings!$O$4:$O$1000,0)),"") -> CLI-007

Sheet TB_Master_Bookings
A1: MODULE: MASTER BOOKINGS | R1: 🏠 Back to Home
A2: All inbound bookings from tour operators and direct clients. Auto-calculates nights, total FX, and EGP.
A3: Booking_Ref | B3: Client_ID | C3: Client_Name | D3: Agent_Name | E3: Pax_Count | F3: Check_In | G3: Check_Out | H3: Nights | I3: Currency | J3: Contracted_Rate_Foreign | K3: Total_FX | L3: CBE_Rate_at_Departure | M3: Total_EGP | N3: Status | O3: Hotel_ID | P3: Hotel_Provision_EGP
A4: HRG-2026-0815 | B4: CLI-001 | C4: =IF(B4="","",IFERROR(INDEX(TB_Clients_Master!$B$4:$B$1000,MATCH(B4,TB_Clients_Master!$A$4:$A$1000,0)),"INVALID CLIENT ID")) -> Alpine Sun Tours Group | D4: Alpine Sun Tours (Austria) | E4: 200 | F4: 2026-08-01 | G4: 2026-08-08 | H4: =G4-F4 -> 7 | I4: EUR | J4: 90 | K4: =IF(OR(E4="",H4="",J4=""),"",E4*H4*J4) -> 126000 | L4: 53.35 | M4: =K4*L4 -> 6722100 | N4: Checked Out | O4: HTL-001 | P4: =IFERROR(INDEX(TB_Hotel_Accruals!$I$4:$I$1000,MATCH(A4,TB_Hotel_Accruals!$B$4:$B$1000,0)),0) -> 5377680
A5: HRG-2026-0816 | B5: CLI-002 | C5: =IF(B5="","",IFERROR(INDEX(TB_Clients_Master!$B$4:$B$1000,MATCH(B5,TB_Clients_Master!$A$4:$A$1000,0)),"INVALID CLIENT ID")) -> Nordic Wave DMC | D5: Nordic Wave DMC (Sweden) | E5: 45 | F5: 2026-08-02 | G5: 2026-08-09 | H5: =G5-F5 -> 7 | I5: USD | J5: 82 | K5: =IF(OR(E5="",H5="",J5=""),"",E5*H5*J5) -> 25830 | L5: 49.12 | M5: =K5*L5 -> 1268769.6 | N5: Checked Out | O5: HTL-002 | P5: =IFERROR(INDEX(TB_Hotel_Accruals!$I$4:$I$1000,MATCH(A5,TB_Hotel_Accruals!$B$4:$B$1000,0)),0) -> 1005732
A6: HRG-2026-0817 | B6: CLI-003 | C6: =IF(B6="","",IFERROR(INDEX(TB_Clients_Master!$B$4:$B$1000,MATCH(B6,TB_Clients_Master!$A$4:$A$1000,0)),"INVALID CLIENT ID")) -> BritSun Holidays | D6: BritSun Holidays (UK) | E6: 30 | F6: 2026-08-03 | G6: 2026-08-10 | H6: =G6-F6 -> 7 | I6: GBP | J6: 78 | K6: =IF(OR(E6="",H6="",J6=""),"",E6*H6*J6) -> 16380 | L6: 62.3 | M6: =K6*L6 -> 1020474 | N6: Checked Out | O6: HTL-003 | P6: =IFERROR(INDEX(TB_Hotel_Accruals!$I$4:$I$1000,MATCH(A6,TB_Hotel_Accruals!$B$4:$B$1000,0)),0) -> 811146
A7: HRG-2026-0818 | B7: CLI-004 | C7: =IF(B7="","",IFERROR(INDEX(TB_Clients_Master!$B$4:$B$1000,MATCH(B7,TB_Clients_Master!$A$4:$A$1000,0)),"INVALID CLIENT ID")) -> Meridian Voyages | D7: Meridian Voyages (Germany) | E7: 60 | F7: 2026-08-01 | G7: 2026-08-07 | H7: =G7-F7 -> 6 | I7: EUR | J7: 60 | K7: =IF(OR(E7="",H7="",J7=""),"",E7*H7*J7) -> 21600 | L7: 53.4 | M7: =K7*L7 -> 1153440 | N7: Checked Out | O7: HTL-004 | P7: =IFERROR(INDEX(TB_Hotel_Accruals!$I$4:$I$1000,MATCH(A7,TB_Hotel_Accruals!$B$4:$B$1000,0)),0) -> 922752
A8: HRG-2026-0819 | B8: CLI-005 | C8: =IF(B8="","",IFERROR(INDEX(TB_Clients_Master!$B$4:$B$1000,MATCH(B8,TB_Clients_Master!$A$4:$A$1000,0)),"INVALID CLIENT ID")) -> Red Sea Direct Bookings | D8: Direct / Walk-in | E8: 12 | F8: 2026-08-04 | G8: 2026-08-09 | H8: =G8-F8 -> 5 | I8: USD | J8: 53 | K8: =IF(OR(E8="",H8="",J8=""),"",E8*H8*J8) -> 3180 | L8: 49.12 | M8: =K8*L8 -> 156201.6 | N8: Checked Out | O8: HTL-005 | P8: =IFERROR(INDEX(TB_Hotel_Accruals!$I$4:$I$1000,MATCH(A8,TB_Hotel_Accruals!$B$4:$B$1000,0)),0) -> 123782.4
A9: HRG-2026-0820 | B9: CLI-010 | C9: =IF(B9="","",IFERROR(INDEX(TB_Clients_Master!$B$4:$B$1000,MATCH(B9,TB_Clients_Master!$A$4:$A$1000,0)),"INVALID CLIENT ID")) -> SunSeeker Travel | D9: SunSeeker Travel (France) | E9: 80 | F9: 2026-08-15 | G9: 2026-08-22 | H9: =G9-F9 -> 7 | I9: EUR | J9: 95 | K9: =IF(OR(E9="",H9="",J9=""),"",E9*H9*J9) -> 53200 | L9: 53.5 | M9: =K9*L9 -> 2846200 | N9: Confirmed | P9: =IFERROR(INDEX(TB_Hotel_Accruals!$I$4:$I$1000,MATCH(A9,TB_Hotel_Accruals!$B$4:$B$1000,0)),0) -> 0
A10: MBR-2026-0001 | B10: CLI-006 | C10: =IF(B10="","",IFERROR(INDEX(TB_Clients_Master!$B$4:$B$1000,MATCH(B10,TB_Clients_Master!$A$4:$A$1000,0)),"INVALID CLIENT ID")) -> EuroSun Tours | D10: Berlin Leisure | E10: 200 | F10: 2026-08-15 | G10: 2026-08-22 | H10: =G10-F10 -> 7 | I10: EUR | J10: 95 | K10: =IF(OR(E10="",H10="",J10=""),"",E10*H10*J10) -> 133000 | L10: 54.2 | M10: =K10*L10 -> 7208600 | N10: Invoiced | O10: HTL-006 | P10: =IFERROR(INDEX(TB_Hotel_Accruals!$I$4:$I$1000,MATCH(A10,TB_Hotel_Accruals!$B$4:$B$1000,0)),0) -> 5766880
A11: MBR-2026-0002 | B11: CLI-007 | C11: =IF(B11="","",IFERROR(INDEX(TB_Clients_Master!$B$4:$B$1000,MATCH(B11,TB_Clients_Master!$A$4:$A$1000,0)),"INVALID CLIENT ID")) -> Nile Breeze | D11: Cairo Gateway | E11: 46 | F11: 2026-08-15 | G11: 2026-08-22 | H11: =G11-F11 -> 7 | I11: USD | J11: 75 | K11: =IF(OR(E11="",H11="",J11=""),"",E11*H11*J11) -> 24150 | L11: 49.3 | M11: =K11*L11 -> 1190595 | N11: Invoiced | O11: HTL-007 | P11: =IFERROR(INDEX(TB_Hotel_Accruals!$I$4:$I$1000,MATCH(A11,TB_Hotel_Accruals!$B$4:$B$1000,0)),0) -> 952476
A12: MBR-2026-0003 | B12: CLI-008 | C12: =IF(B12="","",IFERROR(INDEX(TB_Clients_Master!$B$4:$B$1000,MATCH(B12,TB_Clients_Master!$A$4:$A$1000,0)),"INVALID CLIENT ID")) -> London Escape | D12: UK Direct | E12: 32 | F12: 2026-08-16 | G12: 2026-08-24 | H12: =G12-F12 -> 8 | I12: GBP | J12: 85 | K12: =IF(OR(E12="",H12="",J12=""),"",E12*H12*J12) -> 21760 | L12: 63.25 | M12: =K12*L12 -> 1376320 | N12: Invoiced | O12: HTL-008 | P12: =IFERROR(INDEX(TB_Hotel_Accruals!$I$4:$I$1000,MATCH(A12,TB_Hotel_Accruals!$B$4:$B$1000,0)),0) -> 1101056
A13: MBR-2026-0004 | B13: CLI-009 | C13: =IF(B13="","",IFERROR(INDEX(TB_Clients_Master!$B$4:$B$1000,MATCH(B13,TB_Clients_Master!$A$4:$A$1000,0)),"INVALID CLIENT ID")) -> Gulf Adventures | D13: Gulf Reps | E13: 120 | F13: 2026-08-17 | G13: 2026-08-22 | H13: =G13-F13 -> 5 | I13: USD | J13: 70 | K13: =IF(OR(E13="",H13="",J13=""),"",E13*H13*J13) -> 42000 | L13: 49.3 | M13: =K13*L13 -> 2070600 | N13: Invoiced | O13: HTL-009 | P13: =IFERROR(INDEX(TB_Hotel_Accruals!$I$4:$I$1000,MATCH(A13,TB_Hotel_Accruals!$B$4:$B$1000,0)),0) -> 1656480
A14: MBR-2026-0005 | B14: CLI-005 | C14: =IF(B14="","",IFERROR(INDEX(TB_Clients_Master!$B$4:$B$1000,MATCH(B14,TB_Clients_Master!$A$4:$A$1000,0)),"INVALID CLIENT ID")) -> Red Sea Direct Bookings | D14: Hurghada Direct | E14: 85 | F14: 2026-08-18 | G14: 2026-08-25 | H14: =G14-F14 -> 7 | I14: EUR | J14: 65 | K14: =IF(OR(E14="",H14="",J14=""),"",E14*H14*J14) -> 38675 | L14: 54.4 | M14: =K14*L14 -> 2103920 | N14: Invoiced | O14: HTL-010 | P14: =IFERROR(INDEX(TB_Hotel_Accruals!$I$4:$I$1000,MATCH(A14,TB_Hotel_Accruals!$B$4:$B$1000,0)),0) -> 1683136
C15: =IF(B15="","",IFERROR(INDEX(TB_Clients_Master!$B$4:$B$1000,MATCH(B15,TB_Clients_Master!$A$4:$A$1000,0)),"INVALID CLIENT ID")) | K15: =IF(OR(E15="",H15="",J15=""),"",E15*H15*J15) | P15: =IFERROR(INDEX(TB_Hotel_Accruals!$I$4:$I$1000,MATCH(A15,TB_Hotel_Accruals!$B$4:$B$1000,0)),0) -> 0
C16: =IF(B16="","",IFERROR(INDEX(TB_Clients_Master!$B$4:$B$1000,MATCH(B16,TB_Clients_Master!$A$4:$A$1000,0)),"INVALID CLIENT ID")) | K16: =IF(OR(E16="",H16="",J16=""),"",E16*H16*J16) | P16: =IFERROR(INDEX(TB_Hotel_Accruals!$I$4:$I$1000,MATCH(A16,TB_Hotel_Accruals!$B$4:$B$1000,0)),0) -> 0
C17: =IF(B17="","",IFERROR(INDEX(TB_Clients_Master!$B$4:$B$1000,MATCH(B17,TB_Clients_Master!$A$4:$A$1000,0)),"INVALID CLIENT ID")) | K17: =IF(OR(E17="",H17="",J17=""),"",E17*H17*J17) | P17: =IFERROR(INDEX(TB_Hotel_Accruals!$I$4:$I$1000,MATCH(A17,TB_Hotel_Accruals!$B$4:$B$1000,0)),0) -> 0
C18: =IF(B18="","",IFERROR(INDEX(TB_Clients_Master!$B$4:$B$1000,MATCH(B18,TB_Clients_Master!$A$4:$A$1000,0)),"INVALID CLIENT ID")) | K18: =IF(OR(E18="",H18="",J18=""),"",E18*H18*J18) | P18: =IFERROR(INDEX(TB_Hotel_Accruals!$I$4:$I$1000,MATCH(A18,TB_Hotel_Accruals!$B$4:$B$1000,0)),0) -> 0
C19: =IF(B19="","",IFERROR(INDEX(TB_Clients_Master!$B$4:$B$1000,MATCH(B19,TB_Clients_Master!$A$4:$A$1000,0)),"INVALID CLIENT ID")) | K19: =IF(OR(E19="",H19="",J19=""),"",E19*H19*J19) | P19: =IFERROR(INDEX(TB_Hotel_Accruals!$I$4:$I$1000,MATCH(A19,TB_Hotel_Accruals!$B$4:$B$1000,0)),0) -> 0
K20: =IF(OR(E20="",H20="",J20=""),"",E20*H20*J20)
K21: =IF(OR(E21="",H21="",J21=""),"",E21*H21*J21)
K22: =IF(OR(E22="",H22="",J22=""),"",E22*H22*J22)
K23: =IF(OR(E23="",H23="",J23=""),"",E23*H23*J23)
K24: =IF(OR(E24="",H24="",J24=""),"",E24*H24*J24)
K25: =IF(OR(E25="",H25="",J25=""),"",E25*H25*J25)
K26: =IF(OR(E26="",H26="",J26=""),"",E26*H26*J26)
K27: =IF(OR(E27="",H27="",J27=""),"",E27*H27*J27)
K28: =IF(OR(E28="",H28="",J28=""),"",E28*H28*J28)
K29: =IF(OR(E29="",H29="",J29=""),"",E29*H29*J29)
K30: =IF(OR(E30="",H30="",J30=""),"",E30*H30*J30)
K31: =IF(OR(E31="",H31="",J31=""),"",E31*H31*J31)
... K1000: =IF(OR(E1000="",H1000="",J1000=""),"",E1000*H1000*J1000)

Sheet TB_Hotel_Accruals
A1: MODULE: HOTEL ACCRUALS | L1: 🏠 Back to Home
A2: Cost provisions for hotel stays. Linked to bookings via Booking_Ref. Auto-converts FX to EGP.
A3: Accrual_ID | B3: Booking_Ref | C3: Hotel_ID | D3: Hotel_Name | E3: Check_Out_Date | F3: Currency | G3: Cost_Foreign | H3: CBE_Rate | I3: Provision_EGP | J3: Status
A4: ACR-0001 | B4: HRG-2026-0815 | C4: =IFERROR(INDEX(TB_Master_Bookings!$O$4:$O$1000,MATCH(B4,TB_Master_Bookings!$A$4:$A$1000,0)),"") -> HTL-001 | D4: =IF(C4="","",IFERROR(INDEX(TB_Hotels_Master!$B$4:$B$1000,MATCH(C4,TB_Hotels_Master!$A$4:$A$1000,0)),"HOTEL NOT FOUND")) -> Steigenberger Aldau Beach | E4: 2026-08-08 | F4: EUR | G4: =IFERROR(INDEX(TB_Master_Bookings!$H$4:$H$1000,MATCH(B4,TB_Master_Bookings!$A$4:$A$1000,0))*INDEX(TB_Master_Bookings!$E$4:$E$1000,MATCH(B4,TB_Master_Bookings!$A$4:$A$1000,0))*INDEX(TB_Hotels_Master!$H$4:$H$1000,MATCH(C4,TB_Hotels_Master!$A$4:$A$1000,0)),0) -> 100800 | H4: =IFERROR(INDEX(TB_Master_Bookings!$L$4:$L$1000,MATCH(B4,TB_Master_Bookings!$A$4:$A$1000,0)),0) -> 53.35 | I4: =G4*H4 -> 5377680 | J4: Posted
A5: ACR-0002 | B5: HRG-2026-0816 | C5: =IFERROR(INDEX(TB_Master_Bookings!$O$4:$O$1000,MATCH(B5,TB_Master_Bookings!$A$4:$A$1000,0)),"") -> HTL-002 | D5: =IF(C5="","",IFERROR(INDEX(TB_Hotels_Master!$B$4:$B$1000,MATCH(C5,TB_Hotels_Master!$A$4:$A$1000,0)),"HOTEL NOT FOUND")) -> Jaz Aquamarine Resort | E5: 2026-08-09 | F5: EUR | G5: =IFERROR(INDEX(TB_Master_Bookings!$H$4:$H$1000,MATCH(B5,TB_Master_Bookings!$A$4:$A$1000,0))*INDEX(TB_Master_Bookings!$E$4:$E$1000,MATCH(B5,TB_Master_Bookings!$A$4:$A$1000,0))*INDEX(TB_Hotels_Master!$H$4:$H$1000,MATCH(C5,TB_Hotels_Master!$A$4:$A$1000,0)),0) -> 20475 | H5: =IFERROR(INDEX(TB_Master_Bookings!$L$4:$L$1000,MATCH(B5,TB_Master_Bookings!$A$4:$A$1000,0)),0) -> 49.12 | I5: =G5*H5 -> 1005732 | J5: Posted
A6: ACR-0003 | B6: HRG-2026-0817 | C6: =IFERROR(INDEX(TB_Master_Bookings!$O$4:$O$1000,MATCH(B6,TB_Master_Bookings!$A$4:$A$1000,0)),"") -> HTL-003 | D6: =IF(C6="","",IFERROR(INDEX(TB_Hotels_Master!$B$4:$B$1000,MATCH(C6,TB_Hotels_Master!$A$4:$A$1000,0)),"HOTEL NOT FOUND")) -> Sunrise Grand Select | E6: 2026-08-10 | F6: EUR | G6: =IFERROR(INDEX(TB_Master_Bookings!$H$4:$H$1000,MATCH(B6,TB_Master_Bookings!$A$4:$A$1000,0))*INDEX(TB_Master_Bookings!$E$4:$E$1000,MATCH(B6,TB_Master_Bookings!$A$4:$A$1000,0))*INDEX(TB_Hotels_Master!$H$4:$H$1000,MATCH(C6,TB_Hotels_Master!$A$4:$A$1000,0)),0) -> 13020 | H6: =IFERROR(INDEX(TB_Master_Bookings!$L$4:$L$1000,MATCH(B6,TB_Master_Bookings!$A$4:$A$1000,0)),0) -> 62.3 | I6: =G6*H6 -> 811146 | J6: Posted
A7: ACR-0004 | B7: HRG-2026-0818 | C7: =IFERROR(INDEX(TB_Master_Bookings!$O$4:$O$1000,MATCH(B7,TB_Master_Bookings!$A$4:$A$1000,0)),"") -> HTL-004 | D7: =IF(C7="","",IFERROR(INDEX(TB_Hotels_Master!$B$4:$B$1000,MATCH(C7,TB_Hotels_Master!$A$4:$A$1000,0)),"HOTEL NOT FOUND")) -> Pickalbatros Aqua Blu | E7: 2026-08-07 | F7: EUR | G7: =IFERROR(INDEX(TB_Master_Bookings!$H$4:$H$1000,MATCH(B7,TB_Master_Bookings!$A$4:$A$1000,0))*INDEX(TB_Master_Bookings!$E$4:$E$1000,MATCH(B7,TB_Master_Bookings!$A$4:$A$1000,0))*INDEX(TB_Hotels_Master!$H$4:$H$1000,MATCH(C7,TB_Hotels_Master!$A$4:$A$1000,0)),0) -> 17280 | H7: =IFERROR(INDEX(TB_Master_Bookings!$L$4:$L$1000,MATCH(B7,TB_Master_Bookings!$A$4:$A$1000,0)),0) -> 53.4 | I7: =G7*H7 -> 922752 | J7: Posted
A8: ACR-0005 | B8: HRG-2026-0819 | C8: =IFERROR(INDEX(TB_Master_Bookings!$O$4:$O$1000,MATCH(B8,TB_Master_Bookings!$A$4:$A$1000,0)),"") -> HTL-005 | D8: =IF(C8="","",IFERROR(INDEX(TB_Hotels_Master!$B$4:$B$1000,MATCH(C8,TB_Hotels_Master!$A$4:$A$1000,0)),"HOTEL NOT FOUND")) -> Sunny Days El Palacio | E8: 2026-08-09 | F8: EUR | G8: =IFERROR(INDEX(TB_Master_Bookings!$H$4:$H$1000,MATCH(B8,TB_Master_Bookings!$A$4:$A$1000,0))*INDEX(TB_Master_Bookings!$E$4:$E$1000,MATCH(B8,TB_Master_Bookings!$A$4:$A$1000,0))*INDEX(TB_Hotels_Master!$H$4:$H$1000,MATCH(C8,TB_Hotels_Master!$A$4:$A$1000,0)),0) -> 2520 | H8: =IFERROR(INDEX(TB_Master_Bookings!$L$4:$L$1000,MATCH(B8,TB_Master_Bookings!$A$4:$A$1000,0)),0) -> 49.12 | I8: =G8*H8 -> 123782.4 | J8: Posted
A9: ACC-0001 | B9: MBR-2026-0001 | C9: =IFERROR(INDEX(TB_Master_Bookings!$O$4:$O$1000,MATCH(B9,TB_Master_Bookings!$A$4:$A$1000,0)),"") -> HTL-006 | D9: =IF(C9="","",IFERROR(INDEX(TB_Hotels_Master!$B$4:$B$1000,MATCH(C9,TB_Hotels_Master!$A$4:$A$1000,0)),"HOTEL NOT FOUND")) -> Sun & Sea Beach Resort | E9: 2026-08-22 | F9: EUR | G9: =IFERROR(INDEX(TB_Master_Bookings!$H$4:$H$1000,MATCH(B9,TB_Master_Bookings!$A$4:$A$1000,0))*INDEX(TB_Master_Bookings!$E$4:$E$1000,MATCH(B9,TB_Master_Bookings!$A$4:$A$1000,0))*INDEX(TB_Hotels_Master!$H$4:$H$1000,MATCH(C9,TB_Hotels_Master!$A$4:$A$1000,0)),0) -> 106400 | H9: =IFERROR(INDEX(TB_Master_Bookings!$L$4:$L$1000,MATCH(B9,TB_Master_Bookings!$A$4:$A$1000,0)),0) -> 54.2 | I9: =G9*H9 -> 5766880 | J9: Posted
A10: ACC-0002 | B10: MBR-2026-0002 | C10: =IFERROR(INDEX(TB_Master_Bookings!$O$4:$O$1000,MATCH(B10,TB_Master_Bookings!$A$4:$A$1000,0)),"") -> HTL-007 | D10: =IF(C10="","",IFERROR(INDEX(TB_Hotels_Master!$B$4:$B$1000,MATCH(C10,TB_Hotels_Master!$A$4:$A$1000,0)),"HOTEL NOT FOUND")) -> Coral Hills Resort | E10: 2026-08-22 | F10: USD | G10: =IFERROR(INDEX(TB_Master_Bookings!$H$4:$H$1000,MATCH(B10,TB_Master_Bookings!$A$4:$A$1000,0))*INDEX(TB_Master_Bookings!$E$4:$E$1000,MATCH(B10,TB_Master_Bookings!$A$4:$A$1000,0))*INDEX(TB_Hotels_Master!$H$4:$H$1000,MATCH(C10,TB_Hotels_Master!$A$4:$A$1000,0)),0) -> 19320 | H10: =IFERROR(INDEX(TB_Master_Bookings!$L$4:$L$1000,MATCH(B10,TB_Master_Bookings!$A$4:$A$1000,0)),0) -> 49.3 | I10: =G10*H10 -> 952476 | J10: Posted
A11: ACC-0003 | B11: MBR-2026-0003 | C11: =IFERROR(INDEX(TB_Master_Bookings!$O$4:$O$1000,MATCH(B11,TB_Master_Bookings!$A$4:$A$1000,0)),"") -> HTL-008 | D11: =IF(C11="","",IFERROR(INDEX(TB_Hotels_Master!$B$4:$B$1000,MATCH(C11,TB_Hotels_Master!$A$4:$A$1000,0)),"HOTEL NOT FOUND")) -> Blue Lagoon Palace | E11: 2026-08-24 | F11: GBP | G11: =IFERROR(INDEX(TB_Master_Bookings!$H$4:$H$1000,MATCH(B11,TB_Master_Bookings!$A$4:$A$1000,0))*INDEX(TB_Master_Bookings!$E$4:$E$1000,MATCH(B11,TB_Master_Bookings!$A$4:$A$1000,0))*INDEX(TB_Hotels_Master!$H$4:$H$1000,MATCH(C11,TB_Hotels_Master!$A$4:$A$1000,0)),0) -> 17408 | H11: =IFERROR(INDEX(TB_Master_Bookings!$L$4:$L$1000,MATCH(B11,TB_Master_Bookings!$A$4:$A$1000,0)),0) -> 63.25 | I11: =G11*H11 -> 1101056 | J11: Posted
A12: ACC-0004 | B12: MBR-2026-0004 | C12: =IFERROR(INDEX(TB_Master_Bookings!$O$4:$O$1000,MATCH(B12,TB_Master_Bookings!$A$4:$A$1000,0)),"") -> HTL-009 | D12: =IF(C12="","",IFERROR(INDEX(TB_Hotels_Master!$B$4:$B$1000,MATCH(C12,TB_Hotels_Master!$A$4:$A$1000,0)),"HOTEL NOT FOUND")) -> Desert Rose Plaza | E12: 2026-08-22 | F12: USD | G12: =IFERROR(INDEX(TB_Master_Bookings!$H$4:$H$1000,MATCH(B12,TB_Master_Bookings!$A$4:$A$1000,0))*INDEX(TB_Master_Bookings!$E$4:$E$1000,MATCH(B12,TB_Master_Bookings!$A$4:$A$1000,0))*INDEX(TB_Hotels_Master!$H$4:$H$1000,MATCH(C12,TB_Hotels_Master!$A$4:$A$1000,0)),0) -> 33600 | H12: =IFERROR(INDEX(TB_Master_Bookings!$L$4:$L$1000,MATCH(B12,TB_Master_Bookings!$A$4:$A$1000,0)),0) -> 49.3 | I12: =G12*H12 -> 1656480 | J12: Posted
A13: ACC-0005 | B13: MBR-2026-0005 | C13: =IFERROR(INDEX(TB_Master_Bookings!$O$4:$O$1000,MATCH(B13,TB_Master_Bookings!$A$4:$A$1000,0)),"") -> HTL-010 | D13: =IF(C13="","",IFERROR(INDEX(TB_Hotels_Master!$B$4:$B$1000,MATCH(C13,TB_Hotels_Master!$A$4:$A$1000,0)),"HOTEL NOT FOUND")) -> Seagull Beach Resort | E13: 2026-08-25 | F13: EUR | G13: =IFERROR(INDEX(TB_Master_Bookings!$H$4:$H$1000,MATCH(B13,TB_Master_Bookings!$A$4:$A$1000,0))*INDEX(TB_Master_Bookings!$E$4:$E$1000,MATCH(B13,TB_Master_Bookings!$A$4:$A$1000,0))*INDEX(TB_Hotels_Master!$H$4:$H$1000,MATCH(C13,TB_Hotels_Master!$A$4:$A$1000,0)),0) -> 30940 | H13: =IFERROR(INDEX(TB_Master_Bookings!$L$4:$L$1000,MATCH(B13,TB_Master_Bookings!$A$4:$A$1000,0)),0) -> 54.4 | I13: =G13*H13 -> 1683136 | J13: Posted

Sheet TB_Excursions_Sales
A1: MODULE: EXCURSIONS SALES | T1: 🏠 Back to Home
A2: Daily excursion tickets sold by reps. Auto-calculates commission and EGP equivalent.
A3: Ticket_ID | B3: Sale_Date | C3: Rep_ID | D3: Guest_Name | E3: Hotel | F3: Excursion_Type | G3: Currency | H3: Pax_Qty | I3: Unit_Price_FX | J3: Sale_Amount_FX | K3: CBE_Rate | L3: Sale_Amount_EGP | M3: Payment_Method | N3: Commission_Pct | O3: Rep_Commission_FX | P3: Rep_Commission_EGP | Q3: Deposit_Status | R3: Client_ID (linked)
A4: TCK-1001 | B4: 2026-08-08 | C4: REP-01 | D4: Hans Gruber | E4: Steigenberger Aldau Beach | F4: Luxor Full Day | G4: USD | H4: 1 | I4: 65 | J4: =H4*I4 -> 65 | K4: 49.08 | L4: =J4*K4 -> 3190.2 | M4: Cash | N4: 0.1 | O4: =J4*N4 -> 6.5 | P4: =O4*K4 -> 319.02 | Q4: Deposited | R4: =IFERROR(INDEX(TB_Master_Bookings!$B$4:$B$1000,MATCH(INDEX(TB_Hotels_Master!$A$4:$A$1000,MATCH(E4,TB_Hotels_Master!$B$4:$B$1000,0)),TB_Master_Bookings!$O$4:$O$1000,0)),"") -> CLI-001
A5: TCK-1002 | B5: 2026-08-08 | C5: REP-01 | D5: Ingrid Berg | E5: Steigenberger Aldau Beach | F5: Sea Trip Snorkeling | G5: USD | H5: 1 | I5: 35 | J5: =H5*I5 -> 35 | K5: 49.08 | L5: =J5*K5 -> 1717.8 | M5: POS | N5: 0.12 | O5: =J5*N5 -> 4.2 | P5: =O5*K5 -> 206.136 | Q5: POS Settlement | R5: =IFERROR(INDEX(TB_Master_Bookings!$B$4:$B$1000,MATCH(INDEX(TB_Hotels_Master!$A$4:$A$1000,MATCH(E5,TB_Hotels_Master!$B$4:$B$1000,0)),TB_Master_Bookings!$O$4:$O$1000,0)),"") -> CLI-001
A6: TCK-1003 | B6: 2026-08-08 | C6: REP-02 | D6: Marco Rossi | E6: Jaz Aquamarine Resort | F6: Desert Safari | G6: USD | H6: 1 | I6: 45 | J6: =H6*I6 -> 45 | K6: 49.08 | L6: =J6*K6 -> 2208.6 | M6: Cash | N6: 0.1 | O6: =J6*N6 -> 4.5 | P6: =O6*K6 -> 220.86 | Q6: Deposited | R6: =IFERROR(INDEX(TB_Master_Bookings!$B$4:$B$1000,MATCH(INDEX(TB_Hotels_Master!$A$4:$A$1000,MATCH(E6,TB_Hotels_Master!$B$4:$B$1000,0)),TB_Master_Bookings!$O$4:$O$1000,0)),"") -> CLI-002
A7: TCK-1004 | B7: 2026-08-08 | C7: REP-02 | D7: Lena Weber | E7: Jaz Aquamarine Resort | F7: Luxor Full Day | G7: USD | H7: 1 | I7: 65 | J7: =H7*I7 -> 65 | K7: 49.08 | L7: =J7*K7 -> 3190.2 | M7: POS | N7: 0.1 | O7: =J7*N7 -> 6.5 | P7: =O7*K7 -> 319.02 | Q7: POS Settlement | R7: =IFERROR(INDEX(TB_Master_Bookings!$B$4:$B$1000,MATCH(INDEX(TB_Hotels_Master!$A$4:$A$1000,MATCH(E7,TB_Hotels_Master!$B$4:$B$1000,0)),TB_Master_Bookings!$O$4:$O$1000,0)),"") -> CLI-002
A8: TCK-1005 | B8: 2026-08-08 | C8: REP-03 | D8: James Cole | E8: Sunrise Grand Select | F8: Sea Trip Snorkeling | G8: GBP | H8: 1 | I8: 35 | J8: =H8*I8 -> 35 | K8: 62.15 | L8: =J8*K8 -> 2175.25 | M8: Cash | N8: 0.12 | O8: =J8*N8 -> 4.2 | P8: =O8*K8 -> 261.03 | Q8: Deposited | R8: =IFERROR(INDEX(TB_Master_Bookings!$B$4:$B$1000,MATCH(INDEX(TB_Hotels_Master!$A$4:$A$1000,MATCH(E8,TB_Hotels_Master!$B$4:$B$1000,0)),TB_Master_Bookings!$O$4:$O$1000,0)),"") -> CLI-003
A9: TCK-1006 | B9: 2026-08-08 | C9: REP-01 | D9: Otto Frank | E9: Steigenberger Aldau Beach | F9: Quad Bike Safari | G9: USD | H9: 1 | I9: 45 | J9: =H9*I9 -> 45 | K9: 49.08 | L9: =J9*K9 -> 2208.6 | M9: Cash | N9: 0.1 | O9: =J9*N9 -> 4.5 | P9: =O9*K9 -> 220.86 | Q9: Deposited | R9: =IFERROR(INDEX(TB_Master_Bookings!$B$4:$B$1000,MATCH(INDEX(TB_Hotels_Master!$A$4:$A$1000,MATCH(E9,TB_Hotels_Master!$B$4:$B$1000,0)),TB_Master_Bookings!$O$4:$O$1000,0)),"") -> CLI-001
A10: TCK-1007 | B10: 2026-08-08 | C10: REP-04 | D10: Sara Nilsson | E10: Pickalbatros Aqua Blu | F10: Desert Safari | G10: EUR | H10: 1 | I10: 45 | J10: =H10*I10 -> 45 | K10: 53.35 | L10: =J10*K10 -> 2400.75 | M10: POS | N10: 0.1 | O10: =J10*N10 -> 4.5 | P10: =O10*K10 -> 240.075 | Q10: POS Settlement | R10: =IFERROR(INDEX(TB_Master_Bookings!$B$4:$B$1000,MATCH(INDEX(TB_Hotels_Master!$A$4:$A$1000,MATCH(E10,TB_Hotels_Master!$B$4:$B$1000,0)),TB_Master_Bookings!$O$4:$O$1000,0)),"") -> CLI-004
A11: TCK-1008 | B11: 2026-08-08 | C11: REP-02 | D11: Tom Baker | E11: Jaz Aquamarine Resort | F11: Sea Trip Snorkeling | G11: USD | H11: 1 | I11: 35 | J11: =H11*I11 -> 35 | K11: 49.08 | L11: =J11*K11 -> 1717.8 | M11: Cash | N11: 0.12 | O11: =J11*N11 -> 4.2 | P11: =O11*K11 -> 206.136 | Q11: Deposited | R11: =IFERROR(INDEX(TB_Master_Bookings!$B$4:$B$1000,MATCH(INDEX(TB_Hotels_Master!$A$4:$A$1000,MATCH(E11,TB_Hotels_Master!$B$4:$B$1000,0)),TB_Master_Bookings!$O$4:$O$1000,0)),"") -> CLI-002
A12: TCK-1009 | B12: 2026-08-08 | C12: REP-03 | D12: Alice Wu | E12: Sunrise Grand Select | F12: Luxor Full Day | G12: GBP | H12: 1 | I12: 65 | J12: =H12*I12 -> 65 | K12: 62.15 | L12: =J12*K12 -> 4039.75 | M12: POS | N12: 0.1 | O12: =J12*N12 -> 6.5 | P12: =O12*K12 -> 403.975 | Q12: POS Settlement | R12: =IFERROR(INDEX(TB_Master_Bookings!$B$4:$B$1000,MATCH(INDEX(TB_Hotels_Master!$A$4:$A$1000,MATCH(E12,TB_Hotels_Master!$B$4:$B$1000,0)),TB_Master_Bookings!$O$4:$O$1000,0)),"") -> CLI-003
A13: TCK-1010 | B13: 2026-08-08 | C13: REP-04 | D13: Karl Braun | E13: Pickalbatros Aqua Blu | F13: Quad Bike Safari | G13: EUR | H13: 1 | I13: 45 | J13: =H13*I13 -> 45 | K13: 53.35 | L13: =J13*K13 -> 2400.75 | M13: Cash | N13: 0.1 | O13: =J13*N13 -> 4.5 | P13: =O13*K13 -> 240.075 | Q13: Deposited | R13: =IFERROR(INDEX(TB_Master_Bookings!$B$4:$B$1000,MATCH(INDEX(TB_Hotels_Master!$A$4:$A$1000,MATCH(E13,TB_Hotels_Master!$B$4:$B$1000,0)),TB_Master_Bookings!$O$4:$O$1000,0)),"") -> CLI-004
A14: TKT-1001 | B14: 2026-08-16 | C14: REP-HRG-01 | D14: Anna Schmidt | E14: Sun & Sea Beach Resort | F14: Sea Trip | G14: EUR | H14: 1 | I14: 35 | J14: =H14*I14 -> 35 | K14: 53.85 | L14: =J14*K14 -> 1884.75 | M14: Cash | N14: 0.12 | O14: =J14*N14 -> 4.2 | P14: =O14*K14 -> 226.17 | Q14: Deposited | R14: =IFERROR(INDEX(TB_Master_Bookings!$B$4:$B$1000,MATCH(INDEX(TB_Hotels_Master!$A$4:$A$1000,MATCH(E14,TB_Hotels_Master!$B$4:$B$1000,0)),TB_Master_Bookings!$O$4:$O$1000,0)),"") -> CLI-006
A15: TKT-1002 | B15: 2026-08-16 | C15: REP-HRG-01 | D15: Mark Weber | E15: Sun & Sea Beach Resort | F15: Sea Trip | G15: EUR | H15: 1 | I15: 35 | J15: =H15*I15 -> 35 | K15: 53.85 | L15: =J15*K15 -> 1884.75 | M15: POS | N15: 0.12 | O15: =J15*N15 -> 4.2 | P15: =O15*K15 -> 226.17 | Q15: POS Settlement | R15: =IFERROR(INDEX(TB_Master_Bookings!$B$4:$B$1000,MATCH(INDEX(TB_Hotels_Master!$A$4:$A$1000,MATCH(E15,TB_Hotels_Master!$B$4:$B$1000,0)),TB_Master_Bookings!$O$4:$O$1000,0)),"") -> CLI-006
... A20: TKT-1007 | B20: 2026-08-16 | C20: REP-HRG-01 | D20: Laura Becker | E20: Sun & Sea Beach Resort | F20: Luxor | G20: EUR | H20: 1 | I20: 65 | J20: =H20*I20 -> 65 | K20: 53.85 | L20: =J20*K20 -> 3500.25 | M20: Cash | N20: 0.1 | O20: =J20*N20 -> 6.5 | P20: =O20*K20 -> 350.025 | Q20: Deposited | R20: =IFERROR(INDEX(TB_Master_Bookings!$B$4:$B$1000,MATCH(INDEX(TB_Hotels_Master!$A$4:$A$1000,MATCH(E20,TB_Hotels_Master!$B$4:$B$1000,0)),TB_Master_Bookings!$O$4:$O$1000,0)),"") -> CLI-006
A21: TKT-1008 | B21: 2026-08-16 | C21: REP-HRG-01 | D21: Paul Wagner | E21: Sun & Sea Beach Resort | F21: Sea Trip | G21: EUR | H21: 1 | I21: 35 | J21: =H21*I21 -> 35 | K21: 53.85 | L21: 1884.75 | M21: POS | N21: 0.12 | O21: =J21*N21 -> 4.2 | P21: =O21*K21 -> 226.17 | Q21: POS Settlement | R21: =IFERROR(INDEX(TB_Master_Bookings!$B$4:$B$1000,MATCH(INDEX(TB_Hotels_Master!$A$4:$A$1000,MATCH(E21,TB_Hotels_Master!$B$4:$B$1000,0)),TB_Master_Bookings!$O$4:$O$1000,0)),"") -> CLI-006

Sheet TB_Cash_Rep_Reconciliation
A1: MODULE: CASH RECONCILIATION | L1: 🏠 Back to Home
A2: Daily cash reconciliation per rep. Expected = Cash + POS - Commission. Variance = Actual - Expected.
A3: Reconciliation_ID | B3: Rep_ID | C3: Business_Date | D3: Total_Cash_Collected_EGP | E3: POS_Amount_EGP | F3: Commission_Deducted_EGP | G3: Expected_Net_Cash_EGP | H3: Actual_Net_Cash_Deposited_EGP | I3: Variance_EGP | J3: Status
A4: REC-0001 | B4: REP-01 | C4: 2026-08-08 | D4: 7607.4 | E4: 2208.6 | F4: 1074.85 | G4: =D4+E4-F4 -> 8741.15 | H4: 8920 | I4: =H4-G4 -> 178.85 | J4: Exception
A5: REC-0002 | B5: REP-02 | C5: 2026-08-08 | D5: 4908 | E5: 4662.6 | F5: 1050.31 | G5: =D5+E5-F5 -> 8520.29 | H5: 8520.29 | I5: =H5-G5 -> 0 | J5: Reconciled
A6: REC-0003 | B6: REP-03 | C6: 2026-08-08 | D6: 2486 | E6: 4972 | F6: 845.24 | G6: =D6+E6-F6 -> 6612.76 | H6: 6612.76 | I6: =H6-G6 -> 0 | J6: Reconciled
A7: REC-0004 | B7: REP-04 | C7: 2026-08-08 | D7: 2934.25 | E7: 2667.5 | F7: 560.18 | G7: =D7+E7-F7 -> 5041.57 | H7: 5041.57 | I7: =H7-G7 -> 0 | J7: Reconciled
A8: REC-0005 | B8: REP-HRG-01 | C8: 2026-08-16 | D8: 7808.25 | E8: 3769.5 | F8: 1200.86 | G8: =D8+E8-F8 -> 10376.89 | H8: 10600 | I8: =H8-G8 -> 223.11 | J8: Exception
A9: REC-0006 | B9: REP-HRG-02 | C9: 2026-08-17 | D9: 4312 | E9: 3503.5 | F9: 749.21 | G9: =D9+E9-F9 -> 7066.29 | H9: 7066.29 | I9: =H9-G9 -> 0 | J9: Reconciled
A10: REC-0007 | B10: REP-HRG-03 | C10: 2026-08-18 | D10: 2500 | E10: 1200 | F10: 300 | G10: =D10+E10-F10 -> 3400 | H10: 3400 | I10: =H10-G10 -> 0 | J10: Reconciled

Sheet TB_AP_Invoices
A1: MODULE: ACCOUNTS PAYABLE - INVOICES | P1: 🏠 Back to Home
A2: Supplier invoices for hotels, transport, and excursions. Linked to bookings and accruals.
A3: Invoice_ID | B3: Supplier_ID | C3: Supplier_Name | D3: Invoice_Type | E3: Invoice_Date | F3: Due_Date | G3: Booking_Ref | H3: Currency | I3: Amount_FX | J3: CBE_Rate | K3: Amount_EGP | L3: VAT_Amount_EGP | M3: Total_EGP | N3: Status
A4: AP-0001 | B4: =IFERROR(INDEX(TB_Hotels_Master!$O$4:$O$1000,MATCH(INDEX(TB_Hotel_Accruals!$C$4:$C$1000,MATCH(G4,TB_Hotel_Accruals!$B$4:$B$1000,0)),TB_Hotels_Master!$A$4:$A$1000,0)),"") -> SUP-HTL-001 | C4: =IF(B4="","",IFERROR(INDEX(TB_Suppliers_Master!$B$4:$B$1000,MATCH(B4,TB_Suppliers_Master!$A$4:$A$1000,0)),"INVALID SUPPLIER ID")) -> Steigenberger Aldau Beach | D4: Hotel | E4: 2026-08-09 | F4: 2026-09-08 | G4: HRG-2026-0815 | H4: EUR | I4: =IFERROR(INDEX(TB_Hotel_Accruals!$G$4:$G$1000,MATCH(G4,TB_Hotel_Accruals!$B$4:$B$1000,0)),0) -> 100800 | J4: 53.35 | K4: =M4/1.14 -> 4717263.2 | L4: =M4-K4 -> 660416.84 | M4: =I4*J4 -> 5377680 | N4: Pending
A5: AP-0002 | B5: =IFERROR(INDEX(TB_Hotels_Master!$O$4:$O$1000,MATCH(INDEX(TB_Hotel_Accruals!$C$4:$C$1000,MATCH(G5,TB_Hotel_Accruals!$B$4:$B$1000,0)),TB_Hotels_Master!$A$4:$A$1000,0)),"") -> SUP-HTL-002 | C5: =IF(B5="","",IFERROR(INDEX(TB_Suppliers_Master!$B$4:$B$1000,MATCH(B5,TB_Suppliers_Master!$A$4:$A$1000,0)),"INVALID SUPPLIER ID")) -> Jaz Aquamarine Resort | D5: Hotel | E5: 2026-08-10 | F5: 2026-09-09 | G5: HRG-2026-0816 | H5: USD | I5: =IFERROR(INDEX(TB_Hotel_Accruals!$G$4:$G$1000,MATCH(G5,TB_Hotel_Accruals!$B$4:$B$1000,0)),0) -> 20475 | J5: 49.12 | K5: =M5/1.14 -> 882221.05 | L5: =M5-K5 -> 123510.95 | M5: =I5*J5 -> 1005732 | N5: Pending
A6: AP-0003 | B6: =IFERROR(INDEX(TB_Hotels_Master!$O$4:$O$1000,MATCH(INDEX(TB_Hotel_Accruals!$C$4:$C$1000,MATCH(G6,TB_Hotel_Accruals!$B$4:$B$1000,0)),TB_Hotels_Master!$A$4:$A$1000,0)),"") -> SUP-HTL-003 | C6: =IF(B6="","",IFERROR(INDEX(TB_Suppliers_Master!$B$4:$B$1000,MATCH(B6,TB_Suppliers_Master!$A$4:$A$1000,0)),"INVALID SUPPLIER ID")) -> Sunrise Grand Select | D6: Hotel | E6: 2026-08-11 | F6: 2026-09-25 | G6: HRG-2026-0817 | H6: GBP | I6: =IFERROR(INDEX(TB_Hotel_Accruals!$G$4:$G$1000,MATCH(G6,TB_Hotel_Accruals!$B$4:$B$1000,0)),0) -> 13020 | J6: 62.3 | K6: =M6/1.14 -> 711531.58 | L6: =M6-K6 -> 99614.421 | M6: =I6*J6 -> 811146 | N6: Pending
A7: AP-0004 | B7: =IFERROR(INDEX(TB_Hotels_Master!$O$4:$O$1000,MATCH(INDEX(TB_Hotel_Accruals!$C$4:$C$1000,MATCH(G7,TB_Hotel_Accruals!$B$4:$B$1000,0)),TB_Hotels_Master!$A$4:$A$1000,0)),"") -> SUP-HTL-004 | C7: =IF(B7="","",IFERROR(INDEX(TB_Suppliers_Master!$B$4:$B$1000,MATCH(B7,TB_Suppliers_Master!$A$4:$A$1000,0)),"INVALID SUPPLIER ID")) -> Sun & Sea Beach Resort | D7: Hotel | E7: 2026-08-23 | F7: 2026-09-22 | G7: MBR-2026-0001 | H7: EUR | I7: =IFERROR(INDEX(TB_Hotel_Accruals!$G$4:$G$1000,MATCH(G7,TB_Hotel_Accruals!$B$4:$B$1000,0)),0) -> 106400 | J7: 54.2 | K7: =M7/1.14 -> 5058666.7 | L7: =M7-K7 -> 708213.33 | M7: =I7*J7 -> 5766880 | N7: Pending
A8: AP-0005 | B8: =IFERROR(INDEX(TB_Hotels_Master!$O$4:$O$1000,MATCH(INDEX(TB_Hotel_Accruals!$C$4:$C$1000,MATCH(G8,TB_Hotel_Accruals!$B$4:$B$1000,0)),TB_Hotels_Master!$A$4:$A$1000,0)),"") -> SUP-HTL-005 | C8: =IF(B8="","",IFERROR(INDEX(TB_Suppliers_Master!$B$4:$B$1000,MATCH(B8,TB_Suppliers_Master!$A$4:$A$1000,0)),"INVALID SUPPLIER ID")) -> Coral Hills Resort | D8: Hotel | E8: 2026-08-23 | F8: 2026-09-22 | G8: MBR-2026-0002 | H8: USD | I8: =IFERROR(INDEX(TB_Hotel_Accruals!$G$4:$G$1000,MATCH(G8,TB_Hotel_Accruals!$B$4:$B$1000,0)),0) -> 19320 | J8: 49.3 | K8: =M8/1.14 -> 835505.26 | L8: =M8-K8 -> 116970.74 | M8: =I8*J8 -> 952476 | N8: Pending
A9: AP-0006 | B9: =IFERROR(INDEX(TB_Hotels_Master!$O$4:$O$1000,MATCH(INDEX(TB_Hotel_Accruals!$C$4:$C$1000,MATCH(G9,TB_Hotel_Accruals!$B$4:$B$1000,0)),TB_Hotels_Master!$A$4:$A$1000,0)),"") -> SUP-HTL-006 | C9: =IF(B9="","",IFERROR(INDEX(TB_Suppliers_Master!$B$4:$B$1000,MATCH(B9,TB_Suppliers_Master!$A$4:$A$1000,0)),"INVALID SUPPLIER ID")) -> Blue Lagoon Palace | D9: Hotel | E9: 2026-08-25 | F9: 2026-10-09 | G9: MBR-2026-0003 | H9: GBP | I9: =IFERROR(INDEX(TB_Hotel_Accruals!$G$4:$G$1000,MATCH(G9,TB_Hotel_Accruals!$B$4:$B$1000,0)),0) -> 17408 | J9: 63.25 | K9: =M9/1.14 -> 965838.6 | L9: =M9-K9 -> 135217.4 | M9: =I9*J9 -> 1101056 | N9: Pending
A10: AP-0007 | B10: =IFERROR(INDEX(TB_Hotels_Master!$O$4:$O$1000,MATCH(INDEX(TB_Hotel_Accruals!$C$4:$C$1000,MATCH(G10,TB_Hotel_Accruals!$B$4:$B$1000,0)),TB_Hotels_Master!$A$4:$A$1000,0)),"") -> SUP-HTL-007 | C10: =IF(B10="","",IFERROR(INDEX(TB_Suppliers_Master!$B$4:$B$1000,MATCH(B10,TB_Suppliers_Master!$A$4:$A$1000,0)),"INVALID SUPPLIER ID")) -> Desert Rose Plaza | D10: Hotel | E10: 2026-08-23 | F10: 2026-09-22 | G10: MBR-2026-0004 | H10: USD | I10: =IFERROR(INDEX(TB_Hotel_Accruals!$G$4:$G$1000,MATCH(G10,TB_Hotel_Accruals!$B$4:$B$1000,0)),0) -> 33600 | J10: 49.3 | K10: =M10/1.14 -> 1453052.6 | L10: =M10-K10 -> 203427.37 | M10: =I10*J10 -> 1656480 | N10: Pending
A11: AP-0008 | B11: =IFERROR(INDEX(TB_Hotels_Master!$O$4:$O$1000,MATCH(INDEX(TB_Hotel_Accruals!$C$4:$C$1000,MATCH(G11,TB_Hotel_Accruals!$B$4:$B$1000,0)),TB_Hotels_Master!$A$4:$A$1000,0)),"") -> SUP-HTL-008 | C11: =IF(B11="","",IFERROR(INDEX(TB_Suppliers_Master!$B$4:$B$1000,MATCH(B11,TB_Suppliers_Master!$A$4:$A$1000,0)),"INVALID SUPPLIER ID")) -> Seagull Beach Resort | D11: Hotel | E11: 2026-08-26 | F11: 2026-09-25 | G11: MBR-2026-0005 | H11: EUR | I11: =IFERROR(INDEX(TB_Hotel_Accruals!$G$4:$G$1000,MATCH(G11,TB_Hotel_Accruals!$B$4:$B$1000,0)),0) -> 30940 | J11: 54.4 | K11: =M11/1.14 -> 1476435.1 | L11: =M11-K11 -> 206700.91 | M11: =I11*J11 -> 1683136 | N11: Pending

Sheet TB_Bank_Reconciliation
A1: MODULE: BANK RECONCILIATION | Q1: 🏠 Back to Home
A2: Match bank statements with journal entries. Auto-flags unmatched items and calculates reconciled balance.
A3: Recon_ID | B3: Bank_Account | C3: Statement_Date | D3: Statement_Balance_FX | E3: FX_Currency | F3: CBE_Rate | G3: Statement_Balance_EGP | H3: GL_Balance_EGP | I3: Difference_EGP | J3: Unmatched_Dr_Count | K3: Unmatched_Cr_Count | L3: Status | M3: Reconciled_By | N3: Recon_Date | O3: Notes
A4: BR-0001 | B4: Bank - FCY Operations (1001) | C4: 2026-08-31 | D4: 26384.21 | E4: USD | F4: 49.4 | G4: 1303380 | H4: 1302560 | I4: 820 | J4: 2 | K4: 1 | L4: Exception | M4: Ahmed Hassan | N4: 2026-09-01 | O4: 2 unmatched deposits, 1 unmatched withdrawal
A5: BR-0002 | B5: Bank Account - EUR (1011) | C5: 2026-08-31 | D5: 124532.71 | E5: EUR | F5: 53.4 | G5: 6650046.7 | H5: 6650000 | I5: 0 | J5: 0 | K5: 0 | L5: Reconciled | M5: Sara Khaled | N5: 2026-09-01 | O5: Perfect match - all items cleared
A6: BR-0003 | B6: Bank - FCY Operations (1001) | C6: 2026-08-25 | D6: 26384.21 | E6: USD | F6: 49.4 | G6: 1303380 | H6: 1302560 | I6: 820 | J6: 2 | K6: 1 | L6: Exception | M6: Ahmed Hassan | N6: 2026-08-26 | O6: Pending bank charges clarification
A7: BR-0004 | B7: Bank Account - EUR (1011) | C7: 2026-08-25 | D7: 124532.71 | E7: EUR | F7: 53.4 | G7: 6650046.7 | H7: 6650000 | I7: 0 | J7: 0 | K7: 0 | L7: Reconciled | M7: Sara Khaled | N7: 2026-08-26 | O7: Weekly reconciliation completed
A8: BR-0005 | B8: Bank - FCY Operations (1001) | C8: 2026-08-15 | D8: 15000 | E8: USD | F8: 49.15 | G8: 737250 | H8: 737250 | I8: 0 | J8: 0 | K8: 0 | L8: Reconciled | M8: Ahmed Hassan | N8: 2026-08-16 | O8: Mid-month check

Sheet TB_Budget_vs_Actual
A1: MODULE: BUDGET VS ACTUAL | O1: 🏠 Back to Home
A2: Monthly budget tracking and variance analysis. Auto-calculates variance % and flags significant deviations (>10%).
A3: Period | B3: Account_Code | C3: Account_Name | D3: Account_Type | E3: Budget_EGP | F3: Actual_EGP | G3: Variance_EGP | H3: Variance_Pct | I3: Status | J3: YTD_Budget_EGP | K3: YTD_Actual_EGP | L3: YTD_Variance_Pct | M3: Notes
A4: 2026-08 | B4: 4000 | C4: Revenue - Package Tours (Bookings) | D4: Revenue | E4: 8000000 | F4: 6615400 | G4: =F4-E4 -> -1384600 | H4: =IF(E4=0,"N/A",G4/E4) -> -0.173075 | I4: =IF(G4>0,"Over Budget",IF(G4<0,"Under Budget","On Target")) -> Under Budget | J4: 8000000 | K4: 6615400 | L4: =IF(J4=0,"N/A",(K4-J4)/J4) -> -0.173075 | M4: August peak season - slightly below target
A5: 2026-08 | B5: 4100 | C5: Revenue - In-Resort Excursions | D5: Revenue | E5: 8000 | F5: 4662.6 | G5: =F5-E5 -> -3337.4 | H5: =IF(E5=0,"N/A",G5/E5) -> -0.417175 | I5: =IF(G5>0,"Over Budget",IF(G5<0,"Under Budget","On Target")) -> Under Budget | J5: 8000 | K5: 4662.6 | L5: =IF(J5=0,"N/A",(K5-J5)/J5) -> -0.417175 | M5: Low excursion sales - weather impact
A6: 2026-08 | B6: 4101 | C6: Revenue - Inbound Packages | D6: Revenue | E6: 3500000 | F6: 2995263.2 | G6: =F6-E6 -> -504736.84 | H6: =IF(E6=0,"N/A",G6/E6) -> -0.14421053 | I6: =IF(G6>0,"Over Budget",IF(G6<0,"Under Budget","On Target")) -> Under Budget | J6: 3500000 | K6: 2995263.2 | L6: =IF(J6=0,"N/A",(K6-J6)/J6) -> -0.14421053 | M6: New clients ramping up
A7: 2026-08 | B7: 4900 | C7: Realized FX Gain | D7: Revenue | E7: 50000 | F7: 34600 | G7: =F7-E7 -> -15400 | H7: =IF(E7=0,"N/A",G7/E7) -> -0.308 | I7: =IF(G7>0,"Over Budget",IF(G7<0,"Under Budget","On Target")) -> Under Budget | J7: 50000 | K7: 34600 | L7: =IF(J7=0,"N/A",(K7-J7)/J7) -> -0.308 | M7: FX volatility lower than forecast
A8: 2026-08 | B8: 5000 | C8: Cost of Sales - Hotel Accommodation | D8: Expense | E8: 25000 | F8: 20273 | G8: =F8-E8 -> -4727 | H8: =IF(E8=0,"N/A",G8/E8) -> -0.18908 | I8: =IF(G8>0,"Over Budget",IF(G8<0,"Under Budget","On Target")) -> Under Budget | J8: 25000 | K8: 20273 | L8: =IF(J8=0,"N/A",(K8-J8)/J8) -> -0.18908 | M8: Within acceptable range
A9: 2026-08 | B9: 5101 | C9: COGS - Hotel Contracts | D9: Expense | E9: 2500000 | F9: 2124640 | G9: =F9-E9 -> -375360 | H9: =IF(E9=0,"N/A",G9/E9) -> -0.150144 | I9: =IF(G9>0,"Over Budget",IF(G9<0,"Under Budget","On Target")) -> Under Budget | J9: 2500000 | K9: 2124640 | L9: =IF(J9=0,"N/A",(K9-J9)/J9) -> -0.150144 | M9: Contract renegotiation pending
A10: 2026-08 | B10: 5300 | C10: Rep Commission Expense | D10: Expense | E10: 800 | F10: 559.51 | G10: =F10-E10 -> -240.49 | H10: =IF(E10=0,"N/A",G10/E10) -> -0.3006125 | I10: =IF(G10>0,"Over Budget",IF(G10<0,"Under Budget","On Target")) -> Under Budget | J10: 800 | K10: 559.51 | L10: =IF(J10=0,"N/A",(K10-J10)/J10) -> -0.3006125 | M10: Commission rate higher than planned
A11: 2026-08 | B11: 5401 | C11: FX Gain/Loss | D11: Expense/Income | E11: 0 | F11: -12600 | G11: =F11-E11 -> -12600 | H11: =IF(E11=0,"N/A",G11/E11) -> N/A | I11: =IF(G11>0,"Over Budget",IF(G11<0,"Under Budget","On Target")) -> Under Budget | J11: 0 | K11: -12600 | L11: =IF(J11=0,"N/A",(K11-J11)/J11) -> N/A | M11: Gain booked - favorable movement
A12: 2026-08 | B12: 2101 | C12: Output VAT Payable (14%) | D12: Liability | E12: 420000 | F12: 419336.84 | G12: =F12-E12 -> -663.16 | H12: =IF(E12=0,"N/A",G12/E12) -> -0.0015789524 | I12: =IF(G12>0,"Over Budget",IF(G12<0,"Under Budget","On Target")) -> Under Budget | J12: 420000 | K12: 419336.84 | L12: =IF(J12=0,"N/A",(K12-J12)/J12) -> -0.0015789524 | M12: VAT tracking accurate
A13: 2026-08 | B13: 2300 | C13: Rep Commission Payable | D13: Liability | E13: 600 | F13: 559.51 | G13: =F13-E13 -> -40.49 | H13: =IF(E13=0,"N/A",G13/E13) -> -0.067483333 | I13: =IF(G13>0,"Over Budget",IF(G13<0,"Under Budget","On Target")) -> Under Budget | J13: 600 | K13: 559.51 | L13: =IF(J13=0,"N/A",(K13-J13)/J13) -> -0.067483333 | M13: Accrued commissions aligned
A14: 2026-08 | B14: 2-3200 | C14: Withholding Tax Payable (3%) | D14: Liability | E14: 0 | F14: 246574.47 | G14: =F14-E14 -> 246574.47 | H14: =IF(E14=0,"N/A",G14/E14) -> N/A | I14: =IF(G14>0,"Over Budget",IF(G14<0,"Under Budget","On Target")) -> Over Budget | J14: 0 | K14: 246574.47 | L14: =IF(J14=0,"N/A",(K14-J14)/J14) -> N/A | M14: WHT on all AP invoices Q3-2026

Sheet TB_Audit_Trail
A1: MODULE: AUDIT TRAIL | N1: 🏠 Back to Home
A2: Log of all critical changes with user ID, timestamp, and before/after values. WARNING: Excel is NOT immutable — use version control or migrate to SQL for production.
A3: ⚠️ CRITICAL LIMITATION: Excel allows editing of historical records. For EAS compliance at scale, migrate to an immutable database (SQL) with timestamped transactions.
A4: Log_ID | B4: Timestamp | C4: User_ID | D4: Sheet_Name | E4: Row_Reference | F4: Action_Type | G4: Field_Changed | H4: Old_Value | I4: New_Value | J4: Voucher_Ref | K4: Approval_Status | L4: Notes
A5: LOG-0001 | B5: 2026-08-10 09:15:23 | C5: ahmed.hassan | D5: TB_General_Journal | E5: Row 5 | F5: INSERT | G5: Debit_EGP | I5: 4662.6 | J5: JV-0002 | K5: Auto-Posted | L5: Excursion cash sale recorded
A6: LOG-0002 | B6: 2026-08-10 09:15:23 | C6: ahmed.hassan | D6: TB_General_Journal | E6: Row 6 | F6: INSERT | G6: Credit_EGP | I6: 4662.6 | J6: JV-0002 | K6: Auto-Posted | L6: Revenue recognition entry
A7: LOG-0003 | B7: 2026-08-10 14:30:00 | C7: sara.khaled | D7: TB_CBE_Rates | E7: Row 11 | F7: UPDATE | G7: USD_Rate | H7: 49.12 | I7: 49.15 | J7: N/A | K7: Approved | L7: CBE rate updated for Aug 10
A8: LOG-0004 | B8: 2026-08-22 10:00:00 | C8: mohamed.ali | D8: TB_AP_Invoices | E8: Row 5 | F8: INSERT | G8: Status | I8: Pending | J8: AP-0004 | K8: Auto-Posted | L8: Sun & Sea invoice registered
A9: LOG-0005 | B9: 2026-08-22 10:05:00 | C9: mohamed.ali | D9: TB_AP_Invoices | E9: Row 5 | F9: UPDATE | G9: Status | H9: Pending | I9: Approved | J9: AP-0004 | K9: Approved | L9: Invoice approved for payment
A10: LOG-0006 | B10: 2026-08-25 11:20:00 | C10: ahmed.hassan | D10: TB_General_Journal | E10: Row 21 | F10: INSERT | G10: Debit_EGP | I10: 2124640 | J10: JV-0009 | K10: Auto-Posted | L10: Hotel payment to Sun & Sea
A11: LOG-0007 | B11: 2026-08-25 11:20:00 | C11: ahmed.hassan | D11: TB_General_Journal | E11: Row 22 | F11: INSERT | G11: Credit_EGP | I11: 2124640 | J11: JV-0009 | K11: Auto-Posted | L11: Bank deduction for hotel payment
A12: LOG-0008 | B12: 2026-08-25 16:45:00 | C12: sara.khaled | D12: TB_Bank_Reconciliation | E12: Row 4 | F12: UPDATE | G12: Status | H12: Pending | I12: Reconciled | J12: BR-0002 | K12: Approved | L12: EUR account reconciled
A13: LOG-0013 | B13: 2026-08-13 10:00:00 | C13: system | D13: TB_General_Journal | E13: Row 6 | F13: INSERT | G13: Account_Code | I13: 1-3400 | J13: JV-0001 | K13: Auto-Posted | L13: Input VAT added to hotel accrual
A14: LOG-0014 | B14: 2026-08-13 10:00:00 | C14: system | D14: TB_General_Journal | E14: Row 21 | F14: INSERT | G14: Account_Code | I14: 1-3400 | J14: JV-0007 | K14: Auto-Posted | L14: Input VAT added to hotel accrual
A15: LOG-0015 | B15: 2026-08-13 10:00:00 | C15: system | D15: TB_General_Journal | E15: Row 27 | F15: INSERT | G15: Account_Code | I15: 6-8000 | J15: JV-0009 | K15: Auto-Posted | L15: FX Loss added to supplier payment
A16: LOG-0016 | B16: 2026-08-13 10:00:00 | C16: system | D16: TB_General_Journal | E16: Row 28 | F16: INSERT | G16: Account_Code | I16: 2-3200 | J16: JV-0009 | K16: Auto-Posted | L16: WHT 3% added to supplier payment
A17: LOG-0017 | B17: 2026-08-13 10:00:00 | C17: system | D17: TB_General_Journal | E17: Row 29 | F17: INSERT | G17: Account_Code | I17: 1-3400 | J17: JV-0009 | K17: Auto-Posted | L17: Input VAT recovery net of WHT
A18: LOG-0018 | B18: 2026-08-13 10:00:00 | C18: system | D18: TB_General_Journal | E18: Row 30-31 | F18: INSERT | G18: Voucher_No | I18: JV-0010 | J18: JV-0010 | K18: Auto-Posted | L18: WHT quarterly payment Q3-2026
A19: LOG-0019 | B19: 2026-08-13 10:00:00 | C19: system | D19: TB_COA | E19: Row 50 | F19: INSERT | G19: Account_Code | I19: 2-3200 | J19: N/A | K19: Auto-Posted | L19: WHT Payable account added
A20: LOG-0020 | B20: 2026-08-13 10:00:00 | C20: system | D20: TB_Suppliers_Master | E20: All | F20: INSERT | G20: WHT_Exempt | I20: FALSE | J20: N/A | K20: Auto-Posted | L20: WHT exemption flag added to all suppliers
A21: LOG-0013 | B21: 2026-08-13 10:00:00 | C21: system | D21: TB_General_Journal | E21: Row 5 | F21: INSERT | G21: Account_Code | I21: 1-3400 | J21: JV-0001 | K21: Auto-Posted | L21: Input VAT added to hotel accrual
A22: LOG-0014 | B22: 2026-08-13 10:00:00 | C22: system | D22: TB_General_Journal | E22: Row 20 | F22: INSERT | G22: Account_Code | I22: 1-3400 | J22: JV-0007 | K22: Auto-Posted | L22: Input VAT added to hotel accrual
A23: LOG-0015 | B23: 2026-08-13 10:00:00 | C23: system | D23: TB_General_Journal | E23: Row 26 | F23: INSERT | G23: Account_Code | I23: 6-8000 | J23: JV-0009 | K23: Auto-Posted | L23: FX Loss added to supplier payment
A24: LOG-0016 | B24: 2026-08-13 10:00:00 | C24: system | D24: TB_General_Journal | E24: Row 28 | F24: INSERT | G24: Account_Code | I24: 2-3200 | J24: JV-0009 | K24: Auto-Posted | L24: WHT 3% added to supplier payment
A25: LOG-0017 | B25: 2026-08-13 10:00:00 | C25: system | D25: TB_General_Journal | E25: Row 29-30 | F25: INSERT | G25: Voucher_No | I25: JV-0010 | J25: JV-0010 | K25: Auto-Posted | L25: WHT quarterly payment Q3-2026

Sheet TB_Dimensions
A1: MODULE: ANALYTICAL DIMENSIONS | G1: 🏠 Back to Home
A2: Mandatory analytical dimensions for DMC reporting. Every journal entry MUST tag at least one dimension for P&L analysis.
A3: DIMENSION DEFINITIONS
A4: Dimension_Code | B4: Dimension_Name | C4: Description | D4: Mandatory | E4: Applies_To
A5: DIM-TO | B5: Tour Operator / Market | C5: Source market or tour operator generating the revenue/cost | D5: YES | E5: Revenue, COGS, AR
A6: DIM-REG | B6: Destination / Region | C6: Geographic region where service is delivered | D6: YES | E6: All transactions
A7: DIM-EXC-TYPE | B7: Excursion Category | C7: Type of excursion for margin analysis | D7: NO | E7: Excursion Revenue & COGS
A8: DIM-HOTEL | B8: Hotel Property | C8: Specific hotel for cost allocation | D8: NO | E8: Hotel Revenue & COGS
A9: DIM-CLIENT | B9: Client Segment | C9: B2B vs B2C segmentation | D9: NO | E9: Revenue, AR
A10: DIM-TO: TOUR OPERATOR / MARKET VALUES
A11: Dimension_Code | B11: Value_Code | C11: Value_Name | D11: Country | E11: Credit_Limit_FX | F11: Currency | G11: Payment_Terms | H11: Status
A12: DIM-TO | B12: TO-001 | C12: TUI Germany | D12: Germany | E12: 500000 | F12: EUR | G12: 30 | H12: Active
A13: DIM-TO | B13: TO-002 | C13: Al-Tayyar KSA | D13: Saudi Arabia | E13: 400000 | F13: SAR | G13: 45 | H13: Active
A14: DIM-TO | B14: TO-003 | C14: OTA Ukraine | D14: Ukraine | E14: 150000 | F14: USD | G14: 30 | H14: Active
A15: DIM-TO | B15: TO-004 | C15: B2C Polish Direct | D15: Poland | E15: 0 | F15: PLN | G15: 0 | H15: Active
A16: DIM-TO | B16: TO-005 | C16: Nordic Wave DMC | D16: Sweden | E16: 300000 | F16: EUR | G16: 45 | H16: Active
A17: DIM-TO | B17: TO-006 | C17: BritSun Holidays | D17: UK | E17: 250000 | F17: GBP | G17: 30 | H17: Active
A18: DIM-TO | B18: TO-007 | C18: EuroSun Tours | D18: Germany | E18: 350000 | F18: EUR | G18: 30 | H18: Active
A19: DIM-TO | B19: TO-008 | C19: Gulf Adventures | D19: UAE | E19: 450000 | F19: USD | G19: 45 | H19: Active
A21: DIM-REG: DESTINATION / REGION VALUES
A22: Dimension_Code | B22: Value_Code | C22: Value_Name | D22: Location_Type | E22: Seasonality | F22: Notes
A23: DIM-REG | B23: REG-01 | C23: Hurghada | D23: Beach Resort | E23: Year-round | F23: Main hub - 60% of operations
A24: DIM-REG | B24: REG-02 | C24: Sharm El Sheikh | D24: Beach Resort | E24: Year-round | F24: Secondary hub - 25% of operations
A25: DIM-REG | B25: REG-03 | C25: Luxor | D25: Cultural | E25: Oct-Apr | F25: Nile cruise & temple tours
A26: DIM-REG | B26: REG-04 | C26: Cairo | D26: City | E26: Year-round | F26: Airport transfers & city tours
A27: DIM-REG | B27: REG-05 | C27: Marsa Alam | D27: Beach/Diving | E27: Mar-Nov | F27: Diving & marine excursions
A29: DIM-EXC-TYPE: EXCURSION CATEGORY VALUES
A30: Dimension_Code | B30: Value_Code | C30: Value_Name | D30: Margin_Target_Pct | E30: Avg_Price_EGP | F30: Notes
A31: DIM-EXC-TYPE | B31: CAT-01 | C31: Marine | D31: 0.35 | E31: 2500 | F31: Snorkeling, diving, boat trips
A32: DIM-EXC-TYPE | B32: CAT-02 | C32: Safari | D32: 0.4 | E32: 3000 | F32: Desert safari, quad bikes, camel rides
A33: DIM-EXC-TYPE | B33: CAT-03 | C33: Cultural | D33: 0.3 | E33: 3500 | F33: Luxor, Cairo, temple tours
A34: DIM-EXC-TYPE | B34: CAT-04 | C34: Adventure | D34: 0.45 | E34: 2000 | F34: Parasailing, kite surfing
A35: DIM-EXC-TYPE | B35: CAT-05 | C35: Luxury | D35: 0.5 | E35: 8000 | F35: Private yacht, VIP experiences

Sheet TB_Golden_Report
A1: MODULE: THE GOLDEN REPORT — TOUR OPERATOR P&L | N1: 🏠 Back to Home
A2: Live Operational Management P&L per Tour Operator / Client, driven by Bookings, Hotel Accruals, Excursion Sales and Rep data. 📌 MANAGEMENT ARCHITECTURE NOTE: This Golden Report is an Operational Management P&L driven by live Bookings and Field Sales data. For Statutory Accounting Statements, refer to TB_Income_Statement and TB_Balance_Sheet.
A3: Client_ID | B3: Tour_Operator | C3: Booking_Revenue_EGP | D3: Discounts_EGP | E3: Net_Revenue_EGP | F3: Supplier_Cost_EGP | G3: Variable_Cost_EGP | H3: Rep_Comm_EGP | I3: Net_Margin_EGP | J3: Margin_Pct | K3: Performance_Band | L3: Action_Required
A4: =TB_Clients_Master!A4 -> CLI-001 | B4: =TB_Clients_Master!B4 -> Alpine Sun Tours Group | C4: =SUMIFS(TB_Master_Bookings!$M$4:$M$1000,TB_Master_Bookings!$B$4:$B$1000,A4) -> 6722100 | D4: =-C4*IFERROR(INDEX(TB_Clients_Master!$J$4:$J$13,MATCH(A4,TB_Clients_Master!$A$4:$A$13,0)),0) -> 0 | E4: =C4+D4 -> 6722100 | F4: =-SUMIFS(TB_Master_Bookings!$P$4:$P$1000,TB_Master_Bookings!$B$4:$B$1000,A4) -> -5377680 | G4: =-SUMIFS(TB_Reps_Master!$E$4:$E$11,TB_Reps_Master!$L$4:$L$11,A4,TB_Reps_Master!$I$4:$I$11,"Active") -> -5000 | H4: =-SUMIFS(TB_Excursions_Sales!$P$4:$P$21,TB_Excursions_Sales!$R$4:$R$21,A4) -> -746.016 | I4: =E4+F4+G4+H4 -> 1338674 | J4: =IF(E4=0,0,I4/E4) -> 0.19914521 | K4: =IF(J4>=0.5,"🟢 Excellent",IF(J4>=0.3,"🟡 Good",IF(J4>=0.15,"🟠 Watch","🔴 Critical"))) -> 🟠 Watch | L4: =IF(J4<0.1,"Urgent Review Required",IF(J4<0.2,"Collect AR & Optimize Cost","Maintain & Expand Market")) -> Collect AR & Optimize Cost
A5: =TB_Clients_Master!A5 -> CLI-002 | B5: =TB_Clients_Master!B5 -> Nordic Wave DMC | C5: =SUMIFS(TB_Master_Bookings!$M$4:$M$1000,TB_Master_Bookings!$B$4:$B$1000,A5) -> 1268769.6 | D5: =-C5*IFERROR(INDEX(TB_Clients_Master!$J$4:$J$13,MATCH(A5,TB_Clients_Master!$A$4:$A$13,0)),0) -> 0 | E5: =C5+D5 -> 1268769.6 | F5: =-SUMIFS(TB_Master_Bookings!$P$4:$P$1000,TB_Master_Bookings!$B$4:$B$1000,A5) -> -1005732 | G5: =-SUMIFS(TB_Reps_Master!$E$4:$E$11,TB_Reps_Master!$L$4:$L$11,A5,TB_Reps_Master!$I$4:$I$11,"Active") -> -5000 | H5: =-SUMIFS(TB_Excursions_Sales!$P$4:$P$21,TB_Excursions_Sales!$R$4:$R$21,A5) -> -746.016 | I5: =E5+F5+G5+H5 -> 257291.58 | J5: =IF(E5=0,0,I5/E5) -> 0.20278826 | K5: =IF(J5>=0.5,"🟢 Excellent",IF(J5>=0.3,"🟡 Good",IF(J5>=0.15,"🟠 Watch","🔴 Critical"))) -> 🟠 Watch | L5: =IF(J5<0.1,"Urgent Review Required",IF(J5<0.2,"Collect AR & Optimize Cost","Maintain & Expand Market")) -> Maintain & Expand Market
A6: =TB_Clients_Master!A6 -> CLI-003 | B6: =TB_Clients_Master!B6 -> BritSun Holidays | C6: =SUMIFS(TB_Master_Bookings!$M$4:$M$1000,TB_Master_Bookings!$B$4:$B$1000,A6) -> 1020474 | D6: =-C6*IFERROR(INDEX(TB_Clients_Master!$J$4:$J$13,MATCH(A6,TB_Clients_Master!$A$4:$A$13,0)),0) -> 0 | E6: =C6+D6 -> 1020474 | F6: =-SUMIFS(TB_Master_Bookings!$P$4:$P$1000,TB_Master_Bookings!$B$4:$B$1000,A6) -> -811146 | G6: =-SUMIFS(TB_Reps_Master!$E$4:$E$11,TB_Reps_Master!$L$4:$L$11,A6,TB_Reps_Master!$I$4:$I$11,"Active") -> -5000 | H6: =-SUMIFS(TB_Excursions_Sales!$P$4:$P$21,TB_Excursions_Sales!$R$4:$R$21,A6) -> -665.005 | I6: =E6+F6+G6+H6 -> 203662.99 | J6: =IF(E6=0,0,I6/E6) -> 0.19957686 | K6: =IF(J6>=0.5,"🟢 Excellent",IF(J6>=0.3,"🟡 Good",IF(J6>=0.15,"🟠 Watch","🔴 Critical"))) -> 🟠 Watch | L6: =IF(J6<0.1,"Urgent Review Required",IF(J6<0.2,"Collect AR & Optimize Cost","Maintain & Expand Market")) -> Collect AR & Optimize Cost
A7: =TB_Clients_Master!A7 -> CLI-004 | B7: =TB_Clients_Master!B7 -> Meridian Voyages | C7: =SUMIFS(TB_Master_Bookings!$M$4:$M$1000,TB_Master_Bookings!$B$4:$B$1000,A7) -> 1153440 | D7: =-C7*IFERROR(INDEX(TB_Clients_Master!$J$4:$J$13,MATCH(A7,TB_Clients_Master!$A$4:$A$13,0)),0) -> 0 | E7: =C7+D7 -> 1153440 | F7: =-SUMIFS(TB_Master_Bookings!$P$4:$P$1000,TB_Master_Bookings!$B$4:$B$1000,A7) -> -922752 | G7: =-SUMIFS(TB_Reps_Master!$E$4:$E$11,TB_Reps_Master!$L$4:$L$11,A7,TB_Reps_Master!$I$4:$I$11,"Active") -> -5000 | H7: =-SUMIFS(TB_Excursions_Sales!$P$4:$P$21,TB_Excursions_Sales!$R$4:$R$21,A7) -> -480.15 | I7: =E7+F7+G7+H7 -> 225207.85 | J7: =IF(E7=0,0,I7/E7) -> 0.19524886 | K7: =IF(J7>=0.5,"🟢 Excellent",IF(J7>=0.3,"🟡 Good",IF(J7>=0.15,"🟠 Watch","🔴 Critical"))) -> 🟠 Watch | L7: =IF(J7<0.1,"Urgent Review Required",IF(J7<0.2,"Collect AR & Optimize Cost","Maintain & Expand Market")) -> Collect AR & Optimize Cost
A8: =TB_Clients_Master!A8 -> CLI-005 | B8: =TB_Clients_Master!B8 -> Red Sea Direct Bookings | C8: =SUMIFS(TB_Master_Bookings!$M$4:$M$1000,TB_Master_Bookings!$B$4:$B$1000,A8) -> 2260121.6 | D8: =-C8*IFERROR(INDEX(TB_Clients_Master!$J$4:$J$13,MATCH(A8,TB_Clients_Master!$A$4:$A$13,0)),0) -> 0 | E8: =C8+D8 -> 2260121.6 | F8: =-SUMIFS(TB_Master_Bookings!$P$4:$P$1000,TB_Master_Bookings!$B$4:$B$1000,A8) -> -1806918.4 | G8: =-SUMIFS(TB_Reps_Master!$E$4:$E$11,TB_Reps_Master!$L$4:$L$11,A8,TB_Reps_Master!$I$4:$I$11,"Active") -> 0 | H8: =-SUMIFS(TB_Excursions_Sales!$P$4:$P$21,TB_Excursions_Sales!$R$4:$R$21,A8) -> 0 | I8: =E8+F8+G8+H8 -> 453203.2 | J8: =IF(E8=0,0,I8/E8) -> 0.2005216 | K8: =IF(J8>=0.5,"🟢 Excellent",IF(J8>=0.3,"🟡 Good",IF(J8>=0.15,"🟠 Watch","🔴 Critical"))) -> 🟠 Watch | L8: =IF(J8<0.1,"Urgent Review Required",IF(J8<0.2,"Collect AR & Optimize Cost","Maintain & Expand Market")) -> Maintain & Expand Market
A9: =TB_Clients_Master!A9 -> CLI-006 | B9: =TB_Clients_Master!B9 -> EuroSun Tours | C9: =SUMIFS(TB_Master_Bookings!$M$4:$M$1000,TB_Master_Bookings!$B$4:$B$1000,A9) -> 7208600 | D9: =-C9*IFERROR(INDEX(TB_Clients_Master!$J$4:$J$13,MATCH(A9,TB_Clients_Master!$A$4:$A$13,0)),0) -> 0 | E9: =C9+D9 -> 7208600 | F9: =-SUMIFS(TB_Master_Bookings!$P$4:$P$1000,TB_Master_Bookings!$B$4:$B$1000,A9) -> -5766880 | G9: =-SUMIFS(TB_Reps_Master!$E$4:$E$11,TB_Reps_Master!$L$4:$L$11,A9,TB_Reps_Master!$I$4:$I$11,"Active") -> -5500 | H9: =-SUMIFS(TB_Excursions_Sales!$P$4:$P$21,TB_Excursions_Sales!$R$4:$R$21,A9) -> -1270.86 | I9: =E9+F9+G9+H9 -> 1434949.1 | J9: =IF(E9=0,0,I9/E9) -> 0.19906072 | K9: =IF(J9>=0.5,"🟢 Excellent",IF(J9>=0.3,"🟡 Good",IF(J9>=0.15,"🟠 Watch","🔴 Critical"))) -> 🟠 Watch | L9: =IF(J9<0.1,"Urgent Review Required",IF(J9<0.2,"Collect AR & Optimize Cost","Maintain & Expand Market")) -> Collect AR & Optimize Cost
A10: =TB_Clients_Master!A10 -> CLI-007 | B10: =TB_Clients_Master!B10 -> Nile Breeze | C10: =SUMIFS(TB_Master_Bookings!$M$4:$M$1000,TB_Master_Bookings!$B$4:$B$1000,A10) -> 1190595 | D10: =-C10*IFERROR(INDEX(TB_Clients_Master!$J$4:$J$13,MATCH(A10,TB_Clients_Master!$A$4:$A$13,0)),0) -> 0 | E10: =C10+D10 -> 1190595 | F10: =-SUMIFS(TB_Master_Bookings!$P$4:$P$1000,TB_Master_Bookings!$B$4:$B$1000,A10) -> -952476 | G10: =-SUMIFS(TB_Reps_Master!$E$4:$E$11,TB_Reps_Master!$L$4:$L$11,A10,TB_Reps_Master!$I$4:$I$11,"Active") -> -5500 | H10: =-SUMIFS(TB_Excursions_Sales!$P$4:$P$21,TB_Excursions_Sales!$R$4:$R$21,A10) -> 0 | I10: =E10+F10+G10+H10 -> 232619 | J10: =IF(E10=0,0,I10/E10) -> 0.19538046 | K10: =IF(J10>=0.5,"🟢 Excellent",IF(J10>=0.3,"🟡 Good",IF(J10>=0.15,"🟠 Watch","🔴 Critical"))) -> 🟠 Watch | L10: =IF(J10<0.1,"Urgent Review Required",IF(J10<0.2,"Collect AR & Optimize Cost","Maintain & Expand Market")) -> Collect AR & Optimize Cost
A11: =TB_Clients_Master!A11 -> CLI-008 | B11: =TB_Clients_Master!B11 -> London Escape | C11: =SUMIFS(TB_Master_Bookings!$M$4:$M$1000,TB_Master_Bookings!$B$4:$B$1000,A11) -> 1376320 | D11: =-C11*IFERROR(INDEX(TB_Clients_Master!$J$4:$J$13,MATCH(A11,TB_Clients_Master!$A$4:$A$13,0)),0) -> 0 | E11: =C11+D11 -> 1376320 | F11: =-SUMIFS(TB_Master_Bookings!$P$4:$P$1000,TB_Master_Bookings!$B$4:$B$1000,A11) -> -1101056 | G11: =-SUMIFS(TB_Reps_Master!$E$4:$E$11,TB_Reps_Master!$L$4:$L$11,A11,TB_Reps_Master!$I$4:$I$11,"Active") -> -5500 | H11: =-SUMIFS(TB_Excursions_Sales!$P$4:$P$21,TB_Excursions_Sales!$R$4:$R$21,A11) -> -819.28 | I11: =E11+F11+G11+H11 -> 268944.72 | J11: =IF(E11=0,0,I11/E11) -> 0.19540857 | K11: =IF(J11>=0.5,"🟢 Excellent",IF(J11>=0.3,"🟡 Good",IF(J11>=0.15,"🟠 Watch","🔴 Critical"))) -> 🟠 Watch | L11: =IF(J11<0.1,"Urgent Review Required",IF(J11<0.2,"Collect AR & Optimize Cost","Maintain & Expand Market")) -> Collect AR & Optimize Cost
A12: =TB_Clients_Master!A12 -> CLI-009 | B12: =TB_Clients_Master!B12 -> Gulf Adventures | C12: =SUMIFS(TB_Master_Bookings!$M$4:$M$1000,TB_Master_Bookings!$B$4:$B$1000,A12) -> 2070600 | D12: =-C12*IFERROR(INDEX(TB_Clients_Master!$J$4:$J$13,MATCH(A12,TB_Clients_Master!$A$4:$A$13,0)),0) -> 0 | E12: =C12+D12 -> 2070600 | F12: =-SUMIFS(TB_Master_Bookings!$P$4:$P$1000,TB_Master_Bookings!$B$4:$B$1000,A12) -> -1656480 | G12: =-SUMIFS(TB_Reps_Master!$E$4:$E$11,TB_Reps_Master!$L$4:$L$11,A12,TB_Reps_Master!$I$4:$I$11,"Active") -> 0 | H12: =-SUMIFS(TB_Excursions_Sales!$P$4:$P$21,TB_Excursions_Sales!$R$4:$R$21,A12) -> 0 | I12: =E12+F12+G12+H12 -> 414120 | J12: =IF(E12=0,0,I12/E12) -> 0.2 | K12: =IF(J12>=0.5,"🟢 Excellent",IF(J12>=0.3,"🟡 Good",IF(J12>=0.15,"🟠 Watch","🔴 Critical"))) -> 🟠 Watch | L12: =IF(J12<0.1,"Urgent Review Required",IF(J12<0.2,"Collect AR & Optimize Cost","Maintain & Expand Market")) -> Maintain & Expand Market
A13: =TB_Clients_Master!A13 -> CLI-010 | B13: =TB_Clients_Master!B13 -> SunSeeker Travel | C13: =SUMIFS(TB_Master_Bookings!$M$4:$M$1000,TB_Master_Bookings!$B$4:$B$1000,A13) -> 2846200 | D13: =-C13*IFERROR(INDEX(TB_Clients_Master!$J$4:$J$13,MATCH(A13,TB_Clients_Master!$A$4:$A$13,0)),0) -> 0 | E13: =C13+D13 -> 2846200 | F13: =-SUMIFS(TB_Master_Bookings!$P$4:$P$1000,TB_Master_Bookings!$B$4:$B$1000,A13) -> 0 | G13: =-SUMIFS(TB_Reps_Master!$E$4:$E$11,TB_Reps_Master!$L$4:$L$11,A13,TB_Reps_Master!$I$4:$I$11,"Active") -> 0 | H13: =-SUMIFS(TB_Excursions_Sales!$P$4:$P$21,TB_Excursions_Sales!$R$4:$R$21,A13) -> 0 | I13: =E13+F13+G13+H13 -> 2846200 | J13: =IF(E13=0,0,I13/E13) -> 1 | K13: =IF(J13>=0.5,"🟢 Excellent",IF(J13>=0.3,"🟡 Good",IF(J13>=0.15,"🟠 Watch","🔴 Critical"))) -> 🟢 Excellent | L13: =IF(J13<0.1,"Urgent Review Required",IF(J13<0.2,"Collect AR & Optimize Cost","Maintain & Expand Market")) -> Maintain & Expand Market
A14: GRAND TOTAL | C14: =SUM(C4:C13) -> 27117220 | D14: =SUM(D4:D13) -> 0 | E14: =SUM(E4:E13) -> 27117220 | F14: =SUM(F4:F13) -> -19401120 | G14: =SUM(G4:G13) -> -36500 | H14: =SUM(H4:H13) -> -4727.327 | I14: =SUM(I4:I13) -> 7674872.5 | J14: =SUM(J4:J13) -> 2.7871305

Sheet TB_Migration_Plan
A1: ✅ MIGRATION COMPLETE — ALL STEPS FINISHED. WORKBOOK VALIDATED AND PRODUCTION READY. | J1: 🏠 Back to Home
A2: MODULE: COA MIGRATION PLAN
A3: Step-by-step migration plan from old COA (4-digit flat) to new COA (hierarchical 1-xxxx). DO NOT SKIP STEPS. Backup before starting.
A4: 🛑 CRITICAL: Before starting migration, create a backup copy of this workbook. Any error in Step 3-5 will corrupt historical data.
A6: 📋 PHASE 1: PREPARATION (Do NOT modify existing sheets yet)
A7: Step | B7: Action | C7: Target_Sheet | D7: Details | E7: Status | F7: Owner | G7: Risk_Level | H7: Estimated_Time
A8: 1.1 | B8: Backup workbook | C8: All | D8: File → Save As → DMC_ERP_BACKUP_YYYYMMDD.xlsx | E8: Complete | F8: IT/Admin | G8: High | H8: 2 min
A9: 1.2 | B9: Review TB_COA | C9: TB_COA | D9: Verify all 45 accounts, check Mapping_Status column | E9: Complete | F9: Finance Manager | G9: Medium | H9: 15 min
A10: 1.3 | B10: Validate critical accounts | C10: TB_COA | D10: Confirm: 1-1200 (Rep Cash), 2-2300 (Rep Comm), 2-2110 (ETA) exist | E10: Complete | F10: Finance Manager | G10: High | H10: 5 min
A11: 1.4 | B11: Freeze existing data | C11: TB_General_Journal, TB_Trial_Balance | D11: Add protection to prevent accidental edits during migration | E11: Complete | F11: IT/Admin | G11: Low | H11: 5 min
A12: 1.5 | B12: Notify team | C12: All | D12: Inform all users that migration is in progress. No new entries until complete. | E12: Complete | F12: Finance Manager | G12: Medium | H12: 10 min
A14: 🔍 PHASE 2: MAPPING VALIDATION (Verify every old code has a new home)

Sheet TB_COA
A1: MODULE: CHART OF ACCOUNTS — PRODUCTION READY | I1: 🏠 Back to Home
A2: Hierarchical COA: Class 1=Assets, 2=Liabilities, 3=Equity, 4=Revenue, 5=COGS, 6=Expenses, 7=FX. Includes Old→New Mapping for migration tracking.
A3: ⚠️ THIS IS THE SINGLE AUTHORITATIVE COA. All journal entries, TB, and reports MUST reference this sheet only.
A4: Account_Code | B4: Account_Name | C4: Account_Type | D4: Class | E4: Category | F4: Currency | G4: IsActive
A5: 1-1001 | B5: Main Safe - EGP | C5: Asset | D5: 1 | E5: Cash & Bank | F5: EGP | G5: TRUE
A6: 1-1002 | B6: Petty Cash - FCY | C6: Asset | D6: 1 | E6: Cash & Bank | F6: Multi | G6: TRUE
A7: 1-1101 | B7: Bank Account - EGP | C7: Asset | D7: 1 | E7: Bank | F7: EGP | G7: TRUE
A8: 1-1102 | B8: Bank Account - USD | C8: Asset | D8: 1 | E8: Bank | F8: USD | G8: TRUE
A9: 1-1103 | B9: Bank Account - EUR | C9: Asset | D9: 1 | E9: Bank | F9: EUR | G9: TRUE
A10: 1-1200 | B10: Rep Cash Advance (Petty Cash) | C10: Asset | D10: 1 | E10: Cash & Bank | F10: EGP | G10: TRUE
A11: 1-2100 | B11: AR - Local Clients / Agents | C11: Asset | D11: 1 | E11: Receivables | F11: EGP | G11: TRUE
A12: 1-2200 | B12: AR - Foreign Tour Operators (Control) | C12: Asset | D12: 1 | E12: Receivables | F12: Multi | G12: TRUE
A13: 1-3100 | B13: Advances to Hotels (Prepayments) | C13: Asset | D13: 1 | E13: Prepayments | F13: EGP | G13: TRUE
A14: 1-3200 | B14: Accrued Revenue - Unbilled Services | C14: Asset | D14: 1 | E14: Accruals | F14: EGP | G14: TRUE
A15: 1-3300 | B15: Prepaid Excursion Costs (Allotments) | C15: Asset | D15: 1 | E15: Prepayments | F15: Multi | G15: TRUE
... A49: 7-2000 | B49: Unrealized FX Gain/Loss | C49: Expense/Income | D49: 7 | E49: FX | F49: EGP | G49: TRUE
A50: TOTAL ACCOUNTS | C50: 45 | D50: Production Ready

Sheet TB_General_Journal
A1: MODULE: GENERAL JOURNAL | N1: 🏠 Back to Home
A2: Double-entry accounting journal — the single source feeding TB_Trial_Balance via SUMIFS.
A3: Voucher_No | B3: Date | C3: Account_Code | D3: Account_Name | E3: Debit_EGP | F3: Credit_EGP | G3: FX_Amount | H3: FX_Currency | I3: FX_Rate | J3: Reference_ID | K3: FX_Variance_Flag | L3: Description
A4: JV-0001 | B4: 46244 | C4: 1-2200 | D4: =IFERROR(INDEX(TB_COA!$B$5:$B$1000,MATCH(C4,TB_COA!$A$5:$A$1000,0)),"") -> AR - Foreign Tour Operators (Control) | E4: =TB_Master_Bookings!M4 -> 6722100 | F4: 0 | G4: =TB_Master_Bookings!K4 -> 126000 | H4: EUR | I4: 53.35 | J4: HRG-2026-0815 | L4: Client invoice - Alpine Sun Tours Group (HRG-2026-0815)
A5: JV-0001 | B5: 46244 | C5: 4-2000 | D5: =IFERROR(INDEX(TB_COA!$B$5:$B$1000,MATCH(C5,TB_COA!$A$5:$A$1000,0)),"") -> Revenue - Package Tours | E5: 0 | F5: =E4/1.14 -> 5896578.9 | G5: =G4/1.14 -> 110526.32 | H5: EUR | I5: 53.35 | J5: HRG-2026-0815 | L5: Revenue net of VAT - Alpine Sun Tours Group
A6: JV-0001 | B6: 46244 | C6: 2-3100 | D6: =IFERROR(INDEX(TB_COA!$B$5:$B$1000,MATCH(C6,TB_COA!$A$5:$A$1000,0)),"") -> Output VAT Payable (14%) | E6: 0 | F6: =E4-F5 -> 825521.05 | G6: =G4-G5 -> 15473.684 | H6: EUR | I6: 53.35 | J6: HRG-2026-0815 | L6: Output VAT 14% - Alpine Sun Tours Group
A7: JV-0002 | B7: 46245 | C7: 1-2200 | D7: =IFERROR(INDEX(TB_COA!$B$5:$B$1000,MATCH(C7,TB_COA!$A$5:$A$1000,0)),"") -> AR - Foreign Tour Operators (Control) | E7: =TB_Master_Bookings!M5 -> 1268769.6 | F7: 0 | G7: =TB_Master_Bookings!K5 -> 25830 | H7: USD | I7: 49.12 | J7: HRG-2026-0816 | L7: Client invoice - Nordic Wave Charter (HRG-2026-0816)
A8: JV-0002 | B8: 46245 | C8: 4-2000 | D8: =IFERROR(INDEX(TB_COA!$B$5:$B$1000,MATCH(C8,TB_COA!$A$5:$A$1000,0)),"") -> Revenue - Package Tours | E8: 0 | F8: =E7/1.14 -> 1112955.8 | G8: =G7/1.14 -> 22657.895 | H8: USD | I8: 49.12 | J8: HRG-2026-0816 | L8: Revenue net of VAT - Nordic Wave Charter
A9: JV-0002 | B9: 46245 | C9: 2-3100 | D9: =IFERROR(INDEX(TB_COA!$B$5:$B$1000,MATCH(C9,TB_COA!$A$5:$A$1000,0)),"") -> Output VAT Payable (14%) | E9: 0 | F9: =E7-F8 -> 155813.81 | G9: =G7-G8 -> 3172.1053 | H9: USD | I9: 49.12 | J9: HRG-2026-0816 | L9: Output VAT 14% - Nordic Wave Charter
A10: JV-0003 | B10: 46246 | C10: 1-2200 | D10: =IFERROR(INDEX(TB_COA!$B$5:$B$1000,MATCH(C10,TB_COA!$A$5:$A$1000,0)),"") -> AR - Foreign Tour Operators (Control) | E10: =TB_Master_Bookings!M6 -> 1020474 | F10: 0 | G10: =TB_Master_Bookings!K6 -> 16380 | H10: GBP | I10: 62.3 | J10: HRG-2026-0817 | L10: Client invoice - BritSun Holidays (HRG-2026-0817)
A11: JV-0003 | B11: 46246 | C11: 4-2000 | D11: =IFERROR(INDEX(TB_COA!$B$5:$B$1000,MATCH(C11,TB_COA!$A$5:$A$1000,0)),"") -> Revenue - Package Tours | E11: 0 | F11: =E10/1.14 -> 895152.63 | G11: =G10/1.14 -> 14368.421 | H11: GBP | I11: 62.3 | J11: HRG-2026-0817 | L11: Revenue net of VAT - BritSun Holidays
A12: JV-0003 | B12: 46246 | C12: 2-3100 | D12: =IFERROR(INDEX(TB_COA!$B$5:$B$1000,MATCH(C12,TB_COA!$A$5:$A$1000,0)),"") -> Output VAT Payable (14%) | E12: 0 | F12: =E10-F11 -> 125321.37 | G12: =G10-G11 -> 2011.5789 | H12: GBP | I12: 62.3 | J12: HRG-2026-0817 | L12: Output VAT 14% - BritSun Holidays
A13: JV-0004 | B13: 46243 | C13: 1-2200 | D13: =IFERROR(INDEX(TB_COA!$B$5:$B$1000,MATCH(C13,TB_COA!$A$5:$A$1000,0)),"") -> AR - Foreign Tour Operators (Control) | E13: =TB_Master_Bookings!M7 -> 1153440 | F13: 0 | G13: =TB_Master_Bookings!K7 -> 21600 | H13: EUR | I13: 53.4 | J13: HRG-2026-0818 | L13: Client invoice - Meridian Voyages (HRG-2026-0818)
A14: JV-0004 | B14: 46243 | C14: 4-2000 | D14: =IFERROR(INDEX(TB_COA!$B$5:$B$1000,MATCH(C14,TB_COA!$A$5:$A$1000,0)),"") -> Revenue - Package Tours | E14: 0 | F14: =E13/1.14 -> 1011789.5 | G14: =G13/1.14 -> 18947.368 | H14: EUR | I14: 53.4 | J14: HRG-2026-0818 | L14: Revenue net of VAT - Meridian Voyages
A15: JV-0004 | B15: 46243 | C15: 2-3100 | D15: =IFERROR(INDEX(TB_COA!$B$5:$B$1000,MATCH(C15,TB_COA!$A$5:$A$1000,0)),"") -> Output VAT Payable (14%) | E15: 0 | F15: =E13-F14 -> 141650.53 | G15: =G13-G14 -> 2652.6316 | H15: EUR | I15: 53.4 | J15: HRG-2026-0818 | L15: Output VAT 14% - Meridian Voyages
A16: JV-0005 | B16: 46245 | C16: 1-2200 | D16: =IFERROR(INDEX(TB_COA!$B$5:$B$1000,MATCH(C16,TB_COA!$A$5:$A$1000,0)),"") -> AR - Foreign Tour Operators (Control) | E16: =TB_Master_Bookings!M8 -> 156201.6 | F16: 0 | G16: =TB_Master_Bookings!K8 -> 3180 | H16: USD | I16: 49.12 | J16: HRG-2026-0819 | L16: Client invoice - Red Sea Direct Bookings (HRG-2026-0819)
A17: JV-0005 | B17: 46245 | C17: 4-2000 | D17: =IFERROR(INDEX(TB_COA!$B$5:$B$1000,MATCH(C17,TB_COA!$A$5:$A$1000,0)),"") -> Revenue - Package Tours | E17: 0 | F17: =E16/1.14 -> 137018.95 | G17: =G16/1.14 -> 2789.4737 | H17: USD | I17: 49.12 | J17: HRG-2026-0819 | L17: Revenue net of VAT - Red Sea Direct Bookings
A18: JV-0005 | B18: 46245 | C18: 2-3100 | D18: =IFERROR(INDEX(TB_COA!$B$5:$B$1000,MATCH(C18,TB_COA!$A$5:$A$1000,0)),"") -> Output VAT Payable (14%) | E18: 0 | F18: =E16-F17 -> 19182.653 | G18: =G16-G17 -> 390.52632 | H18: USD | I18: 49.12 | J18: HRG-2026-0819 | L18: Output VAT 14% - Red Sea Direct Bookings
A19: JV-0006 | B19: 46256 | C19: 1-2200 | D19: =IFERROR(INDEX(TB_COA!$B$5:$B$1000,MATCH(C19,TB_COA!$A$5:$A$1000,0)),"") -> AR - Foreign Tour Operators (Control) | E19: =TB_Master_Bookings!M10 -> 7208600 | F19: 0 | G19: =TB_Master_Bookings!K10 -> 133000 | H19: EUR | I19: 54.2 | J19: MBR-2026-0001 | L19: Client invoice - EuroSun Tours (MBR-2026-0001)
A20: JV-0006 | B20: 46256 | C20: 4-2000 | D20: =IFERROR(INDEX(TB_COA!$B$5:$B$1000,MATCH(C20,TB_COA!$A$5:$A$1000,0)),"") -> Revenue - Package Tours | E20: 0 | F20: =E19/1.14 -> 6323333.3 | G20: =G19/1.14 -> 116666.67 | H20: EUR | I20: 54.2 | J20: MBR-2026-0001 | L20: Revenue net of VAT - EuroSun Tours
A21: JV-0006 | B21: 46256 | C21: 2-3100 | D21: =IFERROR(INDEX(TB_COA!$B$5:$B$1000,MATCH(C21,TB_COA!$A$5:$A$1000,0)),"") -> Output VAT Payable (14%) | E21: 0 | F21: =E19-F20 -> 885266.67 | G21: =G19-G20 -> 16333.333 | H21: EUR | I21: 54.2 | J21: MBR-2026-0001 | L21: Output VAT 14% - EuroSun Tours
A22: JV-0007 | B22: 46256 | C22: 1-2200 | D22: =IFERROR(INDEX(TB_COA!$B$5:$B$1000,MATCH(C22,TB_COA!$A$5:$A$1000,0)),"") -> AR - Foreign Tour Operators (Control) | E22: =TB_Master_Bookings!M11 -> 1190595 | F22: 0 | G22: =TB_Master_Bookings!K11 -> 24150 | H22: USD | I22: 49.3 | J22: MBR-2026-0002 | L22: Client invoice - Nile Breeze (MBR-2026-0002)
A23: JV-0007 | B23: 46256 | C23: 4-2000 | D23: =IFERROR(INDEX(TB_COA!$B$5:$B$1000,MATCH(C23,TB_COA!$A$5:$A$1000,0)),"") -> Revenue - Package Tours | E23: 0 | F23: =E22/1.14 -> 1044381.6 | G23: =G22/1.14 -> 21184.211 | H23: USD | I23: 49.3 | J23: MBR-2026-0002 | L23: Revenue net of VAT - Nile Breeze
A24: JV-0007 | B24: 46256 | C24: 2-3100 | D24: =IFERROR(INDEX(TB_COA!$B$5:$B$1000,MATCH(C24,TB_COA!$A$5:$A$1000,0)),"") -> Output VAT Payable (14%) | E24: 0 | F24: =E22-F23 -> 146213.42 | G24: =G22-G23 -> 2965.7895 | H24: USD | I24: 49.3 | J24: MBR-2026-0002 | L24: Output VAT 14% - Nile Breeze
A25: JV-0008 | B25: 46258 | C25: 1-2200 | D25: =IFERROR(INDEX(TB_COA!$B$5:$B$1000,MATCH(C25,TB_COA!$A$5:$A$1000,0)),"") -> AR - Foreign Tour Operators (Control) | E25: =TB_Master_Bookings!M12 -> 1376320 | F25: 0 | G25: =TB_Master_Bookings!K12 -> 21760 | H25: GBP | I25: 63.25 | J25: MBR-2026-0003 | L25: Client invoice - London Escape (MBR-2026-0003)
A26: JV-0008 | B26: 46258 | C26: 4-2000 | D26: =IFERROR(INDEX(TB_COA!$B$5:$B$1000,MATCH(C26,TB_COA!$A$5:$A$1000,0)),"") -> Revenue - Package Tours | E26: 0 | F26: =E25/1.14 -> 1207298.2 | G26: =G25/1.14 -> 19087.719 | H26: GBP | I26: 63.25 | J26: MBR-2026-0003 | L26: Revenue net of VAT - London Escape
A27: JV-0008 | B27: 46258 | C27: 2-3100 | D27: =IFERROR(INDEX(TB_COA!$B$5:$B$1000,MATCH(C27,TB_COA!$A$5:$A$1000,0)),"") -> Output VAT Payable (14%) | E27: 0 | F27: =E25-F26 -> 169021.75 | G27: =G25-G26 -> 2672.2807 | H27: GBP | I27: 63.25 | J27: MBR-2026-0003 | L27: Output VAT 14% - London Escape
A28: JV-0009 | B28: 46256 | C28: 1-2200 | D28: =IFERROR(INDEX(TB_COA!$B$5:$B$1000,MATCH(C28,TB_COA!$A$5:$A$1000,0)),"") -> AR - Foreign Tour Operators (Control) | E28: =TB_Master_Bookings!M13 -> 2070600 | F28: 0 | G28: =TB_Master_Bookings!K13 -> 42000 | H28: USD | I28: 49.3 | J28: MBR-2026-0004 | L28: Client invoice - Gulf Adventures (MBR-2026-0004)
A29: JV-0009 | B29: 46256 | C29: 4-2000 | D29: =IFERROR(INDEX(TB_COA!$B$5:$B$1000,MATCH(C29,TB_COA!$A$5:$A$1000,0)),"") -> Revenue - Package Tours | E29: 0 | F29: =E28/1.14 -> 1816315.8 | G29: =G28/1.14 -> 36842.105 | H29: USD | I29: 49.3 | J29: MBR-2026-0004 | L29: Revenue net of VAT - Gulf Adventures
A30: JV-0009 | B30: 46256 | C30: 2-3100 | D30: =IFERROR(INDEX(TB_COA!$B$5:$B$1000,MATCH(C30,TB_COA!$A$5:$A$1000,0)),"") -> Output VAT Payable (14%) | E30: 0 | F30: =E28-F29 -> 254284.21 | G30: =G28-G29 -> 5157.8947 | H30: USD | I30: 49.3 | J30: MBR-2026-0004 | L30: Output VAT 14% - Gulf Adventures
A31: JV-0010 | B31: 46259 | C31: 1-2200 | D31: =IFERROR(INDEX(TB_COA!$B$5:$B$1000,MATCH(C31,TB_COA!$A$5:$A$1000,0)),"") -> AR - Foreign Tour Operators (Control) | E31: =TB_Master_Bookings!M14 -> 2103920 | F31: 0 | G31: =TB_Master_Bookings!K14 -> 38675 | H31: EUR | I31: 54.4 | J31: MBR-2026-0005 | L31: Client invoice - Red Sea Direct (MBR-2026-0005)
A32: JV-0010 | B32: 46259 | C32: 4-2000 | D32: =IFERROR(INDEX(TB_COA!$B$5:$B$1000,MATCH(C32,TB_COA!$A$5:$A$1000,0)),"") -> Revenue - Package Tours | E32: 0 | F32: =E31/1.14 -> 1845543.9 | G32: =G31/1.14 -> 33925.439 | H32: EUR | I32: 54.4 | J32: MBR-2026-0005 | L32: Revenue net of VAT - Red Sea Direct
A33: JV-0010 | B33: 46259 | C33: 2-3100 | D33: =IFERROR(INDEX(TB_COA!$B$5:$B$1000,MATCH(C33,TB_COA!$A$5:$A$1000,0)),"") -> Output VAT Payable (14%) | E33: 0 | F33: =E31-F32 -> 258376.14 | G33: =G31-G32 -> 4749.5614 | H33: EUR | I33: 54.4 | J33: MBR-2026-0005 | L33: Output VAT 14% - Red Sea Direct
A34: JV-0011 | B34: 46242 | C34: 5-2000 | D34: =IFERROR(INDEX(TB_COA!$B$5:$B$1000,MATCH(C34,TB_COA!$A$5:$A$1000,0)),"") -> COGS - Package Tours | E34: =TB_AP_Invoices!K4 -> 4717263.2 | F34: 0 | G34: =TB_AP_Invoices!I4 -> 100800 | H34: EUR | I34: 53.35 | J34: ACR-0001 | L34: Hotel cost accrual - Steigenberger Aldau Beach (ACR-0001)
A35: JV-0011 | B35: 46242 | C35: 1-3400 | D35: =IFERROR(INDEX(TB_COA!$B$5:$B$1000,MATCH(C35,TB_COA!$A$5:$A$1000,0)),"") -> VAT Recoverable / Input VAT | E35: =TB_AP_Invoices!L4 -> 660416.84 | F35: 0 | G35: 0 | J35: ACR-0001 | L35: Input VAT 14% on hotel cost - Steigenberger Aldau Beach
A36: JV-0011 | B36: 46242 | C36: 2-1200 | D36: =IFERROR(INDEX(TB_COA!$B$5:$B$1000,MATCH(C36,TB_COA!$A$5:$A$1000,0)),"") -> AP - Foreign Hotels & Suppliers | E36: 0 | F36: =TB_AP_Invoices!M4 -> 5377680 | G36: =TB_AP_Invoices!I4 -> 100800 | H36: EUR | I36: 53.35 | J36: ACR-0001 | L36: Hotel liability - Steigenberger Aldau Beach
A37: JV-0012 | B37: 46243 | C37: 5-2000 | D37: =IFERROR(INDEX(TB_COA!$B$5:$B$1000,MATCH(C37,TB_COA!$A$5:$A$1000,0)),"") -> COGS - Package Tours | E37: =TB_AP_Invoices!K5 -> 882221.05 | F37: 0 | G37: =TB_AP_Invoices!I5 -> 20475 | H37: USD | I37: 49.12 | J37: ACR-0002 | L37: Hotel cost accrual - Jaz Aquamarine Resort (ACR-0002)
A38: JV-0012 | B38: 46243 | C38: 1-3400 | D38: =IFERROR(INDEX(TB_COA!$B$5:$B$1000,MATCH(C38,TB_COA!$A$5:$A$1000,0)),"") -> VAT Recoverable / Input VAT | E38: =TB_AP_Invoices!L5 -> 123510.95 | F38: 0 | G38: 0 | J38: ACR-0002 | L38: Input VAT 14% on hotel cost - Jaz Aquamarine Resort
A39: JV-0012 | B39: 46243 | C39: 2-1200 | D39: =IFERROR(INDEX(TB_COA!$B$5:$B$1000,MATCH(C39,TB_COA!$A$5:$A$1000,0)),"") -> AP - Foreign Hotels & Suppliers | E39: 0 | F39: =TB_AP_Invoices!M5 -> 1005732 | G39: =TB_AP_Invoices!I5 -> 20475 | H39: USD | I39: 49.12 | J39: ACR-0002 | L39: Hotel liability - Jaz Aquamarine Resort
A40: JV-0013 | B40: 46244 | C40: 5-2000 | D40: =IFERROR(INDEX(TB_COA!$B$5:$B$1000,MATCH(C40,TB_COA!$A$5:$A$1000,0)),"") -> COGS - Package Tours | E40: =TB_AP_Invoices!K6 -> 711531.58 | F40: 0 | G40: =TB_AP_Invoices!I6 -> 13020 | H40: GBP | I40: 62.3 | J40: ACR-0003 | L40: Hotel cost accrual - Sunrise Grand Select (ACR-0003)
A41: JV-0013 | B41: 46244 | C41: 1-3400 | D41: =IFERROR(INDEX(TB_COA!$B$5:$B$1000,MATCH(C41,TB_COA!$A$5:$A$1000,0)),"") -> VAT Recoverable / Input VAT | E41: =TB_AP_Invoices!L6 -> 99614.421 | F41: 0 | G41: 0 | J41: ACR-0003 | L41: Input VAT 14% on hotel cost - Sunrise Grand Select
A42: JV-0013 | B42: 46244 | C42: 2-1200 | D42: =IFERROR(INDEX(TB_COA!$B$5:$B$1000,MATCH(C42,TB_COA!$A$5:$A$1000,0)),"") -> AP - Foreign Hotels & Suppliers | E42: 0 | F42: =TB_AP_Invoices!M6 -> 811146 | G42: =TB_AP_Invoices!I6 -> 13020 | H42: GBP | I42: 62.3 | J42: ACR-0003 | L42: Hotel liability - Sunrise Grand Select
A43: JV-0014 | B43: 46241 | C43: 5-2000 | D43: =IFERROR(INDEX(TB_COA!$B$5:$B$1000,MATCH(C43,TB_COA!$A$5:$A$1000,0)),"") -> COGS - Package Tours | E43: =(TB_Hotel_Accruals!I7/1.14) -> 809431.58 | F43: 0 | G43: =TB_Hotel_Accruals!G7 -> 17280 | H43: EUR | I43: 53.4 | J43: ACR-0004 | L43: Hotel cost accrual - Pickalbatros Aqua Blu (ACR-0004)
A44: JV-0014 | B44: 46241 | C44: 1-3400 | D44: =IFERROR(INDEX(TB_COA!$B$5:$B$1000,MATCH(C44,TB_COA!$A$5:$A$1000,0)),"") -> VAT Recoverable / Input VAT | E44: =TB_Hotel_Accruals!I7-(TB_Hotel_Accruals!I7/1.14) -> 113320.42 | F44: 0 | G44: 0 | J44: ACR-0004 | L44: Input VAT 14% on hotel cost - Pickalbatros Aqua Blu
A45: JV-0014 | B45: 46241 | C45: 2-1200 | D45: =IFERROR(INDEX(TB_COA!$B$5:$B$1000,MATCH(C45,TB_COA!$A$5:$A$1000,0)),"") -> AP - Foreign Hotels & Suppliers | E45: 0 | F45: =TB_Hotel_Accruals!I7 -> 922752 | G45: =TB_Hotel_Accruals!G7 -> 17280 | H45: EUR | I45: 53.4 | J45: ACR-0004 | L45: Hotel liability - Pickalbatros Aqua Blu
A46: JV-0015 | B46: 46243 | C46: 5-2000 | D46: =IFERROR(INDEX(TB_COA!$B$5:$B$1000,MATCH(C46,TB_COA!$A$5:$A$1000,0)),"") -> COGS - Package Tours | E46: =(TB_Hotel_Accruals!I8/1.14) -> 108581.05 | F46: 0 | G46: =TB_Hotel_Accruals!G8 -> 2520 | H46: USD | I46: 49.12 | J46: ACR-0005 | L46: Hotel cost accrual - Sunny Days El Palacio (ACR-0005)
A47: JV-0015 | B47: 46243 | C47: 1-3400 | D47: =IFERROR(INDEX(TB_COA!$B$5:$B$1000,MATCH(C47,TB_COA!$A$5:$A$1000,0)),"") -> VAT Recoverable / Input VAT | E47: =TB_Hotel_Accruals!I8-(TB_Hotel_Accruals!I8/1.14) -> 15201.347 | F47: 0 | G47: 0 | J47: ACR-0005 | L47: Input VAT 14% on hotel cost - Sunny Days El Palacio
A48: JV-0015 | B48: 46243 | C48: 2-1200 | D48: =IFERROR(INDEX(TB_COA!$B$5:$B$1000,MATCH(C48,TB_COA!$A$5:$A$1000,0)),"") -> AP - Foreign Hotels & Suppliers | E48: 0 | F48: =TB_Hotel_Accruals!I8 -> 123782.4 | G48: =TB_Hotel_Accruals!G8 -> 2520 | H48: USD | I48: 49.12 | J48: ACR-0005 | L48: Hotel liability - Sunny Days El Palacio
A49: JV-0016 | B49: 46256 | C49: 5-2000 | D49: =IFERROR(INDEX(TB_COA!$B$5:$B$1000,MATCH(C49,TB_COA!$A$5:$A$1000,0)),"") -> COGS - Package Tours | E49: =TB_AP_Invoices!K7 -> 5058666.7 | F49: 0 | G49: =TB_AP_Invoices!I7 -> 106400 | H49: EUR | I49: 54.2 | J49: ACC-0001 | L49: Hotel cost accrual - Sun & Sea Beach Resort (ACC-0001)
A50: JV-0016 | B50: 46256 | C50: 1-3400 | D50: =IFERROR(INDEX(TB_COA!$B$5:$B$1000,MATCH(C50,TB_COA!$A$5:$A$1000,0)),"") -> VAT Recoverable / Input VAT | E50: =TB_AP_Invoices!L7 -> 708213.33 | F50: 0 | G50: 0 | J50: ACC-0001 | L50: Input VAT 14% on hotel cost - Sun & Sea Beach Resort
A51: JV-0016 | B51: 46256 | C51: 2-1200 | D51: =IFERROR(INDEX(TB_COA!$B$5:$B$1000,MATCH(C51,TB_COA!$A$5:$A$1000,0)),"") -> AP - Foreign Hotels & Suppliers | E51: 0 | F51: =TB_AP_Invoices!M7 -> 5766880 | G51: =TB_AP_Invoices!I7 -> 106400 | H51: EUR | I51: 54.2 | J51: ACC-0001 | L51: Hotel liability - Sun & Sea Beach Resort
A52: JV-0017 | B52: 46256 | C52: 5-2000 | D52: =IFERROR(INDEX(TB_COA!$B$5:$B$1000,MATCH(C52,TB_COA!$A$5:$A$1000,0)),"") -> COGS - Package Tours | E52: =TB_AP_Invoices!K8 -> 835505.26 | F52: 0 | G52: =TB_AP_Invoices!I8 -> 19320 | H52: USD | I52: 49.3 | J52: ACC-0002 | L52: Hotel cost accrual - Coral Hills Resort (ACC-0002)
A53: JV-0017 | B53: 46256 | C53: 1-3400 | D53: =IFERROR(INDEX(TB_COA!$B$5:$B$1000,MATCH(C53,TB_COA!$A$5:$A$1000,0)),"") -> VAT Recoverable / Input VAT | E53: =TB_AP_Invoices!L8 -> 116970.74 | F53: 0 | G53: 0 | J53: ACC-0002 | L53: Input VAT 14% on hotel cost - Coral Hills Resort
A54: JV-0017 | B54: 46256 | C54: 2-1200 | D54: =IFERROR(INDEX(TB_COA!$B$5:$B$1000,MATCH(C54,TB_COA!$A$5:$A$1000,0)),"") -> AP - Foreign Hotels & Suppliers | E54: 0 | F54: =TB_AP_Invoices!M8 -> 952476 | G54: =TB_AP_Invoices!I8 -> 19320 | H54: USD | I54: 49.3 | J54: ACC-0002 | L54: Hotel liability - Coral Hills Resort
A55: JV-0018 | B55: 46258 | C55: 5-2000 | D55: =IFERROR(INDEX(TB_COA!$B$5:$B$1000,MATCH(C55,TB_COA!$A$5:$A$1000,0)),"") -> COGS - Package Tours | E55: =TB_AP_Invoices!K9 -> 965838.6 | F55: 0 | G55: =TB_AP_Invoices!I9 -> 17408 | H55: GBP | I55: 63.25 | J55: ACC-0003 | L55: Hotel cost accrual - Blue Lagoon Palace (ACC-0003)
A56: JV-0018 | B56: 46258 | C56: 1-3400 | D56: =IFERROR(INDEX(TB_COA!$B$5:$B$1000,MATCH(C56,TB_COA!$A$5:$A$1000,0)),"") -> VAT Recoverable / Input VAT | E56: =TB_AP_Invoices!L9 -> 135217.4 | F56: 0 | G56: 0 | J56: ACC-0003 | L56: Input VAT 14% on hotel cost - Blue Lagoon Palace
A57: JV-0018 | B57: 46258 | C57: 2-1200 | D57: =IFERROR(INDEX(TB_COA!$B$5:$B$1000,MATCH(C57,TB_COA!$A$5:$A$1000,0)),"") -> AP - Foreign Hotels & Suppliers | E57: 0 | F57: =TB_AP_Invoices!M9 -> 1101056 | G57: =TB_AP_Invoices!I9 -> 17408 | H57: GBP | I57: 63.25 | J57: ACC-0003 | L57: Hotel liability - Blue Lagoon Palace
A58: JV-0019 | B58: 46256 | C58: 5-2000 | D58: =IFERROR(INDEX(TB_COA!$B$5:$B$1000,MATCH(C58,TB_COA!$A$5:$A$1000,0)),"") -> COGS - Package Tours | E58: =TB_AP_Invoices!K10 -> 1453052.6 | F58: 0 | G58: =TB_AP_Invoices!I10 -> 33600 | H58: USD | I58: 49.3 | J58: ACC-0004 | L58: Hotel cost accrual - Desert Rose Plaza (ACC-0004)
A59: JV-0019 | B59: 46256 | C59: 1-3400 | D59: =IFERROR(INDEX(TB_COA!$B$5:$B$1000,MATCH(C59,TB_COA!$A$5:$A$1000,0)),"") -> VAT Recoverable / Input VAT | E59: =TB_AP_Invoices!L10 -> 203427.37 | F59: 0 | G59: 0 | J59: ACC-0004 | L59: Input VAT 14% on hotel cost - Desert Rose Plaza
A60: JV-0019 | B60: 46256 | C60: 2-1200 | D60: =IFERROR(INDEX(TB_COA!$B$5:$B$1000,MATCH(C60,TB_COA!$A$5:$A$1000,0)),"") -> AP - Foreign Hotels & Suppliers | E60: 0 | F60: =TB_AP_Invoices!M10 -> 1656480 | G60: =TB_AP_Invoices!I10 -> 33600 | H60: USD | I60: 49.3 | J60: ACC-0004 | L60: Hotel liability - Desert Rose Plaza
A61: JV-0020 | B61: 46259 | C61: 5-2000 | D61: =IFERROR(INDEX(TB_COA!$B$5:$B$1000,MATCH(C61,TB_COA!$A$5:$A$1000,0)),"") -> COGS - Package Tours | E61: =TB_AP_Invoices!K11 -> 1476435.1 | F61: 0 | G61: =TB_AP_Invoices!I11 -> 30940 | H61: EUR | I61: 54.4 | J61: ACC-0005 | L61: Hotel cost accrual - Seagull Beach Resort (ACC-0005)
A62: JV-0020 | B62: 46259 | C62: 1-3400 | D62: =IFERROR(INDEX(TB_COA!$B$5:$B$1000,MATCH(C62,TB_COA!$A$5:$A$1000,0)),"") -> VAT Recoverable / Input VAT | E62: =TB_AP_Invoices!L11 -> 206700.91 | F62: 0 | G62: 0 | J62: ACC-0005 | L62: Input VAT 14% on hotel cost - Seagull Beach Resort
A63: JV-0020 | B63: 46259 | C63: 2-1200 | D63: =IFERROR(INDEX(TB_COA!$B$5:$B$1000,MATCH(C63,TB_COA!$A$5:$A$1000,0)),"") -> AP - Foreign Hotels & Suppliers | E63: 0 | F63: =TB_AP_Invoices!M11 -> 1683136 | G63: =TB_AP_Invoices!I11 -> 30940 | H63: EUR | I63: 54.4 | J63: ACC-0005 | L63: Hotel liability - Seagull Beach Resort
A64: JV-0021 | B64: 46244 | C64: 1-1103 | D64: =IFERROR(INDEX(TB_COA!$B$5:$B$1000,MATCH(C64,TB_COA!$A$5:$A$1000,0)),"") -> Bank Account - EUR | E64: 6741000 | F64: 0 | G64: 126000 | H64: EUR | I64: 53.5 | J64: PAY-0815 | L64: Client collection - Alpine Sun Tours Group (HRG-2026-0815)
A65: JV-0021 | B65: 46244 | C65: 1-2200 | D65: =IFERROR(INDEX(TB_COA!$B$5:$B$1000,MATCH(C65,TB_COA!$A$5:$A$1000,0)),"") -> AR - Foreign Tour Operators (Control) | E65: 0 | F65: 6722100 | G65: 126000 | H65: EUR | I65: 53.35 | J65: PAY-0815 | L65: AR settlement - Alpine Sun Tours Group
A66: JV-0021 | B66: 46244 | C66: 7-1000 | D66: =IFERROR(INDEX(TB_COA!$B$5:$B$1000,MATCH(C66,TB_COA!$A$5:$A$1000,0)),"") -> Realized FX Gain | E66: 0 | F66: 18900 | G66: 0 | J66: PAY-0815 | K66: Realized Gain | L66: FX gain EUR (53.5-53.35)*126000
A67: JV-0022 | B67: 46246 | C67: 1-1102 | D67: =IFERROR(INDEX(TB_COA!$B$5:$B$1000,MATCH(C67,TB_COA!$A$5:$A$1000,0)),"") -> Bank Account - USD | E67: 1272127.5 | F67: 0 | G67: 25830 | H67: USD | I67: 49.25 | J67: PAY-0816 | L67: Client collection - Nordic Wave Charter (HRG-2026-0816)
A68: JV-0022 | B68: 46246 | C68: 1-2200 | D68: =IFERROR(INDEX(TB_COA!$B$5:$B$1000,MATCH(C68,TB_COA!$A$5:$A$1000,0)),"") -> AR - Foreign Tour Operators (Control) | E68: 0 | F68: 1268769.6 | G68: 25830 | H68: USD | I68: 49.12 | J68: PAY-0816 | L68: AR settlement - Nordic Wave Charter
A69: JV-0022 | B69: 46246 | C69: 7-1000 | D69: =IFERROR(INDEX(TB_COA!$B$5:$B$1000,MATCH(C69,TB_COA!$A$5:$A$1000,0)),"") -> Realized FX Gain | E69: 0 | F69: 3357.9 | G69: 0 | J69: PAY-0816 | K69: Realized Gain | L69: FX gain USD (49.25-49.12)*25830
A70: JV-0023 | B70: 46246 | C70: 1-1103 | D70: =IFERROR(INDEX(TB_COA!$B$5:$B$1000,MATCH(C70,TB_COA!$A$5:$A$1000,0)),"") -> Bank Account - EUR | E70: 1022931 | F70: 0 | G70: 16380 | H70: GBP | I70: 62.45 | J70: PAY-0817 | L70: Client collection - BritSun Holidays (HRG-2026-0817)
A71: JV-0023 | B71: 46246 | C71: 1-2200 | D71: =IFERROR(INDEX(TB_COA!$B$5:$B$1000,MATCH(C71,TB_COA!$A$5:$A$1000,0)),"") -> AR - Foreign Tour Operators (Control) | E71: 0 | F71: 1020474 | G71: 16380 | H71: GBP | I71: 62.3 | J71: PAY-0817 | L71: AR settlement - BritSun Holidays
A72: JV-0023 | B72: 46246 | C72: 7-1000 | D72: =IFERROR(INDEX(TB_COA!$B$5:$B$1000,MATCH(C72,TB_COA!$A$5:$A$1000,0)),"") -> Realized FX Gain | E72: 0 | F72: 2457 | G72: 0 | J72: PAY-0817 | K72: Realized Gain | L72: FX gain GBP (62.45-62.3)*16380
A73: JV-0024 | B73: 46244 | C73: 1-1103 | D73: =IFERROR(INDEX(TB_COA!$B$5:$B$1000,MATCH(C73,TB_COA!$A$5:$A$1000,0)),"") -> Bank Account - EUR | E73: 1156680 | F73: 0 | G73: 21600 | H73: EUR | I73: 53.55 | J73: PAY-0818 | L73: Client collection - Meridian Voyages (HRG-2026-0818)
A74: JV-0024 | B74: 46244 | C74: 1-2200 | D74: =IFERROR(INDEX(TB_COA!$B$5:$B$1000,MATCH(C74,TB_COA!$A$5:$A$1000,0)),"") -> AR - Foreign Tour Operators (Control) | E74: 0 | F74: 1153440 | G74: 21600 | H74: EUR | I74: 53.4 | J74: PAY-0818 | L74: AR settlement - Meridian Voyages
A75: JV-0024 | B75: 46244 | C75: 7-1000 | D75: =IFERROR(INDEX(TB_COA!$B$5:$B$1000,MATCH(C75,TB_COA!$A$5:$A$1000,0)),"") -> Realized FX Gain | E75: 0 | F75: 3240 | G75: 0 | J75: PAY-0818 | K75: Realized Gain | L75: FX gain EUR (53.55-53.4)*21600
A76: JV-0025 | B76: 46246 | C76: 1-1102 | D76: =IFERROR(INDEX(TB_COA!$B$5:$B$1000,MATCH(C76,TB_COA!$A$5:$A$1000,0)),"") -> Bank Account - USD | E76: 156456 | F76: 0 | G76: 3180 | H76: USD | I76: 49.2 | J76: PAY-0819 | L76: Client collection - Red Sea Direct Bookings (HRG-2026-0819)
A77: JV-0025 | B77: 46246 | C77: 1-2200 | D77: =IFERROR(INDEX(TB_COA!$B$5:$B$1000,MATCH(C77,TB_COA!$A$5:$A$1000,0)),"") -> AR - Foreign Tour Operators (Control) | E77: 0 | F77: 156201.6 | G77: 3180 | H77: USD | I77: 49.12 | J77: PAY-0819 | L77: AR settlement - Red Sea Direct Bookings
A78: JV-0025 | B78: 46246 | C78: 7-1000 | D78: =IFERROR(INDEX(TB_COA!$B$5:$B$1000,MATCH(C78,TB_COA!$A$5:$A$1000,0)),"") -> Realized FX Gain | E78: 0 | F78: 254.4 | G78: 0 | J78: PAY-0819 | K78: Realized Gain | L78: FX gain USD (49.2-49.12)*3180
A79: JV-0026 | B79: 46259 | C79: 1-1103 | D79: =IFERROR(INDEX(TB_COA!$B$5:$B$1000,MATCH(C79,TB_COA!$A$5:$A$1000,0)),"") -> Bank Account - EUR | E79: 7235200 | F79: 0 | G79: 133000 | H79: EUR | I79: 54.4 | J79: PAY-0001 | L79: Client collection - EuroSun Tours (MBR-2026-0001)
A80: JV-0026 | B80: 46259 | C80: 1-2200 | D80: =IFERROR(INDEX(TB_COA!$B$5:$B$1000,MATCH(C80,TB_COA!$A$5:$A$1000,0)),"") -> AR - Foreign Tour Operators (Control) | E80: 0 | F80: 7208600 | G80: 133000 | H80: EUR | I80: 54.2 | J80: PAY-0001 | L80: AR settlement - EuroSun Tours
A81: JV-0026 | B81: 46259 | C81: 7-1000 | D81: =IFERROR(INDEX(TB_COA!$B$5:$B$1000,MATCH(C81,TB_COA!$A$5:$A$1000,0)),"") -> Realized FX Gain | E81: 0 | F81: 26600 | G81: 0 | J81: PAY-0001 | K81: Realized Gain | L81: FX gain EUR (54.4-54.2)*133000
A82: JV-0027 | B82: 46249 | C82: 2-1200 | D82: =IFERROR(INDEX(TB_COA!$B$5:$B$1000,MATCH(C82,TB_COA!$A$5:$A$1000,0)),"") -> AP - Foreign Hotels & Suppliers | E82: =F36 -> 5377680 | F82: 0 | G82: 0 | J82: PAYH-0001 | L82: Hotel payment - Steigenberger Aldau Beach (ACR-0001)
A83: JV-0027 | B83: 46249 | C83: 6-8000 | D83: =IFERROR(INDEX(TB_COA!$B$5:$B$1000,MATCH(C83,TB_COA!$A$5:$A$1000,0)),"") -> Bank Charges & Realized FX Loss | E83: 10080 | F83: 0 | G83: 0 | J83: PAYH-0001 | K83: Realized Loss | L83: FX loss on payment EUR (53.45-53.35)*100800
A84: JV-0027 | B84: 46249 | C84: 1-1103 | D84: =IFERROR(INDEX(TB_COA!$B$5:$B$1000,MATCH(C84,TB_COA!$A$5:$A$1000,0)),"") -> Bank Account - EUR | E84: 0 | F84: =E82+E83-F85 -> 5246242.1 | G84: 100800 | H84: EUR | I84: 53.45 | J84: PAYH-0001 | L84: Bank transfer - Steigenberger Aldau Beach
A85: JV-0027 | B85: 46249 | C85: 2-3200 | D85: =IFERROR(INDEX(TB_COA!$B$5:$B$1000,MATCH(C85,TB_COA!$A$5:$A$1000,0)),"") -> Withholding Tax Payable | E85: 0 | F85: =TB_WHT_Quarterly!F4 -> 141517.89 | G85: 0 | J85: PAYH-0001 | L85: WHT 3% on Steigenberger Aldau Beach cost=5377680.00
A86: JV-0028 | B86: 46250 | C86: 2-1200 | D86: =IFERROR(INDEX(TB_COA!$B$5:$B$1000,MATCH(C86,TB_COA!$A$5:$A$1000,0)),"") -> AP - Foreign Hotels & Suppliers | E86: =F39 -> 1005732 | F86: 0 | G86: 0 | J86: PAYH-0002 | L86: Hotel payment - Jaz Aquamarine Resort (ACR-0002)
A87: JV-0028 | B87: 46250 | C87: 6-8000 | D87: =IFERROR(INDEX(TB_COA!$B$5:$B$1000,MATCH(C87,TB_COA!$A$5:$A$1000,0)),"") -> Bank Charges & Realized FX Loss | E87: 614.25 | F87: 0 | G87: 0 | J87: PAYH-0002 | K87: Realized Loss | L87: FX loss on payment USD (49.15-49.12)*20475
A88: JV-0028 | B88: 46250 | C88: 1-1102 | D88: =IFERROR(INDEX(TB_COA!$B$5:$B$1000,MATCH(C88,TB_COA!$A$5:$A$1000,0)),"") -> Bank Account - USD | E88: 0 | F88: =E86+E87-F89 -> 979879.62 | G88: 20475 | H88: USD | I88: 49.15 | J88: PAYH-0002 | L88: Bank transfer - Jaz Aquamarine Resort
A89: JV-0028 | B89: 46250 | C89: 2-3200 | D89: =IFERROR(INDEX(TB_COA!$B$5:$B$1000,MATCH(C89,TB_COA!$A$5:$A$1000,0)),"") -> Withholding Tax Payable | E89: 0 | F89: =TB_WHT_Quarterly!F5 -> 26466.632 | G89: 0 | J89: PAYH-0002 | L89: WHT 3% on Jaz Aquamarine Resort cost=1005732.00
A90: JV-0029 | B90: 46251 | C90: 2-1200 | D90: =IFERROR(INDEX(TB_COA!$B$5:$B$1000,MATCH(C90,TB_COA!$A$5:$A$1000,0)),"") -> AP - Foreign Hotels & Suppliers | E90: =F42 -> 811146 | F90: 0 | G90: 0 | J90: PAYH-0003 | L90: Hotel payment - Sunrise Grand Select (ACR-0003)
A91: JV-0029 | B91: 46251 | C91: 6-8000 | D91: =IFERROR(INDEX(TB_COA!$B$5:$B$1000,MATCH(C91,TB_COA!$A$5:$A$1000,0)),"") -> Bank Charges & Realized FX Loss | E91: 651 | F91: 0 | G91: 0 | J91: PAYH-0003 | K91: Realized Loss | L91: FX loss on payment GBP (62.35-62.3)*13020
A92: JV-0029 | B92: 46251 | C92: 1-1103 | D92: =IFERROR(INDEX(TB_COA!$B$5:$B$1000,MATCH(C92,TB_COA!$A$5:$A$1000,0)),"") -> Bank Account - EUR | E92: 0 | F92: =E90+E91-F93 -> 790451.05 | G92: 13020 | H92: GBP | I92: 62.35 | J92: PAYH-0003 | L92: Bank transfer - Sunrise Grand Select
A93: JV-0029 | B93: 46251 | C93: 2-3200 | D93: =IFERROR(INDEX(TB_COA!$B$5:$B$1000,MATCH(C93,TB_COA!$A$5:$A$1000,0)),"") -> Withholding Tax Payable | E93: 0 | F93: =TB_WHT_Quarterly!F6 -> 21345.947 | G93: 0 | J93: PAYH-0003 | L93: WHT 3% on Sunrise Grand Select cost=811146.00
A94: JV-0030 | B94: 46248 | C94: 2-1200 | D94: =IFERROR(INDEX(TB_COA!$B$5:$B$1000,MATCH(C94,TB_COA!$A$5:$A$1000,0)),"") -> AP - Foreign Hotels & Suppliers | E94: =F45 -> 922752 | F94: 0 | G94: 0 | J94: PAYH-0004 | L94: Hotel payment - Pickalbatros Aqua Blu (ACR-0004)
A95: JV-0030 | B95: 46248 | C95: 6-8000 | D95: =IFERROR(INDEX(TB_COA!$B$5:$B$1000,MATCH(C95,TB_COA!$A$5:$A$1000,0)),"") -> Bank Charges & Realized FX Loss | E95: 1728 | F95: 0 | G95: 0 | J95: PAYH-0004 | K95: Realized Loss | L95: FX loss on payment EUR (53.5-53.4)*17280
A96: JV-0030 | B96: 46248 | C96: 1-1103 | D96: =IFERROR(INDEX(TB_COA!$B$5:$B$1000,MATCH(C96,TB_COA!$A$5:$A$1000,0)),"") -> Bank Account - EUR | E96: 0 | F96: =E94+E95-F97 -> 900197.05 | G96: 17280 | H96: EUR | I96: 53.5 | J96: PAYH-0004 | L96: Bank transfer - Pickalbatros Aqua Blu
A97: JV-0030 | B97: 46248 | C97: 2-3200 | D97: =IFERROR(INDEX(TB_COA!$B$5:$B$1000,MATCH(C97,TB_COA!$A$5:$A$1000,0)),"") -> Withholding Tax Payable | E97: 0 | F97: =TB_WHT_Quarterly!F7 -> 24282.947 | G97: 0 | J97: PAYH-0004 | L97: WHT 3% on Pickalbatros Aqua Blu cost=922752.00
A98: JV-0031 | B98: 46248 | C98: 2-1200 | D98: =IFERROR(INDEX(TB_COA!$B$5:$B$1000,MATCH(C98,TB_COA!$A$5:$A$1000,0)),"") -> AP - Foreign Hotels & Suppliers | E98: =F48 -> 123782.4 | F98: 0 | G98: 0 | J98: PAYH-0005 | L98: Hotel payment - Sunny Days El Palacio (ACR-0005)
A99: JV-0031 | B99: 46248 | C99: 6-8000 | D99: =IFERROR(INDEX(TB_COA!$B$5:$B$1000,MATCH(C99,TB_COA!$A$5:$A$1000,0)),"") -> Bank Charges & Realized FX Loss | E99: 50.4 | F99: 0 | G99: 0 | J99: PAYH-0005 | K99: Realized Loss | L99: FX loss on payment USD (49.14-49.12)*2520
A100: JV-0031 | B100: 46248 | C100: 1-1102 | D100: =IFERROR(INDEX(TB_COA!$B$5:$B$1000,MATCH(C100,TB_COA!$A$5:$A$1000,0)),"") -> Bank Account - USD | E100: 0 | F100: =E98+E99-F101 -> 120575.37 | G100: 2520 | H100: USD | I100: 49.14 | J100: PAYH-0005 | L100: Bank transfer - Sunny Days El Palacio
...

Sheet TB_Trial_Balance
A1: MODULE: TRIAL BALANCE | J1: 🏠 Back to Home
A2: Live account balances aggregated from TB_General_Journal. Debit = Credit, always.
A3: Account_Code | B3: Account_Name | C3: Account_Type | D3: Debit_Movement_EGP | E3: Credit_Movement_EGP | F3: Opening_Balance_EGP | G3: Closing_Balance_EGP | H3: Balance_Type
A4: =IFERROR(INDEX(TB_COA!$A$5:$A$49,ROW()-3),"") -> 1-1001 | B4: =IF($A4="","",IFERROR(INDEX(TB_COA!$B$5:$B$49,MATCH($A4,TB_COA!$A$5:$A$49,0)),"ACCOUNT NOT FOUND")) -> Main Safe - EGP | C4: =IF($A4="","",IFERROR(INDEX(TB_COA!$C$5:$C$49,MATCH($A4,TB_COA!$A$5:$A$49,0)),"ACCOUNT NOT FOUND")) -> Asset | D4: =IF($A4="","",SUMIFS(TB_General_Journal!$E:$E,TB_General_Journal!$C:$C,$A4)) -> 44642.95 | E4: =IF($A4="","",SUMIFS(TB_General_Journal!$F:$F,TB_General_Journal!$C:$C,$A4)) -> 0 | F4: 0 | G4: =F4+D4-E4 -> 44642.95 | H4: =IF(G4="","",IF(G4>0,"Debit",IF(G4<0,"Credit","Zero"))) -> Debit
A5: =IFERROR(INDEX(TB_COA!$A$5:$A$49,ROW()-3),"") -> 1-1002 | B5: =IF($A5="","",IFERROR(INDEX(TB_COA!$B$5:$B$49,MATCH($A5,TB_COA!$A$5:$A$49,0)),"ACCOUNT NOT FOUND")) -> Petty Cash - FCY | C5: =IF($A5="","",IFERROR(INDEX(TB_COA!$C$5:$C$49,MATCH($A5,TB_COA!$A$5:$A$49,0)),"ACCOUNT NOT FOUND")) -> Asset | D5: =IF($A5="","",SUMIFS(TB_General_Journal!$E:$E,TB_General_Journal!$C:$C,$A5)) -> 0 | E5: =IF($A5="","",SUMIFS(TB_General_Journal!$F:$F,TB_General_Journal!$C:$C,$A5)) -> 0 | F5: 0 | G5: =F5+D5-E5 -> 0 | H5: =IF(G5="","",IF(G5>0,"Debit",IF(G5<0,"Credit","Zero"))) -> Zero
A6: =IFERROR(INDEX(TB_COA!$A$5:$A$49,ROW()-3),"") -> 1-1101 | B6: =IF($A6="","",IFERROR(INDEX(TB_COA!$B$5:$B$49,MATCH($A6,TB_COA!$A$5:$A$49,0)),"ACCOUNT NOT FOUND")) -> Bank Account - EGP | C6: =IF($A6="","",IFERROR(INDEX(TB_COA!$C$5:$C$49,MATCH($A6,TB_COA!$A$5:$A$49,0)),"ACCOUNT NOT FOUND")) -> Asset | D6: =IF($A6="","",SUMIFS(TB_General_Journal!$E:$E,TB_General_Journal!$C:$C,$A6)) -> 0 | E6: =IF($A6="","",SUMIFS(TB_General_Journal!$F:$F,TB_General_Journal!$C:$C,$A6)) -> 647567.21 | F6: 0 | G6: =F6+D6-E6 -> -647567.21 | H6: =IF(G6="","",IF(G6>0,"Debit",IF(G6<0,"Credit","Zero"))) -> Credit
A7: =IFERROR(INDEX(TB_COA!$A$5:$A$49,ROW()-3),"") -> 1-1102 | B7: =IF($A7="","",IFERROR(INDEX(TB_COA!$B$5:$B$49,MATCH($A7,TB_COA!$A$5:$A$49,0)),"ACCOUNT NOT FOUND")) -> Bank Account - USD | C7: =IF($A7="","",IFERROR(INDEX(TB_COA!$C$5:$C$49,MATCH($A7,TB_COA!$A$5:$A$49,0)),"ACCOUNT NOT FOUND")) -> Asset | D7: =IF($A7="","",SUMIFS(TB_General_Journal!$E:$E,TB_General_Journal!$C:$C,$A7)) -> 1428583.5 | E7: =IF($A7="","",SUMIFS(TB_General_Journal!$F:$F,TB_General_Journal!$C:$C,$A7)) -> 3651338.2 | F7: 0 | G7: =F7+D7-E7 -> -2222754.8 | H7: =IF(G7="","",IF(G7>0,"Debit",IF(G7<0,"Credit","Zero"))) -> Credit
A8: =IFERROR(INDEX(TB_COA!$A$5:$A$49,ROW()-3),"") -> 1-1103 | B8: =IF($A8="","",IFERROR(INDEX(TB_COA!$B$5:$B$49,MATCH($A8,TB_COA!$A$5:$A$49,0)),"ACCOUNT NOT FOUND")) -> Bank Account - EUR | C8: =IF($A8="","",IFERROR(INDEX(TB_COA!$C$5:$C$49,MATCH($A8,TB_COA!$A$5:$A$49,0)),"ACCOUNT NOT FOUND")) -> Asset | D8: =IF($A8="","",SUMIFS(TB_General_Journal!$E:$E,TB_General_Journal!$C:$C,$A8)) -> 16155811 | E8: =IF($A8="","",SUMIFS(TB_General_Journal!$F:$F,TB_General_Journal!$C:$C,$A8)) -> 15289049 | F8: 0 | G8: =F8+D8-E8 -> 866762.2 | H8: =IF(G8="","",IF(G8>0,"Debit",IF(G8<0,"Credit","Zero"))) -> Debit
A9: =IFERROR(INDEX(TB_COA!$A$5:$A$49,ROW()-3),"") -> 1-1200 | B9: =IF($A9="","",IFERROR(INDEX(TB_COA!$B$5:$B$49,MATCH($A9,TB_COA!$A$5:$A$49,0)),"ACCOUNT NOT FOUND")) -> Rep Cash Advance (Petty Cash) | C9: =IF($A9="","",IFERROR(INDEX(TB_COA!$C$5:$C$49,MATCH($A9,TB_COA!$A$5:$A$49,0)),"ACCOUNT NOT FOUND")) -> Asset | D9: =IF($A9="","",SUMIFS(TB_General_Journal!$E:$E,TB_General_Journal!$C:$C,$A9)) -> 0 | E9: =IF($A9="","",SUMIFS(TB_General_Journal!$F:$F,TB_General_Journal!$C:$C,$A9)) -> 0 | F9: 0 | G9: =F9+D9-E9 -> 0 | H9: =IF(G9="","",IF(G9>0,"Debit",IF(G9<0,"Credit","Zero"))) -> Zero
A10: =IFERROR(INDEX(TB_COA!$A$5:$A$49,ROW()-3),"") -> 1-2100 | B10: =IF($A10="","",IFERROR(INDEX(TB_COA!$B$5:$B$49,MATCH($A10,TB_COA!$A$5:$A$49,0)),"ACCOUNT NOT FOUND")) -> AR - Local Clients / Agents | C10: =IF($A10="","",IFERROR(INDEX(TB_COA!$C$5:$C$49,MATCH($A10,TB_COA!$A$5:$A$49,0)),"ACCOUNT NOT FOUND")) -> Asset | D10: =IF($A10="","",SUMIFS(TB_General_Journal!$E:$E,TB_General_Journal!$C:$C,$A10)) -> 0 | E10: =IF($A10="","",SUMIFS(TB_General_Journal!$F:$F,TB_General_Journal!$C:$C,$A10)) -> 0 | F10: 0 | G10: =F10+D10-E10 -> 0 | H10: =IF(G10="","",IF(G10>0,"Debit",IF(G10<0,"Credit","Zero"))) -> Zero
A11: =IFERROR(INDEX(TB_COA!$A$5:$A$49,ROW()-3),"") -> 1-2200 | B11: =IF($A11="","",IFERROR(INDEX(TB_COA!$B$5:$B$49,MATCH($A11,TB_COA!$A$5:$A$49,0)),"ACCOUNT NOT FOUND")) -> AR - Foreign Tour Operators (Control) | C11: =IF($A11="","",IFERROR(INDEX(TB_COA!$C$5:$C$49,MATCH($A11,TB_COA!$A$5:$A$49,0)),"ACCOUNT NOT FOUND")) -> Asset | D11: =IF($A11="","",SUMIFS(TB_General_Journal!$E:$E,TB_General_Journal!$C:$C,$A11)) -> 24271020 | E11: =IF($A11="","",SUMIFS(TB_General_Journal!$F:$F,TB_General_Journal!$C:$C,$A11)) -> 17529585 | F11: 0 | G11: =F11+D11-E11 -> 6741435 | H11: =IF(G11="","",IF(G11>0,"Debit",IF(G11<0,"Credit","Zero"))) -> Debit
A12: =IFERROR(INDEX(TB_COA!$A$5:$A$49,ROW()-3),"") -> 1-3100 | B12: =IF($A12="","",IFERROR(INDEX(TB_COA!$B$5:$B$49,MATCH($A12,TB_COA!$A$5:$A$49,0)),"ACCOUNT NOT FOUND")) -> Advances to Hotels (Prepayments) | C12: =IF($A12="","",IFERROR(INDEX(TB_COA!$C$5:$C$49,MATCH($A12,TB_COA!$A$5:$A$49,0)),"ACCOUNT NOT FOUND")) -> Asset | D12: =IF($A12="","",SUMIFS(TB_General_Journal!$E:$E,TB_General_Journal!$C:$C,$A12)) -> 0 | E12: =IF($A12="","",SUMIFS(TB_General_Journal!$F:$F,TB_General_Journal!$C:$C,$A12)) -> 0 | F12: 0 | G12: =F12+D12-E12 -> 0 | H12: =IF(G12="","",IF(G12>0,"Debit",IF(G12<0,"Credit","Zero"))) -> Zero
A13: =IFERROR(INDEX(TB_COA!$A$5:$A$49,ROW()-3),"") -> 1-3200 | B13: =IF($A13="","",IFERROR(INDEX(TB_COA!$B$5:$B$49,MATCH($A13,TB_COA!$A$5:$A$49,0)),"ACCOUNT NOT FOUND")) -> Accrued Revenue - Unbilled Services | C13: =IF($A13="","",IFERROR(INDEX(TB_COA!$C$5:$C$49,MATCH($A13,TB_COA!$A$5:$A$49,0)),"ACCOUNT NOT FOUND")) -> Asset | D13: =IF($A13="","",SUMIFS(TB_General_Journal!$E:$E,TB_General_Journal!$C:$C,$A13)) -> 0 | E13: =IF($A13="","",SUMIFS(TB_General_Journal!$F:$F,TB_General_Journal!$C:$C,$A13)) -> 0 | F13: 0 | G13: =F13+D13-E13 -> 0 | H13: =IF(G13="","",IF(G13>0,"Debit",IF(G13<0,"Credit","Zero"))) -> Zero
A14: =IFERROR(INDEX(TB_COA!$A$5:$A$49,ROW()-3),"") -> 1-3300 | B14: =IF($A14="","",IFERROR(INDEX(TB_COA!$B$5:$B$49,MATCH($A14,TB_COA!$A$5:$A$49,0)),"ACCOUNT NOT FOUND")) -> Prepaid Excursion Costs (Allotments) | C14: =IF($A14="","",IFERROR(INDEX(TB_COA!$C$5:$C$49,MATCH($A14,TB_COA!$A$5:$A$49,0)),"ACCOUNT NOT FOUND")) -> Asset | D14: =IF($A14="","",SUMIFS(TB_General_Journal!$E:$E,TB_General_Journal!$C:$C,$A14)) -> 0 | E14: =IF($A14="","",SUMIFS(TB_General_Journal!$F:$F,TB_General_Journal!$C:$C,$A14)) -> 0 | F14: 0 | G14: =F14+D14-E14 -> 0 | H14: =IF(G14="","",IF(G14>0,"Debit",IF(G14<0,"Credit","Zero"))) -> Zero
A15: =IFERROR(INDEX(TB_COA!$A$5:$A$49,ROW()-3),"") -> 1-3400 | B15: =IF($A15="","",IFERROR(INDEX(TB_COA!$B$5:$B$49,MATCH($A15,TB_COA!$A$5:$A$49,0)),"ACCOUNT NOT FOUND")) -> VAT Recoverable / Input VAT | C15: =IF($A15="","",IFERROR(INDEX(TB_COA!$C$5:$C$49,MATCH($A15,TB_COA!$A$5:$A$49,0)),"ACCOUNT NOT FOUND")) -> Asset | D15: =IF($A15="","",SUMIFS(TB_General_Journal!$E:$E,TB_General_Journal!$C:$C,$A15)) -> 2382593.7 | E15: =IF($A15="","",SUMIFS(TB_General_Journal!$F:$F,TB_General_Journal!$C:$C,$A15)) -> 0 | F15: 0 | G15: =F15+D15-E15 -> 2382593.7 | H15: =IF(G15="","",IF(G15>0,"Debit",IF(G15<0,"Credit","Zero"))) -> Debit
... A48: =IFERROR(INDEX(TB_COA!$A$5:$A$49,ROW()-3),"") -> 7-2000 | B48: =IF($A48="","",IFERROR(INDEX(TB_COA!$B$5:$B$49,MATCH($A48,TB_COA!$A$5:$A$49,0)),"ACCOUNT NOT FOUND")) -> Unrealized FX Gain/Loss | C48: =IF($A48="","",IFERROR(INDEX(TB_COA!$C$5:$C$49,MATCH($A48,TB_COA!$A$5:$A$49,0)),"ACCOUNT NOT FOUND")) -> Expense/Income | D48: =IF($A48="","",SUMIFS(TB_General_Journal!$E:$E,TB_General_Journal!$C:$C,$A48)) -> 0 | E48: =IF($A48="","",SUMIFS(TB_General_Journal!$F:$F,TB_General_Journal!$C:$C,$A48)) -> 0 | F48: 0 | G48: =F48+D48-E48 -> 0 | H48: =IF(G48="","",IF(G48>0,"Debit",IF(G48<0,"Credit","Zero"))) -> Zero
B49: TOTALS | D49: =SUM(D4:D48) -> 81404415 | E49: =SUM(E4:E48) -> 81404415 | F49: =SUM(F4:F48) -> 0 | G49: =SUM(G4:G48) -> 3.2814569e-09 | H49: =IF(ROUND(D49-E49,2)=0,"BALANCED","OUT OF BALANCE") -> BALANCED

Sheet TB_WHT_Quarterly
A1: MODULE: WHT QUARTERLY | M1: 🏠 Back to Home
A2: Withholding tax tracking per supplier invoice for quarterly EAS filing.
A3: WHT_ID | B3: Supplier_ID | C3: Invoice_ID | D3: Hotel_Cost_EGP | E3: WHT_Rate | F3: WHT_Amount_EGP | G3: Quarter | H3: Year | I3: Due_Date | J3: Status | K3: Payment_Ref
A4: WHT-0001 | B4: HTL-001 | C4: AP-0001 | D4: =IFERROR(INDEX(TB_AP_Invoices!$K$4:$K$1000,MATCH(INDEX(TB_Hotel_Accruals!$B$4:$B$1000,MATCH($B4,TB_Hotel_Accruals!$C$4:$C$1000,0)),TB_AP_Invoices!$G$4:$G$1000,0)),INDEX(TB_Hotel_Accruals!$I$4:$I$1000,MATCH($B4,TB_Hotel_Accruals!$C$4:$C$1000,0))/1.14) -> 4717263.2 | E4: 0.03 | F4: =D4*E4 -> 141517.89 | G4: Q3 | H4: 2026 | I4: 2026-10-15 | J4: Accrued | K4: WHT-PAY-Q3-2026
A5: WHT-0002 | B5: HTL-002 | C5: AP-0002 | D5: =IFERROR(INDEX(TB_AP_Invoices!$K$4:$K$1000,MATCH(INDEX(TB_Hotel_Accruals!$B$4:$B$1000,MATCH($B5,TB_Hotel_Accruals!$C$4:$C$1000,0)),TB_AP_Invoices!$G$4:$G$1000,0)),INDEX(TB_Hotel_Accruals!$I$4:$I$1000,MATCH($B5,TB_Hotel_Accruals!$C$4:$C$1000,0))/1.14) -> 882221.05 | E5: 0.03 | F5: =D5*E5 -> 26466.632 | G5: Q3 | H5: 2026 | I5: 2026-10-15 | J5: Accrued | K5: WHT-PAY-Q3-2026
A6: WHT-0003 | B6: HTL-003 | C6: AP-0003 | D6: =IFERROR(INDEX(TB_AP_Invoices!$K$4:$K$1000,MATCH(INDEX(TB_Hotel_Accruals!$B$4:$B$1000,MATCH($B6,TB_Hotel_Accruals!$C$4:$C$1000,0)),TB_AP_Invoices!$G$4:$G$1000,0)),INDEX(TB_Hotel_Accruals!$I$4:$I$1000,MATCH($B6,TB_Hotel_Accruals!$C$4:$C$1000,0))/1.14) -> 711531.58 | E6: 0.03 | F6: =D6*E6 -> 21345.947 | G6: Q3 | H6: 2026 | I6: 2026-10-15 | J6: Accrued | K6: WHT-PAY-Q3-2026
A7: WHT-0004 | B7: HTL-004 | C7: AP-0004 | D7: =IFERROR(INDEX(TB_AP_Invoices!$K$4:$K$1000,MATCH(INDEX(TB_Hotel_Accruals!$B$4:$B$1000,MATCH($B7,TB_Hotel_Accruals!$C$4:$C$1000,0)),TB_AP_Invoices!$G$4:$G$1000,0)),INDEX(TB_Hotel_Accruals!$I$4:$I$1000,MATCH($B7,TB_Hotel_Accruals!$C$4:$C$1000,0))/1.14) -> 809431.58 | E7: 0.03 | F7: =D7*E7 -> 24282.947 | G7: Q3 | H7: 2026 | I7: 2026-10-15 | J7: Accrued | K7: WHT-PAY-Q3-2026
A8: WHT-0005 | B8: HTL-005 | C8: AP-0005 | D8: =IFERROR(INDEX(TB_AP_Invoices!$K$4:$K$1000,MATCH(INDEX(TB_Hotel_Accruals!$B$4:$B$1000,MATCH($B8,TB_Hotel_Accruals!$C$4:$C$1000,0)),TB_AP_Invoices!$G$4:$G$1000,0)),INDEX(TB_Hotel_Accruals!$I$4:$I$1000,MATCH($B8,TB_Hotel_Accruals!$C$4:$C$1000,0))/1.14) -> 108581.05 | E8: 0.03 | F8: =D8*E8 -> 3257.4316 | G8: Q3 | H8: 2026 | I8: 2026-10-15 | J8: Accrued | K8: WHT-PAY-Q3-2026
A9: WHT-0007 | B9: HTL-006 | C9: AP-0001 | D9: =IFERROR(INDEX(TB_AP_Invoices!$K$4:$K$1000,MATCH(INDEX(TB_Hotel_Accruals!$B$4:$B$1000,MATCH($B9,TB_Hotel_Accruals!$C$4:$C$1000,0)),TB_AP_Invoices!$G$4:$G$1000,0)),INDEX(TB_Hotel_Accruals!$I$4:$I$1000,MATCH($B9,TB_Hotel_Accruals!$C$4:$C$1000,0))/1.14) -> 5058666.7 | E9: 0.03 | F9: =D9*E9 -> 151760 | G9: Q3 | H9: 2026 | I9: 2026-10-15 | J9: Accrued | K9: WHT-PAY-Q3-2026
A10: WHT-0008 | B10: HTL-007 | C10: AP-0002 | D10: =IFERROR(INDEX(TB_AP_Invoices!$K$4:$K$1000,MATCH(INDEX(TB_Hotel_Accruals!$B$4:$B$1000,MATCH($B10,TB_Hotel_Accruals!$C$4:$C$1000,0)),TB_AP_Invoices!$G$4:$G$1000,0)),INDEX(TB_Hotel_Accruals!$I$4:$I$1000,MATCH($B10,TB_Hotel_Accruals!$C$4:$C$1000,0))/1.14) -> 835505.26 | E10: 0.03 | F10: =D10*E10 -> 25065.158 | G10: Q3 | H10: 2026 | I10: 2026-10-15 | J10: Accrued | K10: WHT-PAY-Q3-2026
A11: WHT-0009 | B11: HTL-008 | C11: AP-0003 | D11: =IFERROR(INDEX(TB_AP_Invoices!$K$4:$K$1000,MATCH(INDEX(TB_Hotel_Accruals!$B$4:$B$1000,MATCH($B11,TB_Hotel_Accruals!$C$4:$C$1000,0)),TB_AP_Invoices!$G$4:$G$1000,0)),INDEX(TB_Hotel_Accruals!$I$4:$I$1000,MATCH($B11,TB_Hotel_Accruals!$C$4:$C$1000,0))/1.14) -> 965838.6 | E11: 0.03 | F11: =D11*E11 -> 28975.158 | G11: Q3 | H11: 2026 | I11: 2026-10-15 | J11: Accrued | K11: WHT-PAY-Q3-2026
A12: WHT-0010 | B12: HTL-009 | C12: AP-0004 | D12: =IFERROR(INDEX(TB_AP_Invoices!$K$4:$K$1000,MATCH(INDEX(TB_Hotel_Accruals!$B$4:$B$1000,MATCH($B12,TB_Hotel_Accruals!$C$4:$C$1000,0)),TB_AP_Invoices!$G$4:$G$1000,0)),INDEX(TB_Hotel_Accruals!$I$4:$I$1000,MATCH($B12,TB_Hotel_Accruals!$C$4:$C$1000,0))/1.14) -> 1453052.6 | E12: 0.03 | F12: =D12*E12 -> 43591.579 | G12: Q3 | H12: 2026 | I12: 2026-10-15 | J12: Accrued | K12: WHT-PAY-Q3-2026
A13: WHT-0011 | B13: HTL-010 | C13: AP-0005 | D13: =IFERROR(INDEX(TB_AP_Invoices!$K$4:$K$1000,MATCH(INDEX(TB_Hotel_Accruals!$B$4:$B$1000,MATCH($B13,TB_Hotel_Accruals!$C$4:$C$1000,0)),TB_AP_Invoices!$G$4:$G$1000,0)),INDEX(TB_Hotel_Accruals!$I$4:$I$1000,MATCH($B13,TB_Hotel_Accruals!$C$4:$C$1000,0))/1.14) -> 1476435.1 | E13: 0.03 | F13: =D13*E13 -> 44293.053 | G13: Q3 | H13: 2026 | I13: 2026-10-15 | J13: Accrued | K13: WHT-PAY-Q3-2026

Sheet TB_ETA_Integration
A1: MODULE: ETA E-INVOICE INTEGRATION | W1: 🏠 Back to Home
A2: Egyptian Tax Authority e-invoice portal reconciliation records.
A3: ETA_UUID | B3: Internal_Ref | C3: Invoice_Type | D3: Client_ID | E3: Client_Name | F3: Client_VAT_Reg | G3: Invoice_Date | H3: Due_Date | I3: Currency | J3: Amount_FX | K3: CBE_Rate | L3: Amount_EGP | M3: VAT_Amount_EGP | N3: Total_With_VAT_EGP | O3: Submission_Status | P3: ETA_Response_Code | Q3: ETA_Response_Msg | R3: Submitted_By | S3: Submitted_Date | T3: Reconciliation_Status | U3: Notes
A4: ETA-2026-0001 | B4: JV-0001 | C4: Tax Invoice | D4: CLI-001 | E4: Alpine Sun Tours Group | F4: ATU12345678 | G4: 2026-08-08 | H4: 2026-09-07 | I4: EUR | J4: 126000 | K4: 53.35 | L4: 6722100 | M4: 825521.05 | N4: 6722100 | O4: Submitted | P4: 200 | Q4: Accepted | R4: system | S4: 2026-08-08 | T4: Matched | U4: Alpine Sun Tours Group - HRG-2026-0815
A5: ETA-2026-0002 | B5: JV-0004 | C5: Tax Invoice | D5: CLI-002 | E5: Nordic Wave Charter | F5: SE5566778899 | G5: 2026-08-09 | H5: 2026-09-08 | I5: USD | J5: 25830 | K5: 49.12 | L5: 1268769.6 | M5: 155813.81 | N5: 1268769.6 | O5: Submitted | P5: 200 | Q5: Accepted | R5: system | S5: 2026-08-09 | T5: Matched | U5: Nordic Wave Charter - HRG-2026-0816
A6: ETA-2026-0003 | B6: JV-0007 | C6: Tax Invoice | D6: CLI-003 | E6: BritSun Holidays | F6: GB123456789 | G6: 2026-08-10 | H6: 2026-09-09 | I6: GBP | J6: 16380 | K6: 62.3 | L6: 1020474 | M6: 125321.37 | N6: 1020474 | O6: Submitted | P6: 200 | Q6: Accepted | R6: system | S6: 2026-08-10 | T6: Matched | U6: BritSun Holidays - HRG-2026-0817
A7: ETA-2026-0004 | B7: JV-0010 | C7: Tax Invoice | D7: CLI-004 | E7: Meridian Voyages | F7: DE123456789 | G7: 2026-08-07 | H7: 2026-09-06 | I7: EUR | J7: 21600 | K7: 53.4 | L7: 1153440 | M7: 141650.53 | N7: 1153440 | O7: Submitted | P7: 200 | Q7: Accepted | R7: system | S7: 2026-08-07 | T7: Matched | U7: Meridian Voyages - HRG-2026-0818
A8: ETA-2026-0005 | B8: JV-0013 | C8: Tax Invoice | D8: CLI-005 | E8: Red Sea Direct Bookings | G8: 2026-08-09 | H8: 2026-09-08 | I8: USD | J8: 3180 | K8: 49.12 | L8: 156201.6 | M8: 19182.65 | N8: 156201.6 | O8: Pending | R8: system | T8: Pending | U8: Red Sea Direct Bookings - HRG-2026-0819
A9: ETA-2026-0007 | B9: JV-0016 | C9: Tax Invoice | D9: CLI-006 | E9: EuroSun Tours | F9: DE987654321 | G9: 2026-08-22 | H9: 2026-09-21 | I9: EUR | J9: 133000 | K9: 54.2 | L9: 7208600 | M9: 885266.67 | N9: 7208600 | O9: Submitted | P9: 200 | Q9: Accepted | R9: system | S9: 2026-08-22 | T9: Matched | U9: EuroSun Tours - MBR-2026-0001
A10: ETA-2026-0008 | B10: JV-0019 | C10: Tax Invoice | D10: CLI-007 | E10: Nile Breeze | G10: 2026-08-22 | H10: 2026-09-21 | I10: USD | J10: 24150 | K10: 49.3 | L10: 1190595 | M10: 146213.42 | N10: 1190595 | O10: Pending | R10: system | T10: Pending | U10: Nile Breeze - MBR-2026-0002
A11: ETA-2026-0009 | B11: JV-0022 | C11: Tax Invoice | D11: CLI-008 | E11: London Escape | F11: GB987654321 | G11: 2026-08-24 | H11: 2026-09-23 | I11: GBP | J11: 21760 | K11: 63.25 | L11: 1376320 | M11: 169021.75 | N11: 1376320 | O11: Submitted | P11: 200 | Q11: Accepted | R11: system | S11: 2026-08-24 | T11: Matched | U11: London Escape - MBR-2026-0003
A12: ETA-2026-0010 | B12: JV-0025 | C12: Tax Invoice | D12: CLI-009 | E12: Gulf Adventures | F12: AE123456789 | G12: 2026-08-22 | H12: 2026-09-21 | I12: USD | J12: 42000 | K12: 49.3 | L12: 2070600 | M12: 254284.21 | N12: 2070600 | O12: Submitted | P12: 200 | Q12: Accepted | R12: system | S12: 2026-08-22 | T12: Matched | U12: Gulf Adventures - MBR-2026-0004
A13: ETA-2026-0011 | B13: JV-0028 | C13: Tax Invoice | D13: CLI-005 | E13: Red Sea Direct | G13: 2026-08-25 | H13: 2026-09-24 | I13: EUR | J13: 38675 | K13: 54.4 | L13: 2103920 | M13: 258376.14 | N13: 2103920 | O13: Pending | R13: system | T13: Pending | U13: Red Sea Direct - MBR-2026-0005

Sheet TB_Income_Statement
A1: MODULE: INCOME STATEMENT (P&L) | D1: 🏠 Back to Home
A2: Live P&L pulling from TB_Trial_Balance by account class. Recalculates automatically as journal entries change.
A3: Line | B3: Amount_EGP
A4: Revenue (Class 4) | B4: =-SUMIFS(TB_Trial_Balance!$G$4:$G$48,TB_Trial_Balance!$A$4:$A$48,"4-*") -> 21335012
A5: COGS (Class 5) | B5: =SUMIFS(TB_Trial_Balance!$G$4:$G$48,TB_Trial_Balance!$A$4:$A$48,"5-*") -> 17023254
A6: Gross Profit | B6: =B4-B5 -> 4311757.5
A7: Operating Expenses (Class 6) | B7: =SUMIFS(TB_Trial_Balance!$G$4:$G$48,TB_Trial_Balance!$A$4:$A$48,"6-*") -> 50642.45
A8: Operating Profit | B8: =B6-B7 -> 4261115.1
A9: FX Gain / (Loss) (Class 7) | B9: =-SUMIFS(TB_Trial_Balance!$G$4:$G$48,TB_Trial_Balance!$A$4:$A$48,"7-*") -> 54809.3
A10: Net Profit | B10: =B8+B9 -> 4315924.4

Sheet TB_Balance_Sheet
A1: MODULE: BALANCE SHEET | D1: 🏠 Back to Home
A2: Live Balance Sheet pulling from TB_Trial_Balance by account class, plus current-year Retained Earnings from TB_Income_Statement.
A3: Line | B3: Amount_EGP
A4: Total Assets (Class 1) | B4: =SUMIFS(TB_Trial_Balance!$G$4:$G$48,TB_Trial_Balance!$A$4:$A$48,"1-*") -> 7165111.9
A5: Total Liabilities (Class 2) | B5: =-SUMIFS(TB_Trial_Balance!$G$4:$G$48,TB_Trial_Balance!$A$4:$A$48,"2-*") -> 2849187.5
A6: Equity - Share Capital & Reserves (Class 3) | B6: =-SUMIFS(TB_Trial_Balance!$G$4:$G$48,TB_Trial_Balance!$A$4:$A$48,"3-*") -> 0
A7: Retained Earnings - Current Year (from P&L) | B7: =TB_Income_Statement!B10 -> 4315924.4
A8: Total Liabilities + Equity | B8: =B5+B6+B7 -> 7165111.9
A9: Check | B9: =IF(ROUND(B4-B8,2)=0,"BALANCED","OUT OF BALANCE") -> BALANCED
